Workbook

Sheet  Ingredients Library
A1: TS GRANULE LIBRARY FOR AUSTRALIA | D1: CURRENT AT DATE: | E1: 46083 | F1: REVISION No: | G1: 15 | J1: HEADING COLOUR INDICATES COLUMNS HIGHLIGHTED FOR IMPORT and use by Customers
A2: Required for formulation | Q2: Printed on label | R2: Calculation fields for label quantities and price | AB2: Calculation field for total pod weight to print on label | AC2: Fields to guide and limit granule inputs to formulation Data will be updated. Limits compared to COLUMN R Justification in Col DS | AL2: Summary of allergen fields to be printed on label. Final expression TBC | BY2: WARNINGS To be printed on label | BZ2: Excipients to be summarised and printed on label | DT2: Prescription Builder Software Description
A3: TSI Ingredients Library Summary Code | B3: Available (A) / Unavailable (U) Ingredient | C3: Granule Price $AUD/granule | D3: Active Ingredient | E3: Common Name - TSI Global granule name (preferred name) | F3: TSIC Active Code | G3: Scientific Name | H3: Latin Binomial | I3: TGA Approved Name | J3: Plant Part | K3: Preparation Type | L3: Extract Ratio | M3: Extraction Solvents | N3: Standardisation | O3: Potency | P3: TGA Ingredient Expression (For reference only) | Q3: Label Expression (To be printed on box back label) | R3: TGA Label Expression Quantity Line 1 | S3: Unit of Measure Line 1 | T3: TGA Label Expression Quantity Line 2 | U3: Unit of Measure Line 2 | V3: TGA Label Expression Quantity Line 3 | W3: Unit of Measure Line 3 | X3: TGA Label Expression Quantity Line 4 | Y3: Unit of Measure Line 4 | Z3: Questions | AA3: Answers | AB3: Granule Weight (mg) | AC3: Maximum Dose (COPY UNITS FROM Column S) | AD3: Recommended Dose (COPY UNITS FROM Column S) | AE3: Active Ingredient Category | AF3: Regulatory Status1 | AG3: HS Code | AH3: Department of Agriculture, Fisheries and Forestry (DAFF) BICON Case | AI3: Department of Agriculture, Fisheries and Forestry (DAFF) Import Permit | AJ3: Convention on International Trade in Endangered Species (CITES) | AK3: Other Import Requirements | AL3: Declarable Ingredients and Allergens (aspartame) | AM3: Declarable Ingredients and Allergens (benzoates) | AN3: Declarable Ingredients and Allergens (celery) | AO3: Declarable Ingredients and Allergens (crustacean) | AP3: Declarable Ingredients and Allergens (dairy) | AQ3: Declarable Ingredients and Allergens (egg) | AR3: Declarable Ingredients and Allergens (fish) | AS3: Declarable Ingredients and Allergens (gluten) | AT3: Declarable Ingredients and Allergens (hydroxybenzoic acid esters) | AU3: Declarable Ingredients and Allergens (peanut) | AV3: Declarable Ingredients and Allergens (phenylalanine) | AW3: Declarable Ingredients and Allergens (pollen) | AX3: Declarable Ingredients and Allergens (propolis) | AY3: Declarable Ingredients and Allergens (royal jelly) | AZ3: Declarable Ingredients and Allergens (sesame) | BA3: Declarable Ingredients and Allergens (soy) | BB3: Declarable Ingredients and Allergens (sulfites) | BC3: Declarable Ingredients and Allergens (tree nuts) | BD3: Declarable Ingredients and Allergens (potassium) | BE3: Declarable Ingredients and Allergens (potassium quantity) | BF3: Declarable Ingredients and Allergens (potassium unit of measure) | BG3: Declarable Ingredients and Allergens (saccharin) | BH3: Declarable Ingredients and Allergens (sodium) | BI3: Declarable Ingredients and Allergens (sodium quantity) | BJ3: Declarable Ingredients and Allergens (sodium unit of measure) | BK3: Declarable Ingredients and Allergens (sorbates) | BL3: Declarable Ingredients and Allergens (sucralose) | BM3: Declarable Ingredients and Allergens (sugars - all) | BN3: Declarable Ingredients and Allergens (sugars - all quantity) | BO3: Declarable Ingredients and Allergens (sugars - all unit of measure) | BP3: Declarable Ingredients and Allergens (sugars - galactose) | BQ3: Declarable Ingredients and Allergens (sugars - lactose) | BR3: Declarable Ingredients and Allergens (sugar alcohols) | BS3: Declarable Ingredients and Allergens (sugar alcohols quantity) | BT3: Declarable Ingredients and Allergens (sugar alcohols unit of measure) | BU3: Declarable Ingredients and Allergens (tartrazine) | BV3: TGA Ingredient ID | BW3: TGA Restrictions (As stated in TGA Permitted Ingredients Determination and associated regulations) | BX3: TGA Warnings (As stated in TGA Permitted Ingredients Determination and associated regulations) | BY3: Compound Pharmacy Required Label Warnings (To be printed on box back label) | BZ3: Excipient (acacia) | CA3: Excipient (butylated hydroxytoluene) | CB3: Excipient (calcium hydrogen phosphate) | CC3: Excipient (carmellose sodium) | CD3: Excipient (casein) | CE3: Excipient (colloidal anhydrous silica) | CF3: Excipient (croscarmellose sodium) | CG3: Excipient (d-alpha-tocopherol) | CH3: Excipient (dl-alpha-tocopherol) | CI3: Excipient (dioleoylpho (sphatidylcholine) | CJ3: Excipient (ethanol) | CK3: Excipient (ethylcellulose) | CL3: Excipient (vanilla flavour) | CM3: Excipient (gelatin) | CN3: Excipient (glacial acetic acid) | CO3: Excipient (glucose) | CP3: Excipient (glucose monohydrate) | CQ3: Excipient (glycerol) | CR3: Excipient (hydrogenated vegetable oil) | CS3: Excipient (hyprolose) | CT3: Excipient (hypromellose) | CU3: Excipient (isomalt) | CV3: Excipient (isomaltooligosaccharides) | CW3: Excipient (lecithin) | CX3: Excipient (magnesium stearate) | CY3: Excipient (maize starch) | CZ3: Excipient (maltodextrin) | DA3: Excipient (medium chain triglycerides) | DB3: Excipient (microcrystalline cellulose) | DC3: Excipient (mixed carotenoids) | DD3: Excipient (pea starch) | DE3: Excipient (phytosterol complex) | DF3: Excipient (poliglusam) | DG3: Excipient (pregelatinised starch) | DH3: Excipient (silicon dioxide) | DI3: Excipient (sodium alginate) | DJ3: Excipient (sodium caseinate) | DK3: Excipient (sodium starch glycollate) | DL3: Excipient (sodium stearyl lactate) | DM3: Excipient (squalene) | DN3: Excipient (sucrose) | DO3: Excipient (tapioca starch) | DP3: Excipient (tocopherol) | DQ3: Non-GMO | DR3: Halal Suitable (NOT Certified) | DS3: Comments - including Nof1 Max Dose Justification from 17/2/2026 | DT3: Prescribing Software Description: To appear as separate lines in the Practitioner formulation website page | DU3: TGA Required Label Warnings NOT to be printed - see Column BY for printed label warning requirements for Pharmacy
A4: 31P0017 | B4: A | C4: 0.12 | E4: Aluminium Cup | AH4: n/a | AI4: n/a | AJ4: n/a | AK4: No
A5: 31M0133 | B5: A | C5: 0.02 | E5: Black Foil Lid Custom | AH5: n/a | AI5: n/a | AJ5: n/a | AK5: No
A6: W010001000 | B6: A | C6: 0.0096 | D6: Ginseng (Panax quinquefolius) extract (root) (standardized to 9% ginsenosides) | E6: American ginseng | F6: A2716 | G6: Panax quinquefolius | H6: Panax quinquefolius | I6: Panax quinquefolius | J6: root | K6: extract dry concentrate standardised | L6: 4:1 | M6: 60% ethanol:water | N6: 9% ginsenosides | O6: - | P6: Panax quinquefolius root ext. dry conc. std. 4:1 (60:40 E:W) Equiv. Panax quinquefolius dry root Equiv. Ginsenosides 9% contains maltodextrin 20% | Q6: Panax quinquefolius (American ginseng) root extract equivalent Panax quinquefolius dry root equivalent ginsenosides | R6: 10 | S6: mg | T6: 40 | U6: mg | V6: 0.9 | W6: mg | Z6: - | AB6: 18.8102 | AC6: 1000 | AD6: 400 | AE6: Herb | AF6: Export Only, Listed, OTC, Prescription | AG6: 1302.19.90 | AH6: Highly refined organic chemicals and substances | AI6: Not required | AJ6: Not included in any CITES Appendix | AK6: No | AP6: dairy | BA6: soy | BB6: sulfites | BH6: sodium | BI6: 0.1 | BJ6: mg | BM6: sugars | BN6: 0.031 | BO6: mg | BV6: 108215 | BW6: No restrictions. | BX6: No warnings. | BY6: No warnings. | CC6: carmellose sodium | CE6: colloidal anhydrous silica | CL6: vanilla flavour | CP6: glucose monohydrate | CQ6: glycerol | CT6: hypromellose | CW6: lecithin | CX6: magnesium stearate | CZ6: maltodextrin | DB6: microcrystalline cellulose | DQ6: Yes | DR6: Yes | DS6: TR 1-3 g/day dried herb equivalent https://pubmed.ncbi.nlm.nih.gov/10761967/ happy with this TR 400 - 750 mg of a 4:1 extract | DT6: Panax quinquefolius (American ginseng) root extract (4:1) equivalent Panax quinquefolius dry root equivalent ginsenosides (9%) | DU6: No warnings.
A7: W010003000 | B7: A | C7: 0.0122 | D7: Ashwagandha (Withania somnifera) extract (root) (standardised to 2.5% withanolides) | E7: Ashwagandha | F7: A730 | G7: Withania somnifera | H7: Withania somnifera | I7: Withania somnifera | J7: root | K7: extract dry concentrate standardised | L7: 10-15:1 | M7: 80% ethanol:water | N7: 2.5% withanolides | O7: - | P7: Withania somnifera (Ashwagandha) root ex dry conc std (10:1, 80% E/W) Equiv. Withania somnifera root dry Equiv. Withanolides (2.5%) | Q7: Withania somnifera (Ashwagandha) root extract equivalent Withania somnifera dry root equivalent withanolides | R7: 10 | S7: mg | T7: 100 | U7: mg | V7: 0.25 | W7: mg | Z7: Please confirm the name and quantity of any excipients present? | AA7: NMT 5% maltodextrin | AB7: 19.4702 | AC7: 800 | AD7: 300 | AE7: Herb | AF7: Export Only, Listed, OTC, Prescription | AG7: 1302.19.90 | AH7: Highly refined organic chemicals and substances | AI7: Not required | AJ7: Not included in any CITES Appendix | AK7: No | AP7: dairy | BA7: soy | BB7: sulfites | BH7: sodium | BI7: 0.11 | BJ7: mg | BM7: sugars | BN7: 0.035 | BO7: mg | BV7: 84964 | BW7: No restrictions. | BX7: The medicine requires the following warning statement on the label:- (WITHANIA) 'If you are pregnant, or considering becoming pregnant, do not take without consulting a health professional' (or words to that effect) unless: (a) the plant part is root; (b) the plant preparation is an extract; (c) the extraction solvents are only water, ethanol or methanol; and (d) the maximum recommended daily dose of the medicine contains no more than the equivalent quantity of 12 g dry root | BY7: No warnings. | CC7: carmellose sodium | CE7: colloidal anhydrous silica | CJ7: ethanol | CL7: vanilla flavour | CN7: glacial acetic acid | CP7: glucose monohydrate | CW7: lecithin | CX7: magnesium stearate | CZ7: maltodextrin | DB7: microcrystalline cellulose | DF7: poliglusam | DQ7: Yes | DR7: Yes | DS7: Therapeutic range 3-6 gm daily MT TR 300mg - 600 mg of a 10:1 extract UL https://www.researchgate.net/publication/232814045_Exploratory_study_to_evaluate_tolerability_safety_and_activity_of_Ashwagandha_Withania_somnifera_in_healthy_volunteers 1250 mg, 8:1 =10000 mg. Divided so brought down UL slightly. ML - Based on 10:1 extract and traditional use equivalent to 5g dry root in a single serve. Typically used at 3-10g per day | DT7: Withania somnifera (Ashwagandha) root extract (10:1) equivalent Withania somnifera dry root equivalent withanolides (2.5%) | DU7: No warnings.
A8: W010004000 | B8: A | C8: 0.0022 | D8: Astragalus (Astragalus membranaceus) (root) extract | E8: Astragalus | F8: A355 | G8: Astragalus membranaceus | H8: Astragalus membranaceus | I8: Astragalus membranaceus | J8: root | K8: extract dry concentrate | L8: 20:1 | M8: 80% ethanol:water | N8: - | O8: - | P8: Astragalus membranaceus Root Ext Dry Conc (20:1 in 80% E:W) Equiv. dry root | Q8: Astragalus membranaceus (Astragalus) root extract equivalent Astragalus membranaceus dry root | R8: 10 | S8: mg | T8: 200 | U8: mg | Z8: - | AB8: 17.8102 | AC8: 1500 | AD8: 150 | AE8: Herb | AF8: Export Only, Listed, OTC, Prescription | AG8: 1302.19.90 | AH8: Highly refined organic chemicals and substances | AI8: Not required | AJ8: Not included in any CITES Appendix | AK8: No | AP8: dairy | BA8: soy | BB8: sulfites | BH8: sodium | BI8: 0.11 | BJ8: mg | BM8: sugars | BN8: 0.035 | BO8: mg | BR8: sugar alcohols | BS8: 14.6 | BT8: mg | BV8: 68522 | BW8: No restrictions. | BX8: No warnings. | BY8: No warnings. | CC8: carmellose sodium | CE8: colloidal anhydrous silica | CL8: vanilla flavour | CP8: glucose monohydrate | CQ8: glycerol | CT8: hypromellose | CU8: isomalt | CW8: lecithin | CX8: magnesium stearate | DB8: microcrystalline cellulose | DQ8: Yes | DR8: Yes | DS8: Therapeutic range 6-15 gm daily MT: 2-30 gm daily Braun and Cohen TR 150 mg - 900 mg of a 20:1 extract TR between MT & BC UL at BC top range | DT8: Astragalus membranaceus (Astragalus) root extract (20:1) equivalent Astragalus membranaceus dry root | DU8: No warnings.
A9: W010006000 | B9: A | C9: 0.0051 | D9: Eleuthero (Eleutherococcus senticosus) extract (root) (standardized to 0.8% eleutherosides) | E9: Siberian ginseng | F9: A2707 | G9: Eleutherococcus senticosus | H9: Eleutherococcus senticosus | I9: Eleutherococcus senticosus | J9: root | K9: extract dry concentrate standardised | L9: 15:1 | M9: 70% ethanol:water | N9: 0.8% eleutherosides | O9: - | P9: Eleutherococcus senticosus (Siberian ginseng) root ext dry conc std 15:1, 70% E/W Equiv. Eleutherococcus senticosus root dry Equiv. Eleutherosides (0.8%) | Q9: Eleutherococcus senticosus (Siberian ginseng) root extract equivalent Eleutherococcus senticosus dry root equivalent eleutherosides | R9: 10 | S9: mg | T9: 150 | U9: mg | V9: 0.8 | W9: mg | Z9: Please confirm the name and quantity of any excipients present? | AA9: 3% maltodextrin | AB9: 19.6902 | AC9: 500 | AD9: 500 | AE9: Herb | AF9: Export Only, Listed, OTC, Prescription | AG9: 1302.19.90 | AH9: Highly refined organic chemicals and substances | AI9: Not required | AJ9: Not included in any CITES Appendix | AK9: No | AP9: dairy | BA9: soy | BB9: sulfites | BH9: sodium | BI9: 0.1 | BJ9: mg | BM9: sugars | BN9: 0.033 | BO9: mg | BR9: sugar alcohols | BS9: 1.2 | BT9: mg | BV9: 60079 | BW9: No restrictions. | BX9: No warnings. | BY9: No warnings. | CC9: carmellose sodium | CE9: colloidal anhydrous silica | CL9: vanilla flavour | CP9: glucose monohydrate | CQ9: glycerol | CT9: hypromellose | CU9: isomalt | CW9: lecithin | CX9: magnesium stearate | CZ9: maltodextrin | DB9: microcrystalline cellulose | DQ9: Yes | DR9: Yes | DS9: Therapeutic range 3-4 gm daily MT TR 1-4 gm day BC TR 70 mg to 270 mg of a 15:1 extract 9BC reference range, UL reflects traditional dosing) | DT9: Eleutherococcus senticosus (Siberian ginseng) root extract (15:1) equivalent Eleutherococcus senticosus dry root equivalent eleutherosides (0.8%) | DU9: No warnings.
A10: W010007000 | B10: A | C10: 0.0038 | D10: Epigallocatechin gallate (EGCG) (Camellia sinensis) (standardized to 95% polyphenols) | E10: Green Tea (EGCG) | F10: A2486 | G10: Camellia sinensis | H10: Camellia sinensis | I10: Camellia sinensis | J10: leaf | K10: extract dry concentrate standardised | L10: 15:1 | M10: 50% ethanol:water | N10: 98% polyphenols 50% EGCG 1% caffeine | O10: - | P10: Camellia sinensis (Green tea) leaf ext dry conc std (15:1, 50% E/W) Equiv. Camellia sinensis leaf dry Equiv. EGCG (50%) Equiv. Caffeine (1%) | Q10: Camellia sinensis (Green tea) leaf extract equivalent Camellia sinensis dry leaf equivalent EGCG equivalent caffeine | R10: 10 | S10: mg | T10: 150 | U10: mg | V10: 5 | W10: mg | X10: 0.1 | Y10: mg | Z10: Please confirm the caffeine content, and the name and quantity of any excipients present? | AA10: NMT1% caffeine No excipients | AB10: 19.4502 | AC10: 1500 | AD10: 150 | AE10: Herb | AF10: Export Only, Listed, OTC, Prescription | AG10: 1302.19.90 | AH10: Highly refined organic chemicals and substances | AI10: Not required | AJ10: Not included in any CITES Appendix | AK10: No | AP10: dairy | BA10: soy | BB10: sulfites | BH10: sodium | BI10: 0.1 | BJ10: mg | BM10: sugars | BN10: 0.033 | BO10: mg | BV10: 94990 | BW10: Caffeine is a mandatory component of Camellia sinensis. When the medicine is packaged for supply as a divided preparation and is for internal use or oral application, the medicine must not contain a concentration of total caffeine greater than 33%. When for internal use or oral application, the maximum recommended daily dose of the medicine must provide no more than 400 mg of total caffeine. When the medicine is packaged for supply as an undivided preparation and is for internal use or oral application, the medicine must not contain a concentration of total caffeine greater than 1%. When the medicine is for internal use or oral application, a maximum recommended dose of the medicine must not provide more than 100 mg of total caffeine within a 3 hour period. | BX10: When the maximum recommended daily dose of the medicine provides greater than 10 mg of total caffeine and the medicine is for internal use or oral application, the following warning statements are required on the label: - (ADULT) 'Adults only' (or words to that effect). - (CAFF) 'Contains [state quantity per dosage unit or per mL or per gram of product] total caffeine [per dosage unit or per mL or per gram]. A cup of instant coffee contains approximately 80mg of caffeine.' - (CAFFPREG) ‘Caffeine intake more than 200 mg per day is not recommended during pregnancy or breastfeeding.’ When the maximum recommended daily dose of the medicine provides greater than 80 mg of total caffeine and the medicines is for internal use or oral application, the following warning statements are required on the label: - (CAFFLMT) 'Limit the use of caffeine-containing products (including tea and coffee) when taking this product.' - (CAFFCYP) ‘Caffeine interacts with enzyme CYP1A2 in the liver. Consult your health professional before taking with other medicines’ (or words to that effect). When used in oral medicines, the following warning statements are required on the medicine label: - 'In rare cases, Camellia sinensis may harm the liver. Stop use and see a doctor if you have yellowing skin/eyes, or unusual: fatigue, nausea, appetite loss, abdominal pain, dark urine, or itching.'; and - (FOOD) ‘To be taken with food.’ unless when: (a) the preparation of Camellia sinensis is derived from an aqueous extract and contains 300 mg or less epigallocatechin-3-gallate per maximum recommended daily dose; or (b) Camellia sinensis is used in combination with other permitted ingredients as a flavour proprietary excipient formulation. The total concentration of flavour proprietary excipient formulations containing Camellia sinensis must not be more than 5% of the total medicine. | BY10: When the maximum recommended daily dose provides greater than 10 mg of total caffeine, the following warning statements are required: "Contains caffeine. Not recommended for children or pregnant/lactating women. Contains [amount of caffeine in milligrams] mg of caffeine." | CC10: carmellose sodium | CE10: colloidal anhydrous silica | CL10: vanilla flavour | CN10: glacial acetic acid | CP10: glucose monohydrate | CW10: lecithin | CX10: magnesium stearate | DB10: microcrystalline cellulose | DF10: poliglusam | DQ10: Yes | DR10: Yes | DS10: Therapeutic range 1.5 - 3 gm daily MT toxicity of EGCG at >800 mg daily. TR should read 100-200 mg of a 15:1 extract UL 1500 mg of extract | DT10: Camellia sinensis (Green tea) leaf extract (15:1) equivalent Camellia sinensis dry leaf equivalent EGCG (50%) equivalent caffeine (1%) | DU10: "Contains [state quantity per dosage unit or per mL or per gram] total caffeine [per dosage unit or per mL or per gram]. A cup of instant coffee contains approximately 80mg of caffeine." "Caffeine intake more than 200 mg per day is not recommended for use by pregnant and lactating women." "Limit the use of caffeine containing products (including tea and coffee) when taking this product.." "Caffeine interacts with enzyme CYP1A2 in the liver. Consult a health professional before taking with other medicines." "In rare cases, Camellia sinensis may harm the liver." "Stop use and consult a healthcare professional if you have yellowing skin/eyes or unusual fatigue, nausea, appetite loss, abdominal pain, dark urine, or itching." "To be taken with food."
A11: W010008000 | B11: A | C11: 0.0051 | D11: Garlic (Allium sativum) extract (bulb) (20:1) | E11: Garlic | F11: A153 | G11: Allium sativum | H11: Allium sativum | I11: Allium sativum | J11: bulb | K11: extract dry concentrate | L11: 20:1 | M11: 75% ethanol:water | N11: - | O11: - | P11: Allium sativum (Garlic) bulb ext dry conc (20:1, 75% E/W) Equiv. Allium sativum bulb dry | Q11: Allium sativum (Garlic) bulb extract equivalent Allium sativum dry bulb | R11: 10 | S11: mg | T11: 200 | U11: mg | Z11: Please confirm the name and quantity of any excipients present? | AA11: No excipients | AB11: 19.8102 | AC11: 200 | AD11: 50 | AE11: Herb | AF11: Export Only, Listed, OTC, Prescription | AG11: 1302.19.90 | AH11: Highly refined organic chemicals and substances | AI11: Not required | AJ11: Not included in any CITES Appendix | AK11: No | AP11: dairy | BA11: soy | BB11: sulfites | BH11: sodium | BI11: 0.11 | BJ11: mg | BM11: sugars | BN11: 0.035 | BO11: mg | BV11: 59168 | BW11: No restrictions. | BX11: No warnings. | BY11: No warnings. | CC11: carmellose sodium | CE11: colloidal anhydrous silica | CJ11: ethanol | CL11: vanilla flavour | CP11: glucose monohydrate | CQ11: glycerol | CT11: hypromellose | CW11: lecithin | CX11: magnesium stearate | DB11: microcrystalline cellulose | DQ11: Yes | DR11: Yes | DS11: Therapeutic range TR 300 - 1500 mg/day BC TR 10mg - 80mg of 20:1 extract UL https://pubmed.ncbi.nlm.nih.gov/17325296/ | DT11: Allium sativum (Garlic) bulb extract (20:1) equivalent Allium sativum dry bulb | DU11: No warnings.
A12: W010009000 | B12: A | C12: 0.0035 | D12: Grape (Vitis vinifera) extract (seed) (standardized to 92-95% proanthocyanidins) | E12: Grape Seed | F12: A461 | G12: Vitis vinifera | H12: Vitis vinifera | I12: Vitis vinifera | J12: seed | K12: extract dry concentrate standardised | L12: 120:1 | M12: 70% ethanol:water | N12: 92-95% proanthocyanidins | O12: - | P12: Vitis vinifera seed dry ext conc std. (120:1 in 70:30 E:W) Equiv. Vitis vinifera seed dry Equiv. proanthocyanodins (92%) | Q12: Vitis vinifera (Grape) seed extract equivalent Vitis vinifera dry seed equivalent proanthocyanidins | R12: 10 | S12: mg | T12: 1200 | U12: mg | V12: 9.2 | W12: mg | Z12: - | AB12: 18.9802 | AC12: 600 | AD12: 200 | AE12: Herb | AF12: Export Only, Listed, OTC, Prescription | AG12: 1302.19.90 | AH12: Highly refined organic chemicals and substances | AI12: Not required | AJ12: Not included in any CITES Appendix | AK12: No | AP12: dairy | BA12: soy | BB12: sulfites | BH12: sodium | BI12: 0.2 | BJ12: mg | BM12: sugars | BN12: 0.033 | BO12: mg | BR12: sugar alcohols | BS12: 3.7 | BT12: mg | BV12: 83764 | BW12: No restrictions. | BX12: No warnings. | BY12: No warnings. | CC12: carmellose sodium | CE12: colloidal anhydrous silica | CL12: vanilla flavour | CP12: glucose monohydrate | CQ12: glycerol | CS12: hyprolose | CT12: hypromellose | CU12: isomalt | CW12: lecithin | CX12: magnesium stearate | DB12: microcrystalline cellulose | DQ12: Yes | DR12: Yes | DS12: TR 150- 400 mg daily BC (extract, need to check the ratio) cites endotelon need to confirm the ratio TR 150 - 400 mg of a 120:1 Matt confirmed | DT12: Vitis vinifera (Grape) seed extract equivalent Vitis vinifera dry seed equivalent proanthocyanidins (92%) | DU12: No warnings.
A13: W010011000 | B13: A | C13: 0.0083 | D13: Lutein | E13: Lutein | F13: A378 | G13: Lutein | H13: Tagetes erecta | I13: Tagetes erecta | J13: flower | K13: extract dry concentrate standardised | L13: 7:1 | M13: 100% hexane | N13: 7.5% lutein | O13: - | P13: Tagetes Erecta L. Flower Ext. Dry Conc. Std. (7:1 in 100% Hexane) Equiv. Tagetes erecta flower dry Equiv. Lutein (7.5%) Excipient: Maltodextrin 5% | Q13: Tagetes erecta (Aztec marigold) flower extract equivalent Tagetes erecta dry flower equivalent lutein | R13: 6.67 | S13: mg | T13: 46.7 | U13: mg | V13: 0.5 | W13: mg | Z13: - | AB13: 18.4612 | AC13: 540 | AD13: 20 | AE13: Herb | AF13: Export Only, Listed, OTC, Prescription | AG13: 2106.90.99 or 1302.19.90 | AH13: Highly refined organic chemicals and substances | AI13: Not required | AJ13: Not included in any CITES Appendix | AK13: No | AP13: dairy | BA13: soy | BB13: sulfites | BH13: sodium | BI13: 0.1 | BJ13: mg | BM13: sugars | BN13: 0.031 | BO13: mg | BV13: 84203 | BW13: No restrictions. | BX13: No warnings. | BY13: No warnings. | CC13: carmellose sodium | CE13: colloidal anhydrous silica | CL13: vanilla flavour | CP13: glucose monohydrate | CQ13: glycerol | CT13: hypromellose | CW13: lecithin | CX13: magnesium stearate | CZ13: maltodextrin | DB13: microcrystalline cellulose | DQ13: Yes | DR13: Yes | DS13: TR 80-270 mg mg/day of a 7:1 extract (gives 6-20 mg of lutein) reference BC | DT13: Tagetes erecta (Aztec marigold) flower extract equivalent Tagetes erecta dry flower equivalent lutein (7.5%) | DU13: No warnings.
A14: W010012000 | B14: A | C14: 0.0093 | D14: Zeaxanthin | E14: Zeaxanthin | F14: A379 | G14: Zeaxanthin | H14: - | I14: Zeaxanthin | J14: - | K14: - | L14: - | M14: - | N14: - | O14: 20% zeaxanthin | P14: Zeaxanthin Equiv. Zeaxanthin 20% Excipients: Maltodextrin 30% | Q14: Zeaxanthin | R14: 1 | S14: mg | Z14: - | AB14: 19.4902 | AC14: 10 | AD14: 2 | AE14: Vitamin | AF14: Export Only, Listed, OTC, Prescription | AG14: 2106.90.99 | AH14: Highly refined organic chemicals and substances | AI14: Not required | AJ14: Not included in any CITES Appendix | AK14: No | AP14: dairy | BA14: soy | BB14: sulfites | BH14: sodium | BI14: 0.1 | BJ14: mg | BM14: sugars | BN14: 0.033 | BO14: mg | BV14: 100386 | BW14: No restrictions. | BX14: No warnings. | BY14: No warnings. | CC14: carmellose sodium | CE14: colloidal anhydrous silica | CL14: vanilla flavour | CP14: glucose monohydrate | CQ14: glycerol | CT14: hypromellose | CW14: lecithin | CX14: magnesium stearate | CZ14: maltodextrin | DB14: microcrystalline cellulose | DQ14: Yes | DR14: Yes | DS14: TR 2-5 mg/day (BC, says 2-5 well tolerated) | DT14: Zeaxanthin | DU14: No warnings.
A15: W010013000 | B15: A | C15: 0.0048 | D15: Milk thistle (Silybum marianum) extract (standardized to 80% silymarin) | E15: Milk thistle | F15: A752 | G15: Silybum marianum | H15: Silybum marianum | I15: Silybum marianum | J15: fruit | K15: extract dry concentrate standardised | L15: 70:1 | M15: 95% ethyl acetate:water | N15: 80% silybin | O15: - | P15: Silybum marianum fruit dry ext conc std 70:1 (95:5 Ethyl acetate:water) Equiv. Silybum marianum fruit dry Equiv. silymarin 80% | Q15: Silybum marianum (Milk thistle) fruit extract equivalent Silybum marianum dry fruit equivalent silymarin | R15: 10 | S15: mg | T15: 700 | U15: mg | V15: 8 | W15: mg | Z15: - | AB15: 19.81 | AC15: 450 | AD15: 150 | AE15: Herb | AF15: Export Only, Listed, OTC, Prescription | AG15: 1302.19.90 | AH15: Highly refined organic chemicals and substances | AI15: Not required | AJ15: Not included in any CITES Appendix | AK15: No | AP15: dairy | BA15: soy | BB15: sulfites | BH15: sodium | BI15: 0.11 | BJ15: mg | BM15: sugars | BN15: 0.035 | BO15: mg | BR15: sugar alcohols | BS15: 4 | BT15: mg | BV15: 62088 | BW15: No restrictions. | BX15: No warnings. | BY15: No warnings. | CC15: carmellose sodium | CJ15: ethanol | CL15: vanilla flavour | CP15: glucose monohydrate | CQ15: glycerol | CT15: hypromellose | CU15: isomalt | CW15: lecithin | CX15: magnesium stearate | DB15: microcrystalline cellulose | DG15: pregelatinised starch | DQ15: Yes | DR15: Yes | DS15: Therapeutic range 6-12 gm daily MT - 200 mg of extract 100 - 170 mg of a 70:1 extract YSCP confirmed 450mg daily is fine. Clinical trials go up to 1500mg in clinical studies. https://link.springer.com/article/10.1186/s12906-025-04886-y | DT15: Silybum marianum (Milk thistle) fruit extract (70:1) equivalent Silybum marianum dry fruit equivalent silymarin (80%) | DU15: No warnings.
A16: W010017000 | B16: A | C16: 0.0029 | D16: Pine (Pinus massoniana) extract (bark) (standardized to 60-70% procyanidins) | E16: Pine Bark (Pycnogenol) | F16: A2768 | G16: Pinus massoniana | H16: Pinus massoniana | I16: Pinus massoniana | J16: bark | K16: extract dry concentrate standardised | L16: 50:1 | M16: 70% ethanol:water | N16: 60-70% procyanidins | O16: - | P16: Pinus massoniana bark extract dry conc std 50:1 (70:30 E:W) Equiv. Pinus massoniana bark dry Equiv. procyanodins 60-70% Excipient: Maltodextrin 15% | Q16: Pinus massoniana (Pine) bark extract equivalent Pinus massoniana dry bark equivalent procyanidins | R16: 7.15 | S16: mg | T16: 357.5 | U16: mg | V16: 4.3 | W16: mg | Z16: - | AB16: 17.4402 | AC16: 360 | AD16: 100 | AE16: Herb | AF16: Export Only, Listed, OTC, Prescription | AG16: 1302.19.90 | AH16: Highly refined organic chemicals and substances | AI16: Not required | AJ16: Not included in any CITES Appendix | AK16: No | AP16: dairy | BA16: soy | BB16: sulfites | BH16: sodium | BI16: 0.09 | BJ16: mg | BM16: sugars | BN16: 0.03 | BO16: mg | BV16: 85330 | BW16: When the plant preparation is oil or distillate the total concentration of Pinus massoniana oil or distillate in the preparation must be no more than 25%. | BX16: No warnings. | BY16: No warnings. | CC16: carmellose sodium | CE16: colloidal anhydrous silica | CL16: vanilla flavour | CP16: glucose monohydrate | CQ16: glycerol | CT16: hypromellose | CW16: lecithin | CX16: magnesium stearate | CZ16: maltodextrin | DB16: microcrystalline cellulose | DG16: pregelatinised starch | DQ16: Yes | DR16: Yes | DS16: TR 50-300 mg https://pubmed.ncbi.nlm.nih.gov/11081989/, TR 100-300 mg of a 50:1 extract ' equiv to 60 -240 mg of procyanidins UL 360 mg/day = extrapolated within safety margins, not standard RCT dose | DT16: Pinus massoniana (Pine) bark extract (50:1) equivalent Pinus massoniana dry bark equivalent procyanidins (60%) | DU16: No warnings.
A17: W010018000 | B17: A | C17: 0.0045 | D17: Pomegranate (Punica granatum) extract (hull) (standardized to 40% ellagic acid) | E17: Pomegranate | F17: A2365 | G17: Punica granatum | H17: Punica granatum | I17: Punica granatum | J17: hull | K17: extract dry concentrate standardised | L17: 18:1 | M17: 50% ethanol:water | N17: 40% ellagic acid | O17: - | P17: Punica granatum hull dry ext conc Std, 18:1, (50% EtOH: water) Equiv. Punica granatum hull dry Equiv. ellagic acid (40%) | Q17: Punica granatum (Pomegranate) hull extract equivalent Punica granatum dry hull equivalent ellagic acid | R17: 10 | S17: mg | T17: 180 | U17: mg | V17: 4 | W17: mg | Z17: - | AB17: 18.8102 | AC17: 1000 | AD17: 250 | AE17: Herb | AF17: Export Only, Listed, OTC, Prescription | AG17: 1302.19.90 | AH17: Highly refined organic chemicals and substances | AI17: Not required | AJ17: Not included in any CITES Appendix | AK17: No | AP17: dairy | BA17: soy | BB17: sulfites | BH17: sodium | BI17: 0.11 | BJ17: mg | BM17: sugars | BN17: 0.035 | BO17: mg | BV17: 93464 | BW17: No restrictions. | BX17: No warnings. | BY17: No warnings. | CC17: carmellose sodium | CE17: colloidal anhydrous silica | CJ17: ethanol | CL17: vanilla flavour | CP17: glucose monohydrate | CQ17: glycerol | CT17: hypromellose | CW17: lecithin | CX17: magnesium stearate | DB17: microcrystalline cellulose | DQ17: Yes | DR17: Yes | DS17: TR 50-750 gm of an 18:1 extract daily UL Fuster‑Márquez M, et al. Effects of pomegranate extract supplementation on metabolic and inflammatory markers. Nutrients. 2021. | DT17: Punica granatum (Pomegranate) hull extract (18:1) equivalent Punica granatum dry hull equivalent ellagic acid (40%) | DU17: No warnings.
A18: W010019000 | B18: A | C18: 0.0144 | D18: Trans-resveratrol | E18: Resveratrol | F18: A2143 | G18: Resveratrol | H18: - | I18: Resveratrol | J18: - | K18: - | L18: - | M18: - | N18: - | O18: 98% resveratrol | P18: Resveratrol (98%) | Q18: Resveratrol | R18: 10 | S18: mg | Z18: - | AB18: 18.4602 | AC18: 1500 | AD18: 150 | AE18: Synthetic | AF18: Export Only, Listed | AG18: 1302.19.90 | AH18: Highly refined organic chemicals and substances | AI18: Not required | AJ18: Not included in any CITES Appendix | AK18: No | AP18: dairy | BA18: soy | BB18: sulfites | BH18: sodium | BI18: 0.1 | BJ18: mg | BM18: sugars | BN18: 0.031 | BO18: mg | BR18: sugar alcohols | BS18: 2.58 | BT18: mg | BV18: 111032 | BW18: The maximum recommended daily dose of the medicine must not contain more than 150 milligrams of resveratrol. | BX18: The following warning statements are required on the medicine label: - (RESVER) 'Resveratrol may affect the way some medicines work, including Warfarin. Consult your health professional before taking with other medicines (or words to that effect).';- (PREGNT) ‘Not recommended for use by pregnant and lactating women’ (or words to that effect)’; and- (CHILD2) ‘Not suitable for children’. | BY18: No warnings. | CC18: carmellose sodium | CE18: colloidal anhydrous silica | CL18: vanilla flavour | CP18: glucose monohydrate | CQ18: glycerol | CT18: hypromellose | CU18: isomalt | CW18: lecithin | CX18: magnesium stearate | DB18: microcrystalline cellulose | DQ18: Yes | DR18: Yes | DS18: TR 150-500 mg daily common dosage, higher doses at 2 gm daily TR 150 -1000 mg daily, UL 5gm https://www.mdpi.com/1422-0067/25/2/747?utm YSCP confirmed 600mg Therapeutic Clinical use (most effective) (Chen S et al. 2015). 1000mg Aggressive Metabolic use. (Brown VA et al. 2010 (Cancer Research)1000mg to 1500mg Upper tolerable long-term. | DT18: Resveratrol | DU18: "Resveratrol may affect the way some medicines work, including warfarin. Consult a health professional before taking with other medicines." "Not recommended for use by pregnant and lactating women."
A19: W010020000 | B19: A | C19: 0.0122 | D19: Rhodiola (Rhodiola rosea) extract (root) (standardized to 3% rosavins and 1% salidroside) | E19: Rhodiola rosea (Rose Root) | F19: A790 | G19: Rhodiola rosea | H19: Rhodiola rosea | I19: Rhodiola rosea | J19: root | K19: extract dry concentrate standardised | L19: 10:1 | M19: 70% ethanol:water | N19: 3% rosavins, 1% salidroside | O19: - | P19: Rhodiola rosea (Rose root) root ext dry conc std (10:1, 70% E/W) Equiv. Rhodiola rosea root dry Equiv. Rosavins (3%) Equiv. Salidroside (1%) | Q19: Rhodiola rosea (Rose root) root extract equivalent Rhodiola rosea dry root equivalent rosavins equivalent salidroside | R19: 10 | S19: mg | T19: 100 | U19: mg | V19: 0.3 | W19: mg | X19: 0.1 | Y19: mg | Z19: Please confirm the name and quantity of any excipients present? | AA19: No excipients | AB19: 18.6702 | AC19: 600 | AD19: 200 | AE19: Herb | AF19: Export Only, Listed, OTC, Prescription | AG19: 1302.19.90 | AH19: Highly refined organic chemicals and substances | AI19: Not required | AJ19: CITES Appendix II | AK19: Department of Climate Change, Energy, the Environment and Water - Wildlife trade permit required for Raw Material only, not formulated products | AP19: dairy | BA19: soy | BB19: sulfites | BH19: sodium | BI19: 0.11 | BJ19: mg | BM19: sugars | BN19: 0.035 | BO19: mg | BR19: sugar alcohols | BS19: 1.2 | BT19: mg | BV19: 104774 | BW19: Only for use in oral medicines. Only available for use when the plant preparation is dry root powder, dry root powder as an aqueous extract or dry root powder as a hydroethanolic extract with no more than 70% ethanol v/v. | BX19: No warnings. | BY19: No warnings. | CC19: carmellose sodium | CE19: colloidal anhydrous silica | CL19: vanilla flavour | CN19: glacial acetic acid | CP19: glucose monohydrate | CU19: isomalt | CW19: lecithin | CX19: magnesium stearate | DB19: microcrystalline cellulose | DF19: poliglusam | DQ19: Yes | DR19: Yes | DS19: Therapeutic range 1-2 gm daily (MT) Research at 600 mg of Rhodiola extract in depression (HWT (6,000 mg) TR 200-400 mg daily of a 10:1 extract UL 680 MG Clinical trial of Rhodiola rosea L. extract SHR-5 in the treatment of mild to moderate depression V Darbinyan 1, G Aslanyan, E Amroyan, E Gabrielyan, C Malmström, A Panossian | DT19: Rhodiola rosea (Rose root) root extract (10:1) equivalent Rhodiola rosea dry root equivalent rosavins (3%) equivalent salidroside (1%) | DU19: No warnings.
A20: W010022000 | B20: A | C20: 0.0016 | D20: Boswellia serrata extract (standardized to 60% boswellic acids) | E20: Boswellia (Frankincense) | F20: A319 | G20: Boswellia serrata | H20: Boswellia serrata | I20: Boswellia serrata | J20: sap resin | K20: extract dry concentrate standardised | L20: 6:1 | M20: 98% ethanol:water | N20: 60% boswellic acids | O20: - | P20: Boswellia Serrata sap resin Ext. Dry Conc std (6:1 98% E/W) Equiv. Boswellia Serrata sap resin dry. Equiv. Boswellic acids (60%) | Q20: Boswellia serrata (Frankincense) sap resin extract equivalent Boswellia serrata dry sap resin equivalent boswellic acids | R20: 5 | S20: mg | T20: 30 | U20: mg | V20: 3 | W20: mg | Z20: - | AB20: 18.3102 | AC20: 1200 | AD20: 800 | AE20: Herb | AF20: Export Only, Listed, OTC, Prescription | AG20: 1302.19.90 | AH20: Highly refined organic chemicals and substances | AI20: Not required | AJ20: Not included in any CITES Appendix | AK20: No | AP20: dairy | BA20: soy | BB20: sulfites | BH20: sodium | BI20: 0.11 | BJ20: mg | BM20: sugars | BN20: 0.035 | BO20: mg | BV20: 96819 | BW20: No restrictions. | BX20: No warnings. | BY20: No warnings. | CC20: carmellose sodium | CE20: colloidal anhydrous silica | CL20: vanilla flavour | CP20: glucose monohydrate | CQ20: glycerol | CT20: hypromellose | CW20: lecithin | CX20: magnesium stearate | CZ20: maltodextrin | DB20: microcrystalline cellulose | DQ20: Yes | DR20: Yes | DS20: TR: 300-400 mg standardised extract, 3 times daily MT TR 800 - 1000 mg of a 6:1 extract UL https://pubmed.ncbi.nlm.nih.gov/17764013/ | DT20: Boswellia serrata (Frankincense) sap resin extract (6:1) equivalent Boswellia serrata dry sap resin equivalent boswellic acids (60%) | DU20: No warnings.
A21: W010023000 | B21: A | C21: 0.0026 | D21: Betaine (Trimethylglycine) | E21: Betaine (Trimethylglycine) | F21: A2232 | G21: Betaine | H21: - | I21: Betaine | J21: - | K21: - | L21: - | M21: - | N21: - | O21: - | P21: Betaine | Q21: Betaine | R21: 5 | S21: mg | Z21: - | AB21: 18.8102 | AC21: 6000 | AD21: 1000 | AE21: Amino acid | AF21: Export Only, OTC, Prescription | AG21: 2923.90.00 | AH21: Highly refined organic chemicals and substances | AI21: Not required | AJ21: Not included in any CITES Appendix | AK21: No | AP21: dairy | BA21: soy | BB21: sulfites | BH21: sodium | BI21: 0.11 | BJ21: mg | BM21: sugars | BN21: 0.035 | BO21: mg | BR21: sugar alcohols | BS21: 9.5 | BT21: mg | BV21: 67679 | BW21: Only for use in topical medicines for dermal application. | BX21: No warnings. | BY21: No warnings. | CC21: carmellose sodium | CE21: colloidal anhydrous silica | CL21: vanilla flavour | CP21: glucose monohydrate | CQ21: glycerol | CT21: hypromellose | CU21: isomalt | CW21: lecithin | CX21: magnesium stearate | DB21: microcrystalline cellulose | DQ21: Yes | DR21: Yes | DS21: TR 2.5 - 6 gm daily https://pubmed.ncbi.nlm.nih.gov/12730412/ TR 1000 mg to 4000 mg daily UL 6 gm YSCP confirmed 600mg Therapeutic Clinical use (most effective) (Chen S et al. 2015). 1000mg Aggressive Metabolic use. (Brown VA et al. 2010 (Cancer Research)1000mg to 1500mg Upper tolerable long-term. | DT21: Betaine (Trimethylglycine) | DU21: No warnings.
A22: W010024000 | B22: A | C22: 0.0054 | D22: Liquorice extract (root) | E22: Licorice DGL | F22: A2657 | G22: Glycyrrhiza glabra | H22: Glycyrrhiza glabra | I22: Glycyrrhiza glabra | J22: root | K22: extract dry concentrate standardised | L22: 8:1 | M22: 100% water | N22: 1.5% glycyrrhizin | O22: - | P22: Glycyrrhiza glabra Root Ext. Dry Conc. Std. (8:1 in 100% Water) Equiv. Glycyrrhiza glabra root dry Equiv. Glycyrrhizin 1.5% Excipient: Maltodextrin 5% | Q22: Glycyrrhiza glabra (Liquorice) root extract equivalent Glycyrrhiza glabra dry root equivalent glycyrrhizin | R22: 10 | S22: mg | T22: 80 | U22: mg | V22: 0.15 | W22: mg | Z22: - | AB22: 19.4902 | AC22: 1000 | AD22: 150 | AE22: Herb | AF22: Export Only, Listed, OTC, Prescription | AG22: 1302.12.00 | AH22: Highly refined organic chemicals and substances | AI22: Not required | AJ22: Not included in any CITES Appendix | AK22: No | AP22: dairy | BA22: soy | BB22: sulfites | BH22: sodium | BI22: 0.1 | BJ22: mg | BM22: sugars | BN22: 0.033 | BO22: mg | BR22: sugar alcohols | BS22: 1.5 | BT22: mg | BV22: 62323 | BW22: No restrictions. | BX22: No warnings. | BY22: No warnings. | CC22: carmellose sodium | CE22: colloidal anhydrous silica | CL22: vanilla flavour | CP22: glucose monohydrate | CQ22: glycerol | CT22: hypromellose | CU22: isomalt | CW22: lecithin | CX22: magnesium stearate | CZ22: maltodextrin | DB22: microcrystalline cellulose | DQ22: Yes | DR22: Yes | DS22: TR 1.5-6 gm daily ABC (Murray and Pizorno) 3.8 gm for ulcers BC in 5 divided doses I think we can stay at 300 mg because it is 1 daily dose. TR is 150mg - 300 mg of a 6:1 extract daily, UL is higher because of safety of DGL | DT22: Glycyrrhiza glabra (Licorice) root extract (8:1) equivalent Glycyrrhiza glabra dry root equivalent glycyrrhizin (1.5%) | DU22: No warnings.
A23: W010025000 | B23: A | C23: 0.008 | D23: Dong quai (Angelica polymorpha) extract (root) (standardized to 0.25% ligustilide) | E23: Dong quai | F23: A2720 | G23: Angelica polymorpha | H23: Angelica polymorpha | I23: Angelica polymorpha | J23: root | K23: extract dry concentrate standardised | L23: 2:1 | M23: 50% ethanol:water | N23: 0.25% ligustilide | O23: - | P23: Angelica polymorpha (Dong quai) root ext dry conc std (2:1, 50% E/W) Equiv. Angelica polymorpha root dry Equiv. Ligustilide (0.25%) | Q23: Angelica polymorpha (Dong quai) root extract equivalent Angelica polymorpha dry root equivalent ligustilide | R23: 10 | S23: mg | T23: 20 | U23: mg | V23: 0.02 | W23: mg | Z23: Please confirm the name and quantity of any excipients present? | AA23: No excipients | AB23: 19.8102 | AC23: 6000 | AD23: 500 | AE23: Herb | AF23: Export Only, Listed, OTC, Prescription | AG23: 1302.19.90 | AH23: Highly refined organic chemicals and substances | AI23: Not required | AJ23: Not included in any CITES Appendix | AK23: No | AP23: dairy | BA23: soy | BB23: sulfites | BH23: sodium | BI23: 0.11 | BJ23: mg | BM23: sugars | BN23: 0.035 | BO23: mg | BV23: 72121 | BW23: No restrictions. | BX23: No warnings. | BY23: No warnings. | CC23: carmellose sodium | CE23: colloidal anhydrous silica | CL23: vanilla flavour | CP23: glucose monohydrate | CQ23: glycerol | CT23: hypromellose | CW23: lecithin | CX23: magnesium stearate | DB23: microcrystalline cellulose | DQ23: Yes | DR23: Yes | DS23: TR 2-4 gram daily KB TR is 500 - 2000 mg of a 2:1 extract daily | DT23: Angelica polymorpha (Dong quai) root extract (2:1) equivalent Angelica polymorpha dry root equivalent ligustilide (0.25%) | DU23: No warnings.
A24: W010026000 | B24: A | C24: 0.0074 | D24: Berberine HCl | E24: Berberine HCL (Indian Barberry) | F24: A2412 | G24: Berberis aristata | H24: Berberis aristata | I24: Berberis aristata | J24: root | K24: extract dry concentrate standardised | L24: 40:1 | M24: 100% methanol | N24: 95% berberine hydrochloride | O24: - | P24: Berberis aristata root extract 40:1 (100% Methanol) Equiv. Berberis aristata root dry Equiv. Berberine Hydrochloride (95%) | Q24: Berberis aristata (Indian barberry) root extract equivalent Berberis aristata dry root equivalent berberine hydrochloride | R24: 10.53 | S24: mg | T24: 421.2 | U24: mg | V24: 10 | W24: mg | Z24: - | AB24: 19.4532 | AC24: 1500 | AD24: 500 | AE24: Herb | AF24: Export Only, Listed | AG24: 1302.19.90 | AH24: Highly refined organic chemicals and substances | AI24: Not required | AJ24: Not included in any CITES Appendix | AK24: No | AP24: dairy | BA24: soy | BB24: sulfites | BH24: sodium | BI24: 0.1 | BJ24: mg | BM24: sugars | BN24: 0.033 | BO24: mg | BV24: 110503 | BW24: Only for use in oral medicines. | BX24: The medicine requires the following warning statement on the medicine label:- (PREGNT) 'Not recommended for use by pregnant and lactating women' (or words to that effect). | BY24: No warnings. | CC24: carmellose sodium | CE24: colloidal anhydrous silica | CL24: vanilla flavour | CN24: glacial acetic acid | CP24: glucose monohydrate | CW24: lecithin | CX24: magnesium stearate | DB24: microcrystalline cellulose | DF24: poliglusam | DQ24: Yes | DR24: Yes | DS24: 500-1000 mg daily BC, TR is 500 - 1000 mg of a 40:1 extract, 1500 mg is UL equiv to 1425 mg of berberine (checked berberine content with Matt) | DT24: Berberis aristata (Indian barberry) root extract (40:1) equivalent Berberis aristata dry root equivalent berberine hydrochloride (95%) | DU24: "Not recommended for use by pregnant and lactating women."
A25: W010028000 | B25: A | C25: 0.0048 | D25: Maca (Lepidium meyenii) extract (standardised to 0.6% glucosinates) | E25: Maca (fruit) | F25: A2710 | G25: Lepidium meyenii | H25: Lepidium meyenii | I25: Lepidium meyenii | J25: fruit | K25: extract dry concentrate standardised | L25: 18:1 | M25: 20% ethanol:water | N25: 0.6% glucosinates | O25: - | P25: Lepidium meyenii fruit ext dry conc std (18-20:1 in 20:80 E:W) Equiv. Fruit dry Equiv. glucosinates (0.6%) | Q25: Lepidium meyenii (Maca) fruit extract equivalent Lepidium meyenii dry fruit equivalent glucosinates | R25: 10 | S25: mg | T25: 180 | U25: mg | V25: 0.06 | W25: mg | Z25: - | AB25: 19.4902 | AC25: 4000 | AD25: 700 | AE25: Herb | AF25: Export Only, Listed | AG25: 1302.19.90 | AH25: Highly refined organic chemicals and substances | AI25: Not required | AJ25: Not included in any CITES Appendix | AK25: No | AP25: dairy | BA25: soy | BB25: sulfites | BH25: sodium | BI25: 0.1 | BJ25: mg | BM25: sugars | BN25: 0.033 | BO25: mg | BR25: sugar alcohols | BS25: 1.2 | BT25: mg | BV25: 104787 | BW25: The route of administration for medicines that contain Lepidium meyenii must be limited to oral. The ingredient must consist of the dried tuber of Lepidium meyenii only. The maximum recommended daily dose of the medicine must not provide more than 3.5 g of Lepidium meyenii dried tuber (or its extract equivalent). | BX25: No warnings. | BY25: No warnings. | CC25: carmellose sodium | CE25: colloidal anhydrous silica | CJ25: ethanol | CL25: vanilla flavour | CP25: glucose monohydrate | CQ25: glycerol | CT25: hypromellose | CU25: isomalt | CW25: lecithin | CX25: magnesium stearate | DB25: microcrystalline cellulose | DQ25: Yes | DR25: Yes | DS25: TR 2- 3.5 gm daily. Toxicity studies show safety at 7.5 g/kg (rats) and 15g/kg on mice, suggesting it is safe in high doses (Meissner, 2006) BC TR is 700mg to 3,500 mg of a 18:1 extract daily | DT25: Lepidium meyenii (Maca) fruit extract (18:1) equivalent Lepidium meyenii dry fruit equivalent glucosinates (0.6%) | DU25: No warnings.
A26: W010029000 | B26: A | C26: 0.0038 | D26: Turmeric (Curcuma longa) extract (root) (standardized to contain 40% curcuminoids) | E26: Turmeric (Curcumin) | F26: A2740 | G26: Curcuma longa | H26: Curcuma longa | I26: Curcuma longa | J26: root | K26: extract dry concentrate standardised | L26: 25:1 | M26: 65% ethanol:water | N26: 40% curcuminoids | O26: - | P26: Curcuma longa (Turmeric) root ext dry conc std (25:1, 54% E/W) Equiv. Curcuma longa root dry Equiv. Curcuminoids (40%) | Q26: Curcuma longa (Turmeric) root extract equivalent Curcuma longa dry root equivalent curcuminoids | R26: 10 | S26: mg | T26: 250 | U26: mg | V26: 4 | W26: mg | Z26: Please confirm the name and quantity of any excipients present? | AA26: 60% maltodextrin | AB26: 19.8102 | AC26: 1000 | AD26: 300 | AE26: Herb | AF26: Export Only, Listed, OTC, Prescription | AG26: 1302.19.90 | AH26: Highly refined organic chemicals and substances | AI26: Not required | AJ26: Not included in any CITES Appendix | AK26: No | AP26: dairy | BA26: soy | BB26: sulfites | BH26: sodium | BI26: 0.1 | BJ26: mg | BM26: sugars | BN26: 0.033 | BO26: mg | BV26: 65400 | BW26: When used in oral medicines the maximum daily dose of (1E,6E)-1,7-bis(4-hydroxy-3-methoxyphenyl)-1,6-heptadiene-3,5-dione in the medicine must not provide more than: (a) 36 mg for children from 2-3 years (inclusive); (b) 48 mg for children from 4-11 years (inclusive); and (c) 123 mg for children from 12-17 years (inclusive). Not permitted for use in children aged below 2 years. | BX26: When used in oral medicines as an active ingredient, the following warning statement is required on the medicine label: ‘In very rare cases, Curcuma species may harm the liver. Stop use and see a doctor if you have yellowing skin/eyes or unusual: fatigue, nausea, appetite loss, abdominal pain, dark urine, or itching.’ | BY26: No warnings. | CC26: carmellose sodium | CE26: colloidal anhydrous silica | CL26: vanilla flavour | CP26: glucose monohydrate | CQ26: glycerol | CT26: hypromellose | CW26: lecithin | CX26: magnesium stearate | CZ26: maltodextrin | DB26: microcrystalline cellulose | DQ26: Yes | DR26: Yes | DS26: Therapuetic range 12 gm daily MT TR IS 300-1000 mg of a 25:1 extract daily No UL YSCP confirmed 1,000–1,500 mg/day Evidence-Based Clinical Dosing | DT26: Curcuma longa (Turmeric) root extract (25:1) equivalent Curcuma longa dry root equivalent curcuminoids (40%) | DU26: "In very rare cases, curcuma species may harm the liver." "Stop use and consult a healthcare professional if you have yellowing skin/eyes or unusual fatigue, nausea, appetite loss, abdominal pain, dark urine, or itching."
A27: W010030000 | B27: A | C27: 0.0086 | D27: Fenugreek (Trigonella foenum-graecum) extract (seed) (standardized to 50% saponins) | E27: Fenugreek | F27: A2737 | G27: Trigonella foenum-graecum | H27: Trigonella foenum-graecum | I27: Trigonella foenum-graecum | J27: seed | K27: extract dry concentrate standardised | L27: 50:1 | M27: 50% ethanol:water | N27: 50% saponins | O27: - | P27: Trigonella foenum-graecum (Fenugreek) seed dry ext conc std. 50:1, (50:50 E:W) Equiv. Trigonella foenum-graecum seed dry Equiv. saponins 50% | Q27: Trigonella foenum-graecum (Fenugreek) seed extract equivalent Trigonella foenum-graecum dry seed equivalent saponins | R27: 5 | S27: mg | T27: 250 | U27: mg | V27: 2.5 | W27: mg | Z27: - | AB27: 18.9502 | AC27: 200 | AD27: 50 | AE27: Herb | AF27: Export Only, Listed, OTC, Prescription | AG27: 1302.19.90 | AH27: Highly refined organic chemicals and substances | AI27: Not required | AJ27: Not included in any CITES Appendix | AK27: No | AP27: dairy | BA27: soy | BB27: sulfites | BH27: sodium | BI27: 0.1 | BJ27: mg | BM27: sugars | BN27: 0.033 | BO27: mg | BR27: sugar alcohols | BS27: 1.5 | BT27: mg | BV27: 59791 | BW27: No restrictions. | BX27: No warnings. | BY27: No warnings. | CC27: carmellose sodium | CE27: colloidal anhydrous silica | CL27: vanilla flavour | CN27: glacial acetic acid | CP27: glucose monohydrate | CU27: isomalt | CW27: lecithin | CX27: magnesium stearate | DB27: microcrystalline cellulose | DF27: poliglusam | DQ27: Yes | DR27: Yes | DS27: Therapeutic range 2-4 gm daily MT, aligns with BC TR 50mg to 100 mg of a 50:1 extract | DT27: Trigonella foenum-graecum (Fenugreek) seed extract (50:1) equivalent Trigonella foenum-graecum dry seed equivalent saponins (50%) | DU27: No warnings.
A28: W010031000 | B28: A | C28: 0.0045 | D28: Quercetin | E28: Quercetin | F28: A090 | G28: Quercetin | H28: - | I28: Quercetin dihydrate | J28: - | K28: - | L28: - | M28: - | N28: - | O28: 88% quercetin | P28: Quercetin dihydrate Equiv. Quercetin (88%) | Q28: Quercetin dihydrate equivalent quercetin | R28: 11.36 | S28: mg | T28: 10 | U28: mg | Z28: There are two forms, quercetin, and quercetin dihydrate. Please confirm which form is being used? | AA28: Quercetin dihydrate | AB28: 17.47 | AC28: 2000 | AD28: 250 | AE28: Herb | AF28: Export Only, Listed, OTC, Prescription | AG28: 1302.19.90 | AH28: Highly refined organic chemicals and substances | AI28: Not required | AJ28: Not included in any CITES Appendix | AK28: No | AP28: dairy | BA28: soy | BB28: sulfites | BH28: sodium | BI28: 0.11 | BJ28: mg | BM28: sugars | BN28: 0.035 | BO28: mg | BR28: sugar alcohols | BS28: 0.01 | BT28: mg | BV28: 106686 | BW28: No restrictions. | BX28: No warnings. | BY28: No warnings. | CC28: carmellose sodium | CE28: colloidal anhydrous silica | CL28: vanilla flavour | CN28: glacial acetic acid | CP28: glucose monohydrate | CT28: hypromellose | CU28: isomalt | CW28: lecithin | CX28: magnesium stearate | DB28: microcrystalline cellulose | DF28: poliglusam | DQ28: Yes | DR28: Yes | DS28: TR 150mg-2000 gm daily. Well tolerated and appears to be associated with little toxicity orally or IV (Lamson and Brignall 2000) BC UL 2gm | DT28: Quercetin dihydrate equivalent quercetin (88%) | DU28: No warnings.
A29: W010032000 | B29: A | C29: 0.0045 | D29: Cinnamon (Cinnamomum cassia) extract (bark) (standardized to 10% polyphenols) | E29: Cinnamon | F29: A2717 | G29: Cinnamomum cassia | H29: Cinnamomum cassia | I29: Cinnamomum cassia | J29: bark | K29: extract dry concentrate standardised | L29: 4:1 | M29: 70% ethanol:water | N29: 10% polyphenols | O29: - | P29: Cinnamomum cassia (Cinnamon) bark ext dry conc std (4:1, 70% E/W) Equiv. Cinnamomum cassia bark dry Equiv. Polyphenols (10%) | Q29: Cinnamomum cassia (Cinnamon) bark extract equivalent Cinnamomum cassia dry bark equivalent polyphenols | R29: 5 | S29: mg | T29: 20 | U29: mg | V29: 0.5 | W29: mg | Z29: Please confirm the name and quantity of any excipients present? | AA29: No excipients | AB29: 19.4702 | AC29: 1500 | AD29: 150 | AE29: Herb | AF29: Export Only, Listed, OTC, Prescription | AG29: 1302.19.90 | AH29: Highly refined organic chemicals and substances | AI29: Not required | AJ29: Not included in any CITES Appendix | AK29: No | AP29: dairy | BA29: soy | BB29: sulfites | BH29: sodium | BI29: 0.11 | BJ29: mg | BM29: sugars | BN29: 0.035 | BO29: mg | BV29: 67430 | BW29: Cassia oil is a mandatory component of Cinnamomum cassia if the plant preparation is an essential oil, distillate, fixed oil or infused oil. The concentration of Cassia oil in the medicine must be no more than 2%. When used as an active ingredient, the concentration of coumarin in the medicine must be no more than 0.001%. | BX29: No warnings. | BY29: No warnings. | CC29: carmellose sodium | CE29: colloidal anhydrous silica | CL29: vanilla flavour | CN29: glacial acetic acid | CP29: glucose monohydrate | CW29: lecithin | CX29: magnesium stearate | DB29: microcrystalline cellulose | DF29: poliglusam | DQ29: Yes | DR29: Yes | DS29: TR 1 - 6 gm daily (BC) 1.5-4 gm up to 4 times daily (BC) Generally well tolerated (BC) TR 250 mg - 1000 mg of a 4:1 extract daily No UL | DT29: Cinnamomum cassia (Cinnamon) bark extract (4:1) equivalent Cinnamomum cassia dry bark equivalent polyphenols (10%) | DU29: No warnings.
A30: W010033000 | B30: A | C30: 0.0067 | D30: Lemon balm (Melissa officinalis) extract (standardized to 3% rosmaric acid) | E30: Lemon balm | F30: A2914 | G30: Melissa officinalis | H30: Melissa officinalis | I30: Melissa officinalis | J30: herb | K30: extract dry concentrate standardised | L30: 4:1 | M30: 100% water | N30: 3% rosmarinic acid | O30: - | P30: Melissa officinalis (Lemon balm) herb ext dry conc std 4:1 (100% water), Equiv. rosmaric acid (3%) | Q30: Melissa officinalis (Lemon balm) herb extract equivalent Melissa officinalis dry herb equivalent rosmarinic acid | R30: 10 | S30: mg | T30: 40 | U30: mg | V30: 0.3 | W30: mg | Z30: - | AB30: 20.0002 | AC30: 3300 | AD30: 200 | AE30: Herb | AF30: Export Only, Listed, OTC, Prescription | AG30: 1302.19.90 | AH30: Highly refined organic chemicals and substances | AI30: Not required | AJ30: Not included in any CITES Appendix | AK30: No | AP30: dairy | BA30: soy | BB30: sulfites | BH30: sodium | BI30: 0.11 | BJ30: mg | BM30: sugars | BN30: 0.035 | BO30: mg | BR30: sugar alcohols | BS30: 3 | BT30: mg | BV30: 60154 | BW30: No restrictions. | BX30: No warnings. | BY30: No warnings. | CC30: carmellose sodium | CE30: colloidal anhydrous silica | CL30: vanilla flavour | CP30: glucose monohydrate | CQ30: glycerol | CT30: hypromellose | CU30: isomalt | CW30: lecithin | CX30: magnesium stearate | DB30: microcrystalline cellulose | DQ30: Yes | DR30: Yes | DS30: Therapeutic range 6-12 gm daily MT TR 4.5- 13.5 gm/day BC TR is 400 mg - 3000 mg of a 4:1 daily extract ROUNDED DOWN to even No. of granules | DT30: Melissa officinalis (Lemon balm) herb extract (4:1) equivalent Melissa officinalis dry herb equivalent rosmarinic acid (3%) | DU30: No warnings.
A31: W010034000 | B31: A | C31: 0.007 | D31: Passionflower (Passiflora incarnata) extract (standardized to 4% flavonoids) | E31: Passionflower | F31: A2915 | G31: Passiflora incarnata | H31: Passiflora incarnata | I31: Passiflora incarnata | J31: herb | K31: extract dry concentrate standardised | L31: 10:1 | M31: 70% ethanol:water | N31: 4% flavonoids | O31: - | P31: Passiflora incarnata (Passionflower) herb extract equivalent Passiflora incarnata dry herb equivalent flavonoids | Q31: Passiflora incarnata (Passionflower) herb extract equivalent Passiflora incarnata dry herb equivalent flavonoids | R31: 10 | S31: mg | T31: 100 | U31: mg | V31: 0.4 | W31: mg | Z31: Please confirm the name and quantity of any excipients present? | AA31: 10% maltodextrin | AB31: 18.4602 | AC31: 800 | AD31: 200 | AE31: Herb | AF31: Export Only, Listed, OTC, Prescription | AG31: 1302.19.90 | AH31: Highly refined organic chemicals and substances | AI31: Not required | AJ31: Not included in any CITES Appendix | AK31: No | AP31: dairy | BA31: soy | BB31: sulfites | BH31: sodium | BI31: 0.1 | BJ31: mg | BM31: sugars | BN31: 0.031 | BO31: mg | BV31: 59183 | BW31: No restrictions. | BX31: No warnings. | BY31: No warnings. | CC31: carmellose sodium | CE31: colloidal anhydrous silica | CL31: vanilla flavour | CP31: glucose monohydrate | CQ31: glycerol | CT31: hypromellose | CW31: lecithin | CX31: magnesium stearate | CZ31: maltodextrin | DB31: microcrystalline cellulose | DQ31: Yes | DR31: Yes | DS31: Therapeutic range 2-8 gm daily MT TR 200 - 700 mg daily of a 10:1 extract, UL 800 mg MT | DT31: Passiflora incarnata (Passionflower) herb extract (10:1) equivalent Passiflora incarnata dry herb equivalent flavonoids (4%) | DU31: No warnings.
A32: W010037000 | B32: A | C32: 0.009 | D32: California poppy extract (herb) (4:1) | E32: California poppy | F32: A660 | G32: Eschscholzia californica | H32: Eschscholzia californica | I32: Eschscholzia californica | J32: herb | K32: extract dry concentrate | L32: 4:1 | M32: 70% ethanol:water | N32: - | O32: - | P32: Eschscholzia californica (California poppy) herb ext dry conc (4:1, 70% E/W) Equiv. Eschscholzia californica herb dry | Q32: Eschscholzia californica (California poppy) herb extract equivalent Eschscholzia californica dry herb | R32: 5 | S32: mg | T32: 20 | U32: mg | Z32: Please confirm the name and quantity of any excipients present? | AA32: NMT 30% maltodextrin | AB32: 198.2802 | AC32: 1000 | AD32: 300 | AE32: Herb | AF32: Export Only, Listed, OTC, Prescription | AG32: 1302.19.90 | AH32: Highly refined organic chemicals and substances | AI32: Not required | AJ32: Not included in any CITES Appendix | AK32: No | AP32: dairy | BA32: soy | BB32: sulfites | BH32: sodium | BI32: 0.1 | BJ32: mg | BM32: sugars | BN32: 0.031 | BO32: mg | BV32: 108194 | BW32: No restrictions. | BX32: No warnings. | BY32: No warnings. | CC32: carmellose sodium | CE32: colloidal anhydrous silica | CL32: vanilla flavour | CP32: glucose monohydrate | CQ32: glycerol | CT32: hypromellose | CW32: lecithin | CX32: magnesium stearate | CZ32: maltodextrin | DB32: microcrystalline cellulose | DQ32: Yes | DR32: Yes | DS32: TR 300-1000 mg/day DEE BHP TR 300mg - 600 mg of a 4:1 extract daily, UL 1000 mg | DT32: Eschscholzia californica (California poppy) herb extract (4:1) equivalent Eschscholzia californica dry herb | DU32: No warnings.
A33: W010038000 | B33: A | C33: 0.0173 | D33: Genistein (Sophora japonica) extract | E33: Genistein | F33: A2709 | G33: Sophora japonica | H33: Styphnolobium japonicum | I33: Styphnolobium japonicum | J33: fruit | K33: extract dry concentrate standardised | L33: 100:1 | M33: 75% ethanol:water | N33: 98% genistein | O33: - | P33: Styphnolobium japonicum (Japanese pagoda tree) fruit ext dry conc std (100:1, 50% E/W) Equiv. Styphnolobium japonicum fruit dry Equiv. Genistein (98%) | Q33: Styphnolobium japonicum (Japanese pagoda tree) fruit extract equivalent Styphnolobium japonicum dry fruit equivalent genistein | R33: 10 | S33: mg | T33: 1000 | U33: mg | V33: 9.8 | W33: mg | Z33: Please confirm the name and quantity of any excipients present? | AA33: No excipients | AB33: 17.7432 | AC33: 150 | AD33: 60 | AE33: Herb | AF33: Export Only, Listed, OTC, Prescription | AG33: 1302.19.90 | AH33: Highly refined organic chemicals and substances | AI33: Not required | AJ33: Not included in any CITES Appendix | AK33: No | AP33: dairy | BA33: soy | BB33: sulfites | BH33: sodium | BI33: 0.09 | BJ33: mg | BM33: sugars | BN33: 0.03 | BO33: mg | BR33: sugar alcohols | BS33: 3 | BT33: mg | BV33: 108241 | BW33: No restrictions. | BX33: No warnings. | BY33: No warnings. | CC33: carmellose sodium | CL33: vanilla flavour | CP33: glucose monohydrate | CQ33: glycerol | CT33: hypromellose | CU33: isomalt | CW33: lecithin | CX33: magnesium stearate | DB33: microcrystalline cellulose | DG33: pregelatinised starch | DQ33: Yes | DR33: Yes | DS33: TR is 30mg - 90 mg of a 100:1 extract daily, UL 150 mg of a 100:1 extract based on a genistein level | DT33: Styphnolobium japonicum (Japanese pagoda tree) fruit extract (100:1) equivalent Styphnolobium japonicum dry fruit equivalent genistein (98%) | DU33: No warnings.
A34: W010039000 | B34: A | C34: 0.0035 | D34: Holy basil (Ocimum tenuiflorum) extract (standardized to 2.5% ursolic acid) | E34: Holy basil | F34: A2723 | G34: Ocimum tenuiflorum | H34: Ocimum tenuiflorum | I34: Ocimum tenuiflorum | J34: leaf | K34: extract dry concentrate standardised | L34: 10:1 | M34: 50% ethanol:water | N34: 2.5% ursolic acid | O34: - | P34: Ocimum tenuiflorum (Holy basil) leaf ext dry conc std (10:1, 50% E/W) Equiv. Ocimum tenuiflorum leaf dry Equiv. Ursolic acid (2.5%) | Q34: Ocimum tenuiflorum (Holy basil) leaf extract equivalent Ocimum tenuiflorum dry leaf equivalent ursolic acid | R34: 5 | S34: mg | T34: 50 | U34: mg | V34: 0.125 | W34: mg | Z34: Please confirm the name and quantity of any excipients present? | AA34: No excipients | AB34: 19.4852 | AC34: 1200 | AD34: 300 | AE34: Herb | AF34: Export Only, Listed, OTC, Prescription | AG34: 1302.19.90 | AH34: Highly refined organic chemicals and substances | AI34: Not required | AJ34: Not included in any CITES Appendix | AK34: No | AP34: dairy | BA34: soy | BB34: sulfites | BH34: sodium | BI34: 0.1 | BJ34: mg | BM34: sugars | BN34: 0.033 | BO34: mg | BV34: 83282 | BW34: When the plant part is oil or distillate, eugenol is a mandatory component of Ocimum tenuiflorum. When the concentration of eugenol in the preparation is more than 25% and the nominal capacity of the container is more than 15 millilitres but less than or equal to 25 millilitres, the medicine must have a child resistant closure and restricted flow insert fitted on the container. When the concentration of eugenol in the preparation is more than 25% and the nominal capacity of the container is no more than 15 millilitres, the medicine must have a restricted flow insert fitted on the container. When the preparation is for topical use in the mouth, the preparation may not contain more than 5 mL of eugenol and the concentration of eugenol in the product must not be greater than 25%. | BX34: When the concentration of eugenol in the preparation is more than 25%, the nominal capacity of the container must not be more than 25 millilitres and the following warning statements must be included on the medicine label: - (CHILD) 'Keep out of reach of children' (or words to that effect); and - (NTAKEN) 'Not to be taken'. | BY34: No warnings. | CC34: carmellose sodium | CE34: colloidal anhydrous silica | CL34: vanilla flavour | CP34: glucose monohydrate | CQ34: glycerol | CT34: hypromellose | CW34: lecithin | CX34: magnesium stearate | CZ34: maltodextrin | DB34: microcrystalline cellulose | DQ34: Yes | DR34: Yes | DS34: TR 300mg - 500 mg of a 10:1 extract daily, UL 1200 mg | DT34: Ocimum tenuiflorum (Holy basil) leaf extract (10:1) equivalent Ocimum tenuiflorum dry leaf equivalent ursolic acid (2.5%) | DU34: No warnings.
A35: W010043000 | B35: A | C35: 0.0077 | D35: Saw Palmetto (Serenoa repens) extract (standardized to 30% fatty acids) | E35: Saw palmetto | F35: A2738 | G35: Serenoa repens | H35: Serenoa repens | I35: Serenoa repens | J35: fruit | K35: extract dry concentrate standardised | L35: 8:1 | M35: 60% ethanol:water | N35: 30% fatty acids | O35: - | P35: Serenoa repens (Saw palmetto) fruit ext dry conc std (8:1, 60% E/W) Equiv. Serenoa repens fruit dry Equiv. Fatty acids (30%) | Q35: Serenoa repens (Saw palmetto) fruit extract equivalent Serenoa repens dry fruit equivalent fatty acids | R35: 5 | S35: mg | T35: 40 | U35: mg | V35: 1.5 | W35: mg | Z35: Please confirm the name and quantity of any excipients present? | AA35: 5-10% maltodextrin | AB35: 20.4702 | AC35: 640 | AD35: 320 | AE35: Herb | AF35: Export Only, Listed, OTC, Prescription | AG35: 1302.19.90 | AH35: Highly refined organic chemicals and substances | AI35: Not required | AJ35: Not included in any CITES Appendix | AK35: No | AP35: dairy | BA35: soy | BB35: sulfites | BH35: sodium | BI35: 0.11 | BJ35: mg | BM35: sugars | BN35: 0.035 | BO35: mg | BR35: sugar alcohols | BS35: 1.5 | BT35: mg | BV35: 61484 | BW35: No restrictions. | BX35: No warnings. | BY35: No warnings. | CC35: carmellose sodium | CE35: colloidal anhydrous silica | CL35: vanilla flavour | CN35: glacial acetic acid | CP35: glucose monohydrate | CT35: hypromellose | CU35: isomalt | CW35: lecithin | CX35: magnesium stearate | CZ35: maltodextrin | DB35: microcrystalline cellulose | DF35: poliglusam | DQ35: Yes | DR35: Yes | DS35: Therapeutic range 1.5 - 3 gm daily MT TR 200 mg - 400 mg of a 8:1 extract daily, UL 640 mg of a 10:1 extract daily | DT35: Serenoa repens (Saw palmetto) fruit extract (8:1) equivalent Serenoa repens dry fruit equivalent fatty acids (30%) | DU35: No warnings.
A36: W010044000 | B36: A | C36: 0.0029 | D36: Skullcap (Scutellaria baicalensis) extract (8:1) | E36: Baical (Chinese) skullcap | F36: A2727 | G36: Scutellaria baicalensis | H36: Scutellaria baicalensis | I36: Scutellaria baicalensis | J36: root | K36: extract dry concentrate | L36: 8:1 | M36: 100% water | N36: - | O36: - | P36: Scutellaria baicalensis (Chinese skullcap) root ext dry conc (8:1, 100% Water) Equiv. Scutellaria baicalensis root dry | Q36: Scutellaria baicalensis (Chinese skullcap) root extract equivalent Scutellaria baicalensis dry root | R36: 5 | S36: mg | T36: 40 | U36: mg | Z36: Please confirm the name and quantity of any excipients present? | AA36: 2% maltodextrin | AB36: 18.9502 | AC36: 1200 | AD36: 370 | AE36: Herb | AF36: Export Only, Listed, OTC, Prescription | AG36: 1302.19.90 | AH36: Highly refined organic chemicals and substances | AI36: Not required | AJ36: Not included in any CITES Appendix | AK36: No | AP36: dairy | BA36: soy | BB36: sulfites | BH36: sodium | BI36: 0.1 | BJ36: mg | BM36: sugars | BN36: 0.033 | BO36: mg | BV36: 68499 | BW36: No restrictions. | BX36: No warnings. | BY36: No warnings. | CC36: carmellose sodium | CE36: colloidal anhydrous silica | CL36: vanilla flavour | CN36: glacial acetic acid | CP36: glucose monohydrate | CW36: lecithin | CX36: magnesium stearate | CZ36: maltodextrin | DB36: microcrystalline cellulose | DF36: poliglusam | DQ36: Yes | DR36: Yes | DS36: Therapeutic range 6-15 g daily (Bensky and Gamble 1986) BC TR is 375 mg - 1000 mg of a 8:1 extract daily, UL 1200 mg of an 8:1 extract | DT36: Scutellaria baicalensis (Chinese skullcap) root extract (8:1) equivalent Scutellaria baicalensis dry root | DU36: No warnings.
A37: W010046000 | B37: A | C37: 0.0026 | D37: Glycyrrhiza glabra extract (root) (10-15:1) (standardized to 26% glycyrrhizic acid) | E37: Licorice | F37: A2715 | G37: Glycyrrhiza glabra | H37: Glycyrrhiza glabra | I37: Glycyrrhiza glabra | J37: root | K37: extract dry concentrate standardised | L37: 10-15:1 | M37: 100% water | N37: 26% glycyrrhizic acid | O37: - | P37: Glycyrrhiza glabra (Liquorice) Root dry Ext conc std. 10-15:1 100% W Equiv. 26% glycyrrhizic acid Equiv. Glycyrrhiza glabra root dry Maltodextrin 1% | Q37: Glycyrrhiza glabra (Liquorice) root extract equivalent Glycyrrhiza glabra dry root equivalent glycyrrhizic acid | R37: 5 | S37: mg | T37: 50 | U37: mg | V37: 1.3 | W37: mg | Z37: - | AB37: 19.4902 | AC37: 385 | AD37: 150 | AE37: Herb | AF37: Export Only, Listed, OTC, Prescription | AG37: 1302.12.00 | AH37: Highly refined organic chemicals and substances | AI37: Not required | AJ37: Not included in any CITES Appendix | AK37: No | AP37: dairy | BA37: soy | BB37: sulfites | BH37: sodium | BI37: 0.1 | BJ37: mg | BM37: sugars | BN37: 0.033 | BO37: mg | BV37: 62323 | BW37: No restrictions. | BX37: No warnings. | BY37: No warnings. | CC37: carmellose sodium | CE37: colloidal anhydrous silica | CL37: vanilla flavour | CP37: glucose monohydrate | CQ37: glycerol | CT37: hypromellose | CW37: lecithin | CX37: magnesium stearate | CZ37: maltodextrin | DB37: microcrystalline cellulose | DQ37: Yes | DR37: Yes | DS37: Therapeutic range 3-15 gm daily MT ABC 150 mg - 300 mg of a 10:1 extract daily, equiv to ga of 78 mg mg (FSA and SCF safety for GA is 100 mg) ul 385 mg | DT37: Glycyrrhiza glabra (Licorice) root extract (10:1) equivalent Glycyrrhiza glabra dry root equivalent glycyrrhizic acid (26%) | DU37: No warnings.
A38: W010048000 | B38: A | C38: 0.0048 | D38: Ginger (Zingiber officinale) extract (root) | E38: Ginger | F38: A372 | G38: Zingiber officinale | H38: Zingiber officinale | I38: Zingiber officinale | J38: root | K38: extract dry concentrate | L38: 20:1 | M38: 95% ethanol:water | N38: - | O38: - | P38: Zingiber officinale (ginger) root ext dry conc 20:1 (95:5 E;W) Equiv. Zingiber officinale root dry | Q38: Zingiber officinale (Ginger) root extract equivalent Zingiber officinale dry root | R38: 5 | S38: mg | T38: 100 | U38: mg | Z38: - | AB38: 19.4472 | AC38: 200 | AD38: 50 | AE38: Herb | AF38: Export Only, Listed, OTC, Prescription | AG38: 1302.19.90 | AH38: Highly refined organic chemicals and substances | AI38: Not required | AJ38: Not included in any CITES Appendix | AK38: No | AP38: dairy | BA38: soy | BB38: sulfites | BH38: sodium | BI38: 0.1 | BJ38: mg | BM38: sugars | BN38: 0.033 | BO38: mg | BV38: 62337 | BW38: No restrictions. | BX38: When for oral use AND the extract ratio is equal to or more than 25:1 AND the equivalent dry weight per dosage unit is equal to or more than 2g, the medicine requires the following warning statement on the medicine label: - (GINGER) 'Individuals taking anticoagulants should seek medical advice before taking this medicine.' AND 'Individuals at risk of bleeding problems should seek advice from their healthcare practitioner prior to taking this medicine'. | BY38: No warnings. | CC38: carmellose sodium | CE38: colloidal anhydrous silica | CL38: vanilla flavour | CN38: glacial acetic acid | CP38: glucose monohydrate | CW38: lecithin | CX38: magnesium stearate | CZ38: maltodextrin | DB38: microcrystalline cellulose | DF38: poliglusam | DQ38: Yes | DR38: Yes | DS38: Therapeutic range .75-3 gm daily MT . TR 1-3 gm/daily BC TR is 50 - 150 mg of a 20:1 extract daily, UL 200 mg of a 20:1 extract ML - Reduced from 250 to 50. 20:1 extract is equivalent to 1gm ginger. Changed max dose from 750 to 250 equivalent to 5g dry ginger root for single serve is in line with traditional recommendations. | DT38: Zingiber officinale (Ginger) root extract (20:1) equivalent Zingiber officinale dry root | DU38: "Individuals taking anticoagulants should consult a healthcare professional before taking this medicine." "'Individuals at risk of bleeding problems should consult a healthcare professional before taking this medicine."
A39: W010049000 | B39: A | C39: 0.0051 | D39: Rosemary (Rosmarinus officinalis) extract (standardized to 10% rosemarinic acid) | E39: Rosemary | F39: A2746 | G39: Rosmarinus officinalis | H39: Rosmarinus officinalis | I39: Rosmarinus officinalis | J39: herb | K39: extract dry concentrate standardised | L39: 15:1 | M39: 100% water | N39: 10% rosmarinic acid | O39: - | P39: Rosmarinus officinalis (Rosemary) herb ext dry conc std (15:1, 100% Water) Equiv. Rosmarinus officinalis herb dry Equiv. Rosmarinic acid (10%) | Q39: Rosmarinus officinalis (Rosemary) herb extract equivalent Rosmarinus officinalis dry herb equivalent rosmarinic acid | R39: 5 | S39: mg | T39: 75 | U39: mg | V39: 0.5 | W39: mg | Z39: Please confirm the name and quantity of any excipients present? | AA39: No excipients | AB39: 18.9702 | AC39: 800 | AD39: 300 | AE39: Herb | AF39: Export Only, Listed, OTC, Prescription | AG39: 1302.19.90 | AH39: Highly refined organic chemicals and substances | AI39: Not required | AJ39: Not included in any CITES Appendix | AK39: No | AP39: dairy | BA39: soy | BB39: sulfites | BH39: sodium | BI39: 0.11 | BJ39: mg | BM39: sugars | BN39: 0.035 | BO39: mg | BV39: 60157 | BW39: Camphor and cineole are mandatory components of Rosmarinus officinalis except when the plant preparation is an essential oil or distillate. In solid and semi-solid preparations, the concentration of camphor must not be more than 12.5%. In liquid preparations other than essential oils or distillates, the concentration of camphor must not be more than 2.5%. | BX39: When the concentration of cineole in the preparation other than essential oils or distillates is more than 25%, the nominal capacity of the container must not be more than 25 millilitres. In liquid preparations other than essential oils or distillates, when the concentration of cineole in the preparation is more than 25% and the nominal capacity of the container is more than 15 millilitres but less than or equal to 25 millilitres, the medicine must have a child resistant closure and restricted flow insert fitted on the container and include the following warning statements on the medicine label:- (CHILD) 'Keep out of reach of children' (or words to that effect); and - (NTAKEN) 'Not to be taken'. In liquid preparations other than essential oils or distillates, when the concentration of cineole in the preparation is more than 25% and the nominal capacity of the container is no more than 15 millilitres, the medicine must have a restricted flow insert fitted on the container and include the following warning statements on the medicine label: - (CHILD) 'Keep out of reach of children' (or words to that effect); and - (NTAKEN) 'Not to be taken'. | BY39: No warnings. | CC39: carmellose sodium | CE39: colloidal anhydrous silica | CL39: vanilla flavour | CN39: glacial acetic acid | CP39: glucose monohydrate | CW39: lecithin | CX39: magnesium stearate | CZ39: maltodextrin | DB39: microcrystalline cellulose | DF39: poliglusam | DQ39: Yes | DR39: Yes | DS39: Therapeutic range 6-12 gm daily MT TR is 400 mg - 800 mg of a 15:1 extract daily, UL 800 mg of 15:1 extract | DT39: Rosmarinus officinalis (Rosemary) herb extract (15:1) equivalent Rosmarinus officinalis dry herb equivalent rosmarinic acid (10%) | DU39: No warnings.
A40: W010050000 | B40: A | C40: 0.0029 | D40: Celery (Apium gravelens) extract (seed) (6:1) | E40: Celery | F40: A567 | G40: Apium graveolens | H40: Apium graveolens | I40: Apium graveolens | J40: seed | K40: extract dry concentrate | L40: 6:1 | M40: 70% ethanol:water | N40: - | O40: - | P40: Apium graveolens (Celery) seed ext dry conc (6:1, 70% E/W) Equiv. Apium graveolens seed dry | Q40: Apium graveolens (Celery) seed extract equivalent Apium graveolens dry seed | R40: 5 | S40: mg | T40: 30 | U40: mg | Z40: Please confirm the name and quantity of any excipients present? | AA40: 80-90% maltodextrin | AB40: 18.9362 | AC40: 1500 | AD40: 300 | AE40: Herb | AF40: Export Only, Listed, OTC, Prescription | AG40: 1302.19.90 | AH40: Highly refined organic chemicals and substances | AI40: Not required | AJ40: Not included in any CITES Appendix | AK40: No | AN40: celery | AP40: dairy | BA40: soy | BB40: sulfites | BH40: sodium | BI40: 0.1 | BJ40: mg | BM40: sugars | BN40: 0.032 | BO40: mg | BV40: 95286 | BW40: No restrictions. | BX40: No warnings. | BY40: No warnings. | CC40: carmellose sodium | CE40: colloidal anhydrous silica | CL40: vanilla flavour | CN40: glacial acetic acid | CP40: glucose monohydrate | CW40: lecithin | CX40: magnesium stearate | CZ40: maltodextrin | DB40: microcrystalline cellulose | DF40: poliglusam | DQ40: Yes | DR40: Yes | DS40: Therapeutic range 1.5 - 9 gm daily MT TR is 250 - 1000 mg of 6:1 extract daily, | DT40: Apium graveolens (Celery) seed extract (6:1) equivalent Apium graveolens dry seed | DU40: No warnings.
A41: W010052000 | B41: A | C41: 0.0054 | D41: Bacopa (Bacopa monnieri) extract (20:1) | E41: Bacopa | F41: A2714 | G41: Bacopa monnieri | H41: Bacopa monnieri | I41: Bacopa monnieri | J41: herb | K41: extract dry concentrate | L41: 20:1 | M41: 10% ethanol:water | N41: - | O41: - | P41: Bacopa monnieri (Bacopa) herb ext dry conc (20:1, 10% E/W) Equiv. Bacopa monnieri herb dry | Q41: Bacopa monnieri (Bacopa) herb extract equivalent Bacopa monnieri dry herb | R41: 5 | S41: mg | T41: 100 | U41: mg | Z41: Please confirm the name and quantity of any excipients present? | AA41: 5% maltodextrin | AB41: 18.9732 | AC41: 600 | AD41: 300 | AE41: Herb | AF41: Export Only, Listed, OTC, Prescription | AG41: 1302.19.90 | AH41: Highly refined organic chemicals and substances | AI41: Not required | AJ41: Not included in any CITES Appendix | AK41: No | AP41: dairy | BA41: soy | BB41: sulfites | BH41: sodium | BI41: 0.1 | BJ41: mg | BM41: sugars | BN41: 0.032 | BO41: mg | BR41: sugar alcohols | BS41: 1.5 | BT41: mg | BV41: 91873 | BW41: No restrictions. | BX41: No warnings. | BY41: No warnings. | CC41: carmellose sodium | CE41: colloidal anhydrous silica | CL41: vanilla flavour | CP41: glucose monohydrate | CQ41: glycerol | CT41: hypromellose | CU41: isomalt | CW41: lecithin | CX41: magnesium stearate | CZ41: maltodextrin | DB41: microcrystalline cellulose | DQ41: Yes | DR41: Yes | DS41: Therapuetic range 3-6 gm daily MT. TR 5-10 g/day BC TR 150-500 mg of a 20:1 extract daily, UL 600 mg | DT41: Bacopa monnieri (Bacopa) herb extract (20:1) equivalent Bacopa monnieri dry herb | DU41: No warnings.
A42: W010053000 | B42: A | C42: 0.0115 | D42: Coffee (Coffea arabica) extract (whole fruit) (20:1) | E42: Coffee | F42: A6004 | G42: Coffea arabica | H42: Coffea arabica | I42: Coffea arabica | J42: fruit | K42: extract dry concentrate standardised | L42: 20:1 | M42: 100% water | N42: 50% chlorogenic acid | O42: - | P42: Coffea arabica (Coffee) fruit ext dry conc std (20:1, 100% Water) Equiv. Coffea arabica fruit dry Equiv. chlorogenic acid (50%) Equiv. caffeine (7%) | Q42: Coffea arabica (Coffee) fruit extract equivalent Coffea arabica dry fruit equivalent chlorogenic acid equivalent caffeine | R42: 10 | S42: mg | T42: 200 | U42: mg | V42: 5 | W42: mg | X42: 0.7 | Y42: mg | Z42: Please confirm the caffeine content, and the name and quantity of any excipients present? | AA42: NMT 7% caffeine No excipients | AB42: 19.2702 | AC42: 800 | AD42: 300 | AE42: Herb | AF42: Export Only, Listed, OTC, Prescription | AG42: 1302.19.90 | AH42: Highly refined organic chemicals and substances | AI42: Not required | AJ42: Not included in any CITES Appendix | AK42: No | AP42: dairy | BA42: soy | BB42: sulfites | BH42: sodium | BI42: 0.11 | BJ42: mg | BM42: sugars | BN42: 0.035 | BO42: mg | BV42: 90327 | BW42: Caffeine is a mandatory component of Coffea arabica. When the medicine is packaged for supply as a divided preparation and is for internal use or oral application, the medicine must not contain a concentration of total caffeine greater than 33%. When for internal use or oral application, the maximum recommended daily dose of the medicine must provide no more than 400 mg of total caffeine. When the medicine is packaged for supply as an undivided preparation and is for internal use or oral application, the medicine must not contain a concentration of total caffeine greater than 1%. When the medicine is for internal use or oral application, a maximum recommended dose of the medicine must not provide more than 100 mg of total caffeine within a 3 hour period. | BX42: When the maximum recommended daily dose of the medicine provides greater than 10 mg of total caffeine and the medicine is for internal use or oral application, the following warning statements are required on the label: - (ADULT) 'Adults only' (or words to that effect). - (CAFF) 'Contains [state quantity per dosage unit or per mL or per gram of product] total caffeine [per dosage unit or per mL or per gram]. A cup of instant coffee contains approximately 80 mg of caffeine.' - (CAFFPREG) ‘Caffeine intake more than 200 mg per day is not recommended during pregnancy or breastfeeding.’ When the maximum recommended daily dose of the medicine provides greater than 80 mg of total caffeine and the medicines is for internal use or oral application, the following warning statements are required on the label: - (CAFFLMT) 'Limit the use of caffeine-containing products (including tea and coffee) when taking this product.' - (CAFFCYP) ‘Caffeine interacts with enzyme CYP1A2 in the liver. Consult your health professional before taking with other medicines’ (or words to that effect). | BY42: When the maximum recommended daily dose provides greater than 10 mg of total caffeine, the following warning statements are required: "Contains caffeine. Not recommended for children or pregnant/lactating women. Contains [amount of caffeine in milligrams] mg of caffeine." | CC42: carmellose sodium | CE42: colloidal anhydrous silica | CL42: vanilla flavour | CN42: glacial acetic acid | CP42: glucose monohydrate | CW42: lecithin | CX42: magnesium stearate | CZ42: maltodextrin | DB42: microcrystalline cellulose | DF42: poliglusam | DQ42: Yes | DR42: Yes | DS42: Therauetic range 100-600 mg, higher doses antioxidant status https://pubmed.ncbi.nlm.nih.gov/19089749/ TR is 100mg - 800 mg of a 20:1 extract daily, UL 800 mg = 56mg caffeine. ML - RD =300 Based on 6g to 12g for single dose | DT42: Coffea arabica (Coffee) fruit extract (20:1) equivalent Coffea arabica dry fruit equivalent chlorogenic acid (50%) equivalent caffeine (7%) | DU42: "Contains [state quantity per dosage unit or per mL or per gram] total caffeine [per dosage unit or per mL or per gram]. A cup of instant coffee contains approximately 80mg of caffeine." "Caffeine intake more than 200 mg per day is not recommended for use by pregnant and lactating women." "Limit the use of caffeine containing products (including tea and coffee) when taking this product.." "Caffeine interacts with enzyme CYP1A2 in the liver. Consult a health professional before taking with other medicines."
A43: W010058000 | B43: A | C43: 0.0029 | D43: Sage (Salvia officinalis) extract (leaf) (5:1) | E43: Sage | F43: A2677 | G43: Salvia officianalis | H43: Salvia officinalis | I43: Salvia officinalis | J43: leaf | K43: extract dry concentrate | L43: 5:1 | M43: 100% water | N43: - | O43: - | P43: Salvia officinalis (Sage) leaf ext dry conc (5:1, 100% water) Equiv. Salvia officinalis leaf dry | Q43: Salvia officinalis (Sage) leaf extract equivalent Salvia officinalis dry leaf | R43: 10 | S43: mg | T43: 50 | U43: mg | Z43: Please confirm the name and quantity of any excipients present? | AA43: 10% maltodextrin | AB43: 19.4472 | AC43: 2000 | AD43: 300 | AE43: Herb | AF43: Export Only, Listed, OTC, Prescription | AG43: 1302.19.90 | AH43: Highly refined organic chemicals and substances | AI43: Not required | AJ43: Not included in any CITES Appendix | AK43: No | AP43: dairy | BA43: soy | BB43: sulfites | BH43: sodium | BI43: 0.1 | BJ43: mg | BM43: sugars | BN43: 0.033 | BO43: mg | BV43: 61834 | BW43: Thujone is a mandatory component of Salvia officinalis. The concentration of thujone in the medicine must be no more than 4%. | BX43: No warnings. | BY43: No warnings. | CC43: carmellose sodium | CE43: colloidal anhydrous silica | CL43: vanilla flavour | CN43: glacial acetic acid | CP43: glucose monohydrate | CW43: lecithin | CX43: magnesium stearate | CZ43: maltodextrin | DB43: microcrystalline cellulose | DF43: poliglusam | DQ43: Yes | DR43: Yes | DS43: Therapeutic range 3-12 gm daily MT BC TR is 300 mg - 1500 mg of a 5:1 extract UL 2000 mg | DT43: Salvia officinalis (Sage) leaf extract (5:1) equivalent Salvia officinalis dry leaf | DU43: No warnings.
A44: W010060000 | B44: A | C44: 0.0077 | D44: Flavonoids | E44: Ginkgo | F44: A318 | G44: Ginkgo biloba | H44: Ginkgo biloba | I44: Ginkgo biloba | J44: leaf | K44: extract dry concentrate standardised | L44: 50:1 | M44: 50% ethanol:water | N44: 24% flavonoids | O44: - | P44: Ginkgo biloba (Ginkgo) leaf ext dry conc (50:1, 50% E/W) Equiv. Ginkgo biloba leaf dry Equiv. Flavonoids (24%) | Q44: Ginkgo biloba (Ginkgo) leaf extract equivalent Ginkgo biloba dry leaf equivalent flavonoids | R44: 5 | S44: mg | T44: 250 | U44: mg | V44: 1.2 | W44: mg | Z44: Please confirm the name and quantity of any excipients present? | AA44: No excipients | AB44: 19.4502 | AC44: 360 | AD44: 80 | AE44: Herb | AF44: Export Only, Listed, OTC, Prescription | AG44: 1302.19.90 | AH44: Highly refined organic chemicals and substances | AI44: Not required | AJ44: Not included in any CITES Appendix | AK44: No | AP44: dairy | BA44: soy | BB44: sulfites | BH44: sodium | BI44: 0.1 | BJ44: mg | BM44: sugars | BN44: 0.033 | BO44: mg | BV44: 67157 | BW44: The Ginkgo biloba leaf extract used in the manufacture of this medicine must comply with the requirement of Identification Test B of the monograph Powdered Ginkgo Extract in the United States Pharmacopeia 32 - National Formulary 27 (USP32-NF27), as in force or existing from time to time. This condition does not apply to powdered or dried leaf. | BX44: No warnings. | BY44: No warnings. | CC44: carmellose sodium | CE44: colloidal anhydrous silica | CL44: vanilla flavour | CN44: glacial acetic acid | CP44: glucose monohydrate | CW44: lecithin | CX44: magnesium stearate | DB44: microcrystalline cellulose | DF44: poliglusam | DQ44: Yes | DR44: Yes | DS44: Therapeutic range 9-10 gm daily BC, MT TR is 40 mg -240 mg of a 50:1 extract extract is recommended at 360 mg but tds (use as UL) YSCP confirmed - 480mg (DeKosky et al., JAMA 2008 and Vellas et al., Lancet Neurology 2012) Bergamot: Evidence-Based Clinical Dosing 500-1000mg daily. ((Mollace et al., 2011; Toth et al., 2016) ML recommended dose Based on EGb761 studies | DT44: Ginkgo biloba (Ginkgo) leaf extract (50:1) equivalent Ginkgo biloba dry leaf equivalent flavonoids (24%) | DU44: No warnings.
A45: W010061000 | B45: A | C45: 0.008 | D45: Oleuropein | E45: Olive leaf | F45: A327 | G45: Olea europaea | H45: Olea europaea | I45: Olea europaea | J45: leaf | K45: extract dry concentrate standardised | L45: 10:1 | M45: 75% ethanol:water | N45: 20% oleuropein | O45: - | P45: Olea europaea (olive) leaf ext dry ext conc std. 10:1 (75% Ethanol:water) Equiv. Olea europaea leaf dry Equiv. Oleuropein 20% | Q45: Olea europaea (Olive) leaf extract equivalent Olea europaea dry leaf equivalent oleuropein | R45: 10 | S45: mg | T45: 100 | U45: mg | V45: 2 | W45: mg | Z45: - | AB45: 17.4012 | AC45: 1000 | AD45: 250 | AE45: Herb | AF45: Export Only, Listed, OTC, Prescription | AG45: 1302.19.90 | AH45: Highly refined organic chemicals and substances | AI45: Not required | AJ45: Not included in any CITES Appendix | AK45: No | AP45: dairy | BA45: soy | BB45: sulfites | BH45: sodium | BI45: 0.09 | BJ45: mg | BM45: sugars | BN45: 0.03 | BO45: mg | BV45: 76064 | BW45: No restrictions. | BX45: No warnings. | BY45: No warnings. | CC45: carmellose sodium | CE45: colloidal anhydrous silica | CL45: vanilla flavour | CN45: glacial acetic acid | CP45: glucose monohydrate | CW45: lecithin | CX45: magnesium stearate | DB45: microcrystalline cellulose | DF45: poliglusam | DQ45: Yes | DR45: Yes | DS45: Therapeutic range 2-4 gm daily MT TR is 200- 400 mg of a 10:1 extract daily ul= 1000 | DT45: Olea europaea (Olive) leaf extract (10:1) equivalent Olea europaea dry leaf equivalent oleuropein (20%) | DU45: No warnings.
A46: W010062000 | B46: A | C46: 0.0099 | D46: Hypericin | E46: St John's Wort | F46: A2792 | G46: Hypericum perforatum | H46: Hypericum perforatum | I46: Hypericum perforatum | J46: herb | K46: extract dry concentrate standardised | L46: 6:1 | M46: 60% ethanol:water | N46: 0.3% hypericin | O46: - | P46: Hypericum perforatum (St John's Wort) herb ext dry conc std (6:1, 60% E/W) Equiv. Hypericum perforatum herb dry Equiv. Hypericin (0.3%) | Q46: Hypericum perforatum (St John's Wort) herb extract equivalent Hypericum perforatum dry herb equivalent hypericin | R46: 10 | S46: mg | T46: 60 | U46: mg | V46: 0.03 | W46: mg | Z46: Please confirm the name and quantity of any excipients present? | AA46: No excipients | AB46: 18.9362 | AC46: 1200 | AD46: 450 | AE46: Herb | AF46: Export Only, Listed, OTC, Prescription | AG46: 1302.19.90 | AH46: Highly refined organic chemicals and substances | AI46: Not required | AJ46: Not included in any CITES Appendix | AK46: No | AP46: dairy | BA46: soy | BB46: sulfites | BH46: sodium | BI46: 0.1 | BJ46: mg | BM46: sugars | BN46: 0.032 | BO46: mg | BR46: sugar alcohols | BS46: 2 | BT46: mg | BV46: 59155 | BW46: No restrictions. | BX46: When used for oral ingestion, the medicine requires the following warning statement on the medicine label: - (STJOHN) 'St John's Wort affects the way many prescription medicines work including oral contraceptives. Consult your doctor.' | BY46: No warnings. | CC46: carmellose sodium | CE46: colloidal anhydrous silica | CL46: vanilla flavour | CN46: glacial acetic acid | CP46: glucose monohydrate | CU46: isomalt | CW46: lecithin | CX46: magnesium stearate | DB46: microcrystalline cellulose | DF46: poliglusam | DQ46: Yes | DR46: Yes | DS46: Therapeutic range 2-5 gm daily BC, 3.6 - 7.2 gm daily KB TR is 350 mg - 900 mg of a 6:1 extract daily | DT46: Hypericum perforatum (St John's Wort) herb extract (6:1) equivalent Hypericum perforatum dry herb equivalent hypericin (0.3%) | DU46: "St John's Wort affects the way many prescription medicines work including oral contraceptives." "Consult a healthcare professional before use."
A47: W010065000 | B47: A | C47: 0.0093 | D47: Lavandula angustifolia (Lavender) flower extract 10:1 | E47: Lavender | F47: A2178 | G47: Lavandula angustifolia | H47: Lavandula angustifolia | I47: Lavandula angustifolia | J47: flower | K47: extract dry concentrate | L47: 10:1 | M47: 50% ethanol:water | N47: - | O47: - | P47: Lavandula angustifolia (Lavender) flower ext dry conc (10:1, 50% E/W) Equiv. Lavandula angustifolia flower dry | Q47: Lavandula angustifolia (Lavender) flower extract equivalent Lavandula angustifolia dry flower | R47: 10 | S47: mg | T47: 100 | U47: mg | Z47: Please confirm the name and quantity of any excipients present? | AA47: No excipients | AB47: 17.9502 | AC47: 500 | AD47: 250 | AE47: Herb | AF47: Export Only, Listed, OTC, Prescription | AG47: 1302.19.90 | AH47: Highly refined organic chemicals and substances | AI47: Not required | AJ47: Not included in any CITES Appendix | AK47: No | AP47: dairy | BA47: soy | BB47: sulfites | BH47: sodium | BI47: 0.1 | BJ47: mg | BM47: sugars | BN47: 0.031 | BO47: mg | BV47: 74583 | BW47: Camphor is a mandatory component of Lavandula angustifolia. In solid and semi solid preparations, the concentration of camphor must be no more than 12.5%. In liquid preparations other than essential oils or distillates, the concentration of camphor must be no more than 2.5%. | BX47: No warnings. | BY47: No warnings. | CC47: carmellose sodium | CE47: colloidal anhydrous silica | CL47: vanilla flavour | CP47: glucose monohydrate | CQ47: glycerol | CT47: hypromellose | CW47: lecithin | CX47: magnesium stearate | DB47: microcrystalline cellulose | DQ47: Yes | DR47: Yes | DS47: TR 2-4 gm daily BC TR is 200-400 mg daily of a 10:1 extract | DT47: Lavandula angustifolia (Lavender) flower extract (10:1) equivalent Lavandula angustifolia dry flower | DU47: No warnings.
A48: W010066000 | B48: A | C48: 0.0115 | D48: Chamomile | E48: Chamomile | F48: A2427 | G48: Matricaria chamomilla | H48: Matricaria chamomilla | I48: Matricaria chamomilla | J48: flower | K48: extract dry concentrate | L48: 5:1 | M48: 100% water | N48: - | O48: - | P48: Matricaria chamomilla Flower Ext Dry Conc. (5:1 in 100% Water) Equiv. Matricaria chamomilla flower dry Contain: 25%Maltodextrin, 2% Silicon dioxide | Q48: Matricaria chamomilla (Chamomile) flower extract equivalent Matricaria chamomilla dry flower | R48: 10 | S48: mg | T48: 50 | U48: mg | Z48: - | AB48: 18.4702 | AC48: 1800 | AD48: 250 | AE48: Herb | AF48: Export Only, Listed, OTC, Prescription | AG48: 1302.19.90 | AH48: Highly refined organic chemicals and substances | AI48: Not required | AJ48: Not included in any CITES Appendix | AK48: No | AP48: dairy | BA48: soy | BB48: sulfites | BH48: sodium | BI48: 0.11 | BJ48: mg | BM48: sugars | BN48: 0.035 | BO48: mg | BV48: 108207 | BW48: No restrictions. | BX48: No warnings. | BY48: No warnings. | CC48: carmellose sodium | CE48: colloidal anhydrous silica | CL48: vanilla flavour | CN48: glacial acetic acid | CP48: glucose monohydrate | CW48: lecithin | CX48: magnesium stearate | CZ48: maltodextrin | DB48: microcrystalline cellulose | DF48: poliglusam | DH48: silicon dioxide | DQ48: Yes | DR48: Yes | DS48: Therapeutic range 900-1800 mg KB, 6-12 G MT TR is 200 - 1200 mg of a 5:1 extract | DT48: Matricaria chamomilla (Chamomile) flower extract (5:1) equivalent Matricaria chamomilla dry flower | DU48: No warnings.
A49: W010067000 | B49: A | C49: 0.0122 | D49: Agnuside | E49: Chaste tree (Vitex) | F49: A2234 | G49: Vitex agnus-castus | H49: Vitex agnus-castus | I49: Vitex agnus-castus | J49: fruit | K49: extract dry concentrate standardised | L49: 10:1 | M49: 80% ethanol:water | N49: 0.83% agnuside | O49: - | P49: Vitex agnus-castus (Chaste tree) fruit ext dry conc std (10:1, 80% E/W) Equiv. Vitex agnus-castus fruit dry Equiv. Agnuside (0.83%) | Q49: Vitex agnus-castus (Chaste tree) fruit extract equivalent Vitex agnus-castus dry fruit equivalent agnuside | R49: 10 | S49: mg | T49: 100 | U49: mg | V49: 0.083 | W49: mg | Z49: Please confirm the name and quantity of any excipients present? | AA49: 10% maltodextrin | AB49: 19.4472 | AC49: 400 | AD49: 10 | AE49: Herb | AF49: Export Only, Listed, OTC, Prescription | AG49: 1302.19.90 | AH49: Highly refined organic chemicals and substances | AI49: Not required | AJ49: Not included in any CITES Appendix | AK49: No | AP49: dairy | BA49: soy | BB49: sulfites | BH49: sodium | BI49: 0.1 | BJ49: mg | BM49: sugars | BN49: 0.033 | BO49: mg | BR49: sugar alcohols | BS49: 6.25 | BT49: mg | BV49: 70352 | BW49: No restrictions. | BX49: When the ingredient is in a medicine that is for internal use, the following warning statement is required on the label:- (VAC) 'Vitex agnus-castus may affect hormones and medicines such as oral contraceptives. Consult your health professional before use' (or words to that effect). | BY49: No warnings. | CC49: carmellose sodium | CE49: colloidal anhydrous silica | CL49: vanilla flavour | CN49: glacial acetic acid | CP49: glucose monohydrate | CU49: isomalt | CW49: lecithin | CX49: magnesium stearate | CZ49: maltodextrin | DF49: poliglusam | DQ49: Yes | DR49: Yes | DS49: Therapeutic range 3-6 gm daily MT bone 0.25-3g daily TR is 25- 300 mg of a 10:1 extract daily | DT49: Vitex agnus-castus (Chaste tree) fruit extract (10:1) equivalent Vitex agnus-castus dry fruit equivalent agnuside (0.83%) | DU49: "Vitex agnus-castus may affect hormones and medicines such as oral contraceptives." "Consult a health professional before use."
A50: W010069000 | B50: A | C50: 0.0128 | D50: Bergamot | E50: Bergamot | F50: A2962 | G50: Citrus aurantium | H50: Citrus aurantium | I50: Citrus aurantium | J50: fruit | K50: extract dry concentrate standardised | L50: 150-170:1 | M50: n/a concentrated from the filtered juice and pulp | N50: neoeriocitrin, naringin, neohesperidin, melitidin, and bruteridin | O50: - | P50: Citrus aurantium bergamia Fruit Ext Dry Conc (150-170:1) Equiv. Citrus aurantium bergamia dry fruit Equiv. Neoeriocitrin, naringin, neohesperidin, melitidin, and bruteridin (NLT 38% total) Equiv. Oxedrine | Q50: Citrus aurantium bergamia (Bergamot) fruit extract equivalent Citrus aurantium bergamia dry fruit equivalent neoeriocitrin, naringin, neohesperidin, melitidin, and bruteridin (total) | R50: 5 | S50: mg | T50: 750 | U50: mg | V50: 1.9 | W50: mg | Z50: Please confirm the extraction solvents, standardisation, oxedrine content, and the name and quantity of any excipients present? | AA50: 150-170:1 neoeriocitrin, naringin, neohesperidin, melitidin, bruteridin No excipients DOES NOT contain Synephrine NOT standardised for Oxedrine | AB50: 18.9702 | AC50: 750 | AD50: 500 | AE50: Herb | AF50: Export Only, Listed, OTC, Prescription | AG50: 1302.19.90 | AH50: Highly refined organic chemicals and substances | AI50: Not required | AJ50: Not included in any CITES Appendix | AK50: No | AP50: dairy | BA50: soy | BB50: sulfites | BH50: sodium | BI50: 0.11 | BJ50: mg | BM50: sugars | BN50: 0.035 | BO50: mg | BR50: sugar alcohols | BS50: 2.8 | BT50: mg | BV50: 68599 | BW50: Oxedrine is a mandatory component of Citrus aurantium (bergamia) when intended for internal use. The quantity of oxedrine in the maximum recommended daily dose must be no more than 30 mg. | BX50: Oxedrine is a mandatory component of Citrus aurantium (bergamia) when intended for internal use. The quantity of oxedrine in the maximum recommended daily dose must be no more than 30 mg. When the plant preparation is oil or distillate, the warning statement (SENS) 'Application to skin may increase sensitivity to sunlight' (or words to that effect) must be included on the medicine label unless the medicine is: a) for internal use; or b) in preparations containing 1.4% or less of citrus aurantium oil or distillate; or c) for use in soaps or bath or shower gels that are washed off the skin. | BY50: No warnings. | CC50: carmellose sodium | CE50: colloidal anhydrous silica | CL50: vanilla flavour | CN50: glacial acetic acid | CP50: glucose monohydrate | CU50: isomalt | CW50: lecithin | CX50: magnesium stearate | DB50: microcrystalline cellulose | DF50: poliglusam | DQ50: Yes | DR50: Yes | DS50: TR 500-1500 mg daily of a 150:1 extract BC check dried herb amount YSCP - Evidence-Based Clinical Dosing 500-1000mg daily. (Mollace et al., 2011; Toth et al., 2016) DOES NOT contain Synephrine - This is not Bitter Orange. Only Bitter Orange contains Synephrin | DT50: Citrus aurantium bergamia (Bergamot) fruit extract (150:1) equivalent Citrus aurantium bergamia dry fruit equivalent neoeriocitrin, naringin, neohesperidin, melitidin, and bruteridin (total) (38%) | DU50: No warnings.
A51: W010072000 | B51: A | C51: 0.0029 | D51: Tart cherry (Prunus cerasus) extract (fruit) (13:1) | E51: Tart cherry | F51: A2562 | G51: Prunus cerasus | H51: Prunus cerasus | I51: Prunus cerasus | J51: fruit | K51: extract dry concentrate | L51: 13:1 | M51: 100% water | N51: - | O51: - | P51: Prunus cerasus (Tart Cherry) Fruit Ext. Dry Conc. (13:1 in 100% water) Equiv. Prunus cerasus fruit dry | Q51: Prunus cerasus (Tart cherry) fruit extract equivalent Prunus cerasus dry fruit | R51: 12.5 | S51: mg | T51: 162.5 | U51: mg | Z51: - | AB51: 19.4852 | AC51: 1200 | AD51: 500 | AE51: Herb | AF51: Export Only, Listed, OTC, Prescription | AG51: 1302.19.90 | AH51: Highly refined organic chemicals and substances | AI51: Not required | AJ51: Not included in any CITES Appendix | AK51: No | AP51: dairy | BA51: soy | BB51: sulfites | BH51: sodium | BI51: 0.1 | BJ51: mg | BM51: sugars | BN51: 0.033 | BO51: mg | BV51: 64276 | BW51: Amygdalin and hydrocyanic acid are mandatory components of Prunus cerasus. The concentration of amygdalin in the medicine must not be more than 10 mg/kg. The concentration of hydrocyanic acid in the medicine must not be more than 10 mg/kg. | BX51: No warnings. | BY51: No warnings. | CC51: carmellose sodium | CE51: colloidal anhydrous silica | CL51: vanilla flavour | CP51: glucose monohydrate | CQ51: glycerol | CT51: hypromellose | CW51: lecithin | CX51: magnesium stearate | CZ51: maltodextrin | DB51: microcrystalline cellulose | DQ51: Yes | DR51: Yes | DS51: TR 300 mg - 900 mg of a 13:1 extract daily | DT51: Prunus cerasus (Tart cherry) fruit extract (13:1) equivalent Prunus cerasus dry fruit | DU51: No warnings.
A52: W010075000 | B52: A | C52: 0.0077 | D52: Gymnema sylvestre extract (leaf) (20:1) | E52: Gymnema | F52: A920 | G52: Gymnema sylvestre | H52: Gymnema sylvestre | I52: Gymnema sylvestre | J52: leaf | K52: extract dry concentrate | L52: 20:1 | M52: 100% water | N52: - | O52: - | P52: Gymnema sylvestre Leaf Ext. Dry Conc. (20:1 in Water) Equiv. Gymnema sylvestre Leaf dry Contain: Maltodextrin (8%) | Q52: Gymnema sylvestre (Gymnema) leaf extract equivalent Gymnema sylvestre dry leaf | R52: 5 | S52: mg | T52: 100 | U52: mg | Z52: - | AB52: 17.4702 | AC52: 800 | AD52: 400 | AE52: Herb | AF52: Export Only, Listed, OTC, Prescription | AG52: 1302.19.90 | AH52: Highly refined organic chemicals and substances | AI52: Not required | AJ52: Not included in any CITES Appendix | AK52: No | AP52: dairy | BA52: soy | BB52: sulfites | BH52: sodium | BI52: 0.092 | BJ52: mg | BM52: sugars | BN52: 0.029 | BO52: mg | BR52: sugar alcohols | BS52: 5.4 | BT52: mg | BV52: 69613 | BW52: No restrictions. | BX52: No warnings. | BY52: No warnings. | CC52: carmellose sodium | CE52: colloidal anhydrous silica | CL52: vanilla flavour | CN52: glacial acetic acid | CP52: glucose monohydrate | CU52: isomalt | CW52: lecithin | CX52: magnesium stearate | CZ52: maltodextrin | DB52: microcrystalline cellulose | DF52: poliglusam | DQ52: Yes | DR52: Yes | DS52: TR 3-9 gm daily MT TR range 150 - 450 mg of a 20:1 extract daily | DT52: Gymnema sylvestre (Gymnema) leaf extract 20:1) equivalent Gymnema sylvestre dry leaf | DU52: No warnings.
A53: W010078000 | B53: A | C53: 0.0064 | D53: Crataegus monogyna Fruit Ext. Dry Conc.(4:1) | E53: Hawthorn | F53: A382 | G53: Crataegus monogyna | H53: Crataegus monogyna | I53: Crataegus monogyna | J53: fruit | K53: extract dry concentrate | L53: 4:1 | M53: 50% ethanol:water | N53: - | O53: - | P53: Crataegus monogyna (Hawthorn) fruit ext dry conc 4:1, 50% E/W Equiv. Crataegus monogyna fruit dry | Q53: Crataegus monogyna (Hawthorn) fruit extract equivalent Crataegus monogyna dry fruit | R53: 10 | S53: mg | T53: 40 | U53: mg | Z53: Please confirm the name and quantity of any excipients present? | AA53: 20% maltodextrin | AB53: 18.8102 | AC53: 1800 | AD53: 500 | AE53: Herb | AF53: Export Only, Listed, OTC, Prescription | AG53: 1302.19.90 | AH53: Highly refined organic chemicals and substances | AI53: Not required | AJ53: Not included in any CITES Appendix | AK53: No | AP53: dairy | BA53: soy | BB53: sulfites | BH53: sodium | BI53: 0.1 | BJ53: mg | BM53: sugars | BN53: 0.031 | BO53: mg | BV53: 83941 | BW53: No restrictions. | BX53: No warnings. | BY53: No warnings. | CC53: carmellose sodium | CE53: colloidal anhydrous silica | CL53: vanilla flavour | CP53: glucose monohydrate | CQ53: glycerol | CT53: hypromellose | CW53: lecithin | CX53: magnesium stearate | CZ53: maltodextrin | DB53: microcrystalline cellulose | DQ53: Yes | DR53: Yes | DS53: TR 1-3 gm daily MT, 3-4 gm daily KB TR 250 mg - 1000 mg of a 4:1 extract | DT53: Crataegus monogyna (Hawthorn) fruit extract (4:1) equivalent Crataegus monogyna dry fruit | DU53: No warnings.
A54: W010084000 | B54: A | C54: 0.0093 | D54: Coleus forskohlii | E54: Coleus (forskolin) | F54: A2533 | G54: Coleus forskohlii | H54: Coleus forskohlii | I54: Plectranthus barbatus | J54: root | K54: extract dry concentrate standardised | L54: 35:1 | M54: 50% ethanol:water | N54: 10% forskolin | P54: Plectranthus barbatus (Coleus) root ext dry conc std 35:1, 50% E/W Equiv. Plectranthus barbatus root dry Equiv. Forskolin (10%) | Q54: Plectranthus barbatus (Coleus) root extract equivalent Plectranthus barbatus dry root equivalent forskolin | R54: 5 | S54: mg | T54: 175 | U54: mg | V54: 0.5 | W54: mg | Z54: - | AB54: 17.45 | AC54: 200 | AD54: 125 | AE54: Herb | AF54: Export Only, Listed, OTC, Prescription | AG54: 1302.19.90 | AH54: Highly refined organic chemicals and substances | AI54: Not required | AJ54: Not included in any CITES Appendix | AK54: No | AP54: dairy | BA54: soy | BB54: sulfites | BH54: sodium | BI54: 0.092 | BJ54: mg | BM54: sugars | BN54: 0.03 | BO54: mg | BV54: 84962 | BW54: No restrictions. | BX54: No warnings. | BY54: No warnings. | CC54: carmellose sodium | CE54: colloidal anhydrous silica | CL54: vanilla flavour | CP54: glucose monohydrate | CQ54: glycerol | CT54: hypromellose | CW54: lecithin | CX54: magnesium stearate | CZ54: maltodextrin | DB54: microcrystalline cellulose | DQ54: Yes | DR54: Yes | DS54: TR 3-6 gm daily MT TR 85mg - 175 mg of a 35:1 extract daily | DT54: Plectranthus barbatus (Coleus) root extract (35:1) equivalent Plectranthus barbatus dry root equivalent forskolin (10%) | DU54: No warnings.
A55: W010089000 | B55: A | C55: 0.0096 | D55: Cardamom (Elettaria cardamomum) extract | E55: Cardamom | F55: A3469/1100674 | G55: Elettaria cardamomum | H55: Elettaria cardamomum | I55: Elettaria cardamomum | J55: seed | K55: extract dry concentrate | L55: 2:1 | M55: 60% ethanol:water | N55: - | O55: - | P55: Elettaria cardamomum (Cardamon) seed dry ext conc. 2:1 (60:40 E:W) Equiv. Elettaria cardamomum seed dry | Q55: Elettaria cardamomum (Cardamom) fruit extract equivalent Elettaria cardamomum dry fruit | R55: 10 | S55: mg | T55: 20 | U55: mg | Z55: - | AB55: 18.4602 | AC55: 3000 | AD55: 500 | AE55: Herb | AF55: Export Only, Listed, OTC, Prescription | AG55: 1302.19.90 | AH55: Highly refined organic chemicals and substances | AI55: Not required | AJ55: Not included in any CITES Appendix | AK55: No | AP55: dairy | BA55: soy | BB55: sulfites | BH55: sodium | BI55: 0.1 | BJ55: mg | BM55: sugars | BN55: 0.031 | BO55: mg | BV55: 60200 | BW55: No restrictions. | BX55: No warnings. | BY55: No warnings. | CC55: carmellose sodium | CE55: colloidal anhydrous silica | CL55: vanilla flavour | CP55: glucose monohydrate | CQ55: glycerol | CT55: hypromellose | CW55: lecithin | CX55: magnesium stearate | DB55: microcrystalline cellulose | DQ55: Yes | DR55: Yes | DS55: Agreed TR ML - Traditional use 500mg instead of 1000mg | DT55: Elettaria cardamomum (Cardamom) fruit extract 2:1 equivalent Elettaria cardamomum dry fruit | DU55: No warnings.
A56: W010090000 | B56: A | C56: 0.0157 | D56: Saffron | E56: Saffron | F56: A2830/1100667 | G56: Crocus sativus | H56: Crocus sativus | I56: Crocus sativus | J56: stigma | K56: extract dry concentrate standardised | L56: 4:1 | M56: 30% ethanol:water | N56: 0.3% safranal | O56: - | P56: Crocus sativus (Saffron) stigma extract dry std 4:1, 30% E/W Equiv. Crocus sativus dry stigma Equiv. safranal (0.3%) | Q56: Crocus sativus (Saffron) stigma extract equivalent Crocus sativus dry stigma equivalent safranal | R56: 10 | S56: mg | T56: 40 | U56: mg | V56: 0.03 | W56: mg | Z56: Please confirm the name and quantity of any excipients present? | AA56: 5% maltodextrin | AB56: 17.9602 | AC56: 100 | AD56: 30 | AE56: Herb | AF56: Export Only, Listed, OTC, Prescription | AG56: 1302.19.90 | AH56: Highly refined organic chemicals and substances | AI56: Not required | AJ56: Not included in any CITES Appendix | AK56: No | AP56: dairy | BA56: soy | BB56: sulfites | BH56: sodium | BI56: 0.1 | BJ56: mg | BM56: sugars | BN56: 0.031 | BO56: mg | BR56: sugar alcohols | BS56: 1 | BT56: mg | BV56: 66688 | BW56: When Crocus sativus is used as an excipient: (a) the ingredient must only be included in medicines when in combination with other permitted ingredients as a flavour proprietary excipient formulation; (b) the plant part must be stigma and/or style; (c) the plant preparation must be fresh or dry; and (d) the total concentration of flavour proprietary excipient formulations containing the ingredient must not be more than 5% of the total medicine. | BX56: No warnings. | BY56: No warnings. | CC56: carmellose sodium | CE56: colloidal anhydrous silica | CL56: vanilla flavour | CP56: glucose monohydrate | CQ56: glycerol | CT56: hypromellose | CU56: isomalt | CW56: lecithin | CX56: magnesium stearate | CZ56: maltodextrin | DB56: microcrystalline cellulose | DQ56: Yes | DR56: Yes | DS56: TR 30 - 100 mg daily BC TR is 30-60 mg of a 3:1 extract daily | DT56: Crocus sativus (Saffron) stigma extract (4:1) equivalent Crocus sativus dry stigma equivalent safranal (0.3%) | DU56: No warnings.
A57: W010091000 | B57: A | C57: 0.0086 | D57: Cordyceps | E57: Cordyceps | F57: A2387 | G57: Cordyceps sinensis | H57: Cordyceps sinensis | I57: Cordyceps sinensis | J57: mycelium | K57: extract dry concentrate standardised | L57: 3:1 | M57: 100% water | N57: 0.3% adenosine | O57: - | P57: Cordyceps sinensis (Cordyceps) mycellium ext dry conc std 3:1, 100% water Equiv. Cordyceps sinensis mycellium dry Equiv. Adenosine (0.3%) | Q57: Cordyceps sinensis (Cordyceps) mycellium extract equivalent Cordyceps sinensis dry mycellium equivalent adenosine | R57: 10 | S57: mg | T57: 30 | U57: mg | V57: 0.03 | W57: mg | Z57: Please confirm the name and quantity of any excipients present? | AA57: 20% maltodextrin | AB57: 18.4602 | AC57: 1300 | AD57: 350 | AE57: Herb | AF57: Export Only, Listed, OTC, Prescription | AG57: 1302.19.90 | AH57: Mushrooms for human consumption | AI57: Not required | AJ57: Not included in any CITES Appendix | AK57: No | AP57: dairy | BA57: soy | BB57: sulfites | BH57: sodium | BI57: 0.1 | BJ57: mg | BM57: sugars | BN57: 0.031 | BO57: mg | BR57: sugar alcohols | BS57: 5.84 | BT57: mg | BV57: 96573 | BW57: Must not contain material of animal origin such as insect larvae. | BX57: No warnings. | BY57: No warnings. | CC57: carmellose sodium | CE57: colloidal anhydrous silica | CL57: vanilla flavour | CP57: glucose monohydrate | CQ57: glycerol | CT57: hypromellose | CU57: isomalt | CW57: lecithin | CX57: magnesium stearate | CZ57: maltodextrin | DQ57: Yes | DR57: Yes | DS57: TR 1-3 gm daily Martin Powell TR is 350-1,000 mg of a 3:1 extract | DT57: Cordyceps sinensis (Cordyceps) mycellium extract (3:1) equivalent Cordyceps sinensis dry mycellium equivalent adenosine (0.3%) | DU57: No warnings.
A58: W020001000 | B58: A | C58: 0.0029 | D58: Glucosamine sulfate | E58: Glucosamine sulfate | F58: A266 | G58: Glucosamine sulfate | H58: - | I58: Glucosamine sulfate sodium chloride | J58: - | K58: - | L58: - | M58: - | N58: - | P58: Glucosamine sulfate sodium chloride Equiv. glucosamine sulfate (79.6%) | Q58: Glucosamine sulfate sodium chloride equivalent glucosamine sulfate | R58: 12.56 | S58: mg | T58: 9.997 | U58: mg | Z58: Please confirm the relevant equivalence? | AA58: equivalent glucosamine sulfate (79.6%) 10mg | AB58: 22.0462 | AC58: 1500 | AD58: 1500 | AE58: Natural | AF58: Export Only, Listed, OTC, Prescription | AG58: 2932.99.00 | AH58: Human therapeutics and medicines | AI58: Required (fermentation source), Not required (shellfish source) | AJ58: Not included in any CITES Appendix | AK58: No | AO58: crustacean | AP58: dairy | BA58: soy | BB58: sulfites | BH58: sodium | BI58: 0.12 | BJ58: mg | BM58: sugars | BN58: 0.038 | BO58: mg | BV58: 101813 | BW58: No restrictions. | BX58: No warnings. | BY58: No warnings. | CC58: carmellose sodium | CE58: colloidal anhydrous silica | CL58: vanilla flavour | CP58: glucose monohydrate | CQ58: glycerol | CT58: hypromellose | CW58: lecithin | CX58: magnesium stearate | CZ58: maltodextrin | DB58: microcrystalline cellulose | DQ58: Yes | DR58: Yes | DS58: TR 1000- 1500 mg/day BC upper range? | DT58: Glucosamine sulfate sodium chloride equivalent glucosamine sulfate (79.6%) | DU58: No warnings.
A59: W020002000 | B59: A | C59: 0.0035 | D59: Chondroitin sulfate | E59: Chondroitin sulfate | F59: A039 | G59: Chondroitin sulfate | H59: - | I59: Bovine sodium chondroitin sulfate | J59: - | K59: - | L59: - | M59: - | N59: - | P59: Bovine sodium chondroitin sulfate Equiv. Chondroitin sulfate (81%) | Q59: Bovine sodium chondroitin sulfate equivalent chondroitin sulfate | R59: 12.35 | S59: mg | T59: 10.003 | U59: mg | Z59: Please confirm the relevant equivalence? | AA59: equivalent chondroitin sulfate (81%) 10mg | AB59: 19.4802 | AC59: 1500 | AD59: 800 | AE59: Natural | AF59: Export Only, Listed, OTC, Prescription | AG59: 3913.90.00 | AH59: Human therapeutics and medicines | AI59: Required (bovine source) | AJ59: Not included in any CITES Appendix | AK59: No | AP59: dairy | BA59: soy | BB59: sulfites | BH59: sodium | BI59: 0.1 | BJ59: mg | BM59: sugars | BN59: 0.033 | BO59: mg | BR59: sugar alcohols | BS59: 3 | BT59: mg | BV59: 102244 | BW59: No restrictions. | BX59: No warnings. | BY59: No warnings. | CC59: carmellose sodium | CE59: colloidal anhydrous silica | CL59: vanilla flavour | CP59: glucose monohydrate | CQ59: glycerol | CT59: hypromellose | CU59: isomalt | CW59: lecithin | CX59: magnesium stearate | DB59: microcrystalline cellulose | DQ59: Yes | DR59: Yes | DS59: 800-1200 mg/day. Considered extremely safe with v low incidence of adverse reactions BC TR is 800-1200 mg daily | DT59: Bovine sodium chondroitin sulfate equivalent chondroitin sulfate (81%) | DU59: No warnings.
A60: W030001000 | B60: A | C60: 0.0016 | D60: Vitamin C (as ascorbic acid) | E60: Vitamin C | F60: I078 | G60: Ascorbic acid | H60: - | I60: Ascorbic acid | J60: - | K60: - | L60: - | M60: - | N60: - | P60: Ascorbic Acid DC97 Equiv. Ascorbic acid (97%) Excipient: Hypromellose (%) | Q60: Ascorbic acid (vitamin C) | R60: 10 | S60: mg | Z60: - | AB60: 19.8112 | AC60: 2500 | AD60: 100 | AE60: Vitamin | AF60: Export Only, Listed, OTC, Prescription | AG60: 2936.27.00 | AH60: Highly refined organic chemicals and substances | AI60: Not required | AJ60: Not included in any CITES Appendix | AK60: No | AP60: dairy | BA60: soy | BB60: sulfites | BH60: sodium | BI60: 0.11 | BJ60: mg | BM60: sugars | BN60: 0.035 | BO60: mg | BR60: sugar alcohols | BS60: 3.36 | BT60: mg | BV60: 52224 | BW60: No restrictions. | BX60: No warnings. | BY60: No warnings. | CE60: colloidal anhydrous silica | CF60: croscarmellose sodium | CL60: vanilla flavour | CP60: glucose monohydrate | CQ60: glycerol | CT60: hypromellose | CU60: isomalt | CW60: lecithin | CX60: magnesium stearate | DB60: microcrystalline cellulose | DQ60: Yes | DR60: Yes | DS60: It is not possible to establish a UL for vitamin C, but 1,000 mg/day is a prudent limit. GIT issues most commonly reported issue of high dose C over a short time. Caution in haemochromotosishttps://www.eatforhealth.gov.au/sites/default/files/2022-04/n35-vitaminc_0.pdf TR is 100-2000 mg daily | DT60: Ascorbic acid (vitamin C) | DU60: No warnings.
A61: W030002000 | B61: A | C61: 0.0048 | D61: Thiamine (Vitamin B1) (as thiamine hydrochloride) | E61: Vitamin B1 | F61: A209 | G61: Thiamine hydrochloride | H61: - | I61: Thiamine hydrochloride | J61: - | K61: - | L61: - | M61: - | N61: - | P61: Thiamine Hydrochloride DC97% Equiv. Thiamine HCl (97%) Equiv. Thiamine (78.68% of ThHCl) Excipient: Hypromellose (3%) | Q61: Thiamine (vitamin B1) equivalent thiamine Hydrochloride | R61: 10 | S61: mg | T61: 12.71 | U61: mg | Z61: - | AB61: 17.4072 | AC61: 600 | AD61: 10 | AE61: Vitamin | AF61: Export Only, Listed, OTC, Prescription | AG61: 2936.22.00 | AH61: Highly refined organic chemicals and substances | AI61: Not required | AJ61: Not included in any CITES Appendix | AK61: No | AP61: dairy | BA61: soy | BB61: sulfites | BH61: sodium | BI61: 0.09 | BJ61: mg | BM61: sugars | BN61: 0.03 | BO61: mg | BR61: sugar alcohols | BS61: 0.01 | BT61: mg | BV61: 56144 | BW61: No restrictions. | BX61: No warnings. | BY61: No warnings. | CC61: carmellose sodium | CE61: colloidal anhydrous silica | CL61: vanilla flavour | CN61: glacial acetic acid | CP61: glucose monohydrate | CT61: hypromellose | CU61: isomalt | CW61: lecithin | CX61: magnesium stearate | DB61: microcrystalline cellulose | DF61: poliglusam | DQ61: Yes | DR61: Yes | DS61: Agreed TR BC TR 10 - 100 mg daily YSCP confirmed 600-1500mg pr day (Costantini et al., BMJ Open, 2013 — high-dose thiamine improved fatigue in IBD and MS patients (600–1,500 mg/day) | DT61: Thiamine (vitamin B1) equivalent thiamine Hydrochloride (97%) | DU61: No warnings.
A62: W030003000 | B62: A | C62: 0.0035 | D62: Vitamin B3 (as nicotinamide) | E62: Vitamin B3 | F62: A305 | G62: Nicotinamide | H62: - | I62: Nicotinamide | J62: - | K62: - | L62: - | M62: - | N62: - | P62: Nicotinamide | Q62: Nicotinamide (vitamin B3) | R62: 10 | S62: mg | Z62: - | AB62: 17.4702 | AC62: 1800 | AD62: 10 | AE62: Vitamin | AF62: Export Only, Listed, OTC, Prescription | AG62: 2936.29.00 | AH62: Highly refined organic chemicals and substances | AI62: Not required | AJ62: Not included in any CITES Appendix | AK62: No | AP62: dairy | BA62: soy | BB62: sulfites | BH62: sodium | BI62: 0.09 | BJ62: mg | BM62: sugars | BN62: 0.03 | BO62: mg | BR62: sugar alcohols | BS62: 3.7 | BT62: mg | BV62: 54851 | BW62: No restrictions. | BX62: No warnings. | BY62: No warnings. | CC62: carmellose sodium | CE62: colloidal anhydrous silica | CL62: vanilla flavour | CN62: glacial acetic acid | CP62: glucose monohydrate | CU62: isomalt | CW62: lecithin | CX62: magnesium stearate | DB62: microcrystalline cellulose | DF62: poliglusam | DQ62: Yes | DR62: Yes | DS62: Large doses of nicotinamide (up to 3,000 mg/day for periods of up to 3 years) appear to be well tolerated, as reported in trials on the possible benefi ts of nicotinamide in patients with, or at risk of developing, diabetes. The NOAEL from these studies is approximately 1,800 mg/day. This value represents the lowest reported dose in a number of high quality trials of (Lampeter et al 1998, Pozilli https://www.eatforhealth.gov.au/nutrient-reference-values/nutrients/niacinb TR 10-1000 mg daily, UL 1800 mg cited daily | DT62: Nicotinamide (vitamin B3) | DU62: No warnings.
A63: W030004000 | B63: A | C63: 0.0026 | D63: Pantothenic Acid (as calcium pantothenate) | E63: Vitamin B5 | F63: A304 | G63: Calcium pantothenate | H63: - | I63: Calcium pantothenate | J63: - | K63: - | L63: - | M63: - | N63: - | P63: Calcium Pantothenate Equiv. Pantothenic acid (__%) | Q63: Calcium pantothenate equivalent pantothenic acid (vitamin B5) | R63: 5.46 | S63: mg | T63: 5.001 | U63: mg | Z63: Please confirm the relevant equivalence? | AA63: equivalent pantothenic acid (vitamin B5) (91.6%) 5mg | AB63: 19.8062 | AC63: 1000 | AD63: 5 | AE63: Vitamin | AF63: Export Only, Listed, OTC, Prescription | AG63: 2936.24.00 | AH63: Highly refined organic chemicals and substances | AI63: Not required | AJ63: Not included in any CITES Appendix | AK63: No | AP63: dairy | BA63: soy | BB63: sulfites | BH63: sodium | BI63: 0.11 | BJ63: mg | BM63: sugars | BN63: 0.035 | BO63: mg | BR63: sugar alcohols | BS63: 7 | BT63: mg | BV63: 52558 | BW63: No restrictions. | BX63: No warnings. | BY63: No warnings. | CC63: carmellose sodium | CE63: colloidal anhydrous silica | CL63: vanilla flavour | CP63: glucose monohydrate | CQ63: glycerol | CT63: hypromellose | CU63: isomalt | CW63: lecithin | CX63: magnesium stearate | DB63: microcrystalline cellulose | DQ63: Yes | DR63: Yes | DS63: A UL cannot be determined at this stage. There are no reports of adverse effects of oral pantothenic acid in either humans or animals on which to base a quantitative estimate. Thus a UL cannot be determined at this stage, but current intakes are unlikely to be associated with adverse health effects. BC cites 20-500 mg agreed TR, TR is 5mg to 500 mg daily | DT63: Calcium pantothenate equivalent pantothenic acid (vitamin B5) (91.6%) | DU63: No warnings.
A64: W030005000 | B64: A | C64: 0.0042 | D64: Vitamin D3 (as colecalciferol) | E64: Vitamin D3 | F64: A228 | G64: Colecalciferol | H64: - | I64: Colecalciferol | J64: - | K64: - | L64: - | M64: - | N64: - | P64: Dry Vitamin D3 100 CWS/AM (PI11111) Equiv. Colecalciferol 100IU/mg Except: Starch Maize, Acacia, Sucrose (38%), DL-alpha-tocopherol, Medium Chain Triglycerides, Silicon Dioxide | Q64: Colecalciferol equivalent colecalciferol (vitamin D3) | R64: 12.5 | S64: mcg | T64: 500 | U64: IU | Z64: - | AB64: 20.8102 | AC64: 25 | AD64: 25 | AE64: Vitamin | AF64: Export Only, Listed, OTC, Prescription | AG64: 2936.29.00 or 2106.90.99 | AH64: Highly refined organic chemicals and substances | AI64: Not required | AJ64: Not included in any CITES Appendix | AK64: No | AP64: dairy | BA64: soy | BB64: sulfites | BH64: sodium | BI64: 0.11 | BJ64: mg | BM64: sugars | BN64: 2.5 | BO64: mg | BR64: sugar alcohols | BS64: 6.5 | BT64: mg | BV64: 100360 | BW64: When for internal use, the maximum recommended daily dose must not be more than 25 micrograms of Vitamin D. | BX64: No warnings. | BY64: No warnings. | BZ64: acacia | CC64: carmellose sodium | CE64: colloidal anhydrous silica | CH64: dl-alpha-tocopherol | CL64: vanilla flavour | CP64: glucose monohydrate | CQ64: glycerol | CT64: hypromellose | CU64: isomalt | CW64: lecithin | CX64: magnesium stearate | CY64: maize starch | DA64: medium chain triglycerides | DB64: microcrystalline cellulose | DH64: silicon dioxide | DN64: sucrose | DQ64: Yes | DR64: Yes | DS64: Upper limit 25 mcg (=0.025mg = 1000IU) | DT64: Colecalciferol (mcg) equivalent colecalciferol (vitamin D3, IU) | DU64: No warnings.
A65: W030006000 | B65: A | C65: 0.0035 | D65: Vitamin A (as retinyl acetate) | E65: Vitamin A | F65: A850 | G65: Retinyl acetate | H65: - | I65: Retinol acetate | J65: - | K65: - | L65: - | M65: - | N65: - | P65: Dry Vitamin A Acetate 500B PI 3176 - Retinyl acetate Equiv. Vit E 500IU/g Equiv. mcg RAE | Q65: Retinyl acetate equivalent Retinol Equivalents equivalent vitamin A | R65: 516 | S65: mcg | T65: 450 | U65: mcg RE | V65: 1500 | W65: IU | Z65: Please confirm the name and quantity of any excipients present? | AA65: 1% butylated hydroxytoluene 48% gelatin 22% maize starch 11.75% sucrose | AB65: 18.4602 | AC65: 3440 | AD65: 1032 | AE65: Vitamin | AF65: Export Only, Listed, OTC, Prescription | AG65: 2936.21.00 or 2106.90.99 | AH65: Highly refined organic chemicals and substances | AI65: Not required | AJ65: Not included in any CITES Appendix | AK65: No | AP65: dairy | BA65: soy | BB65: sulfites | BH65: sodium | BI65: 0.1 | BJ65: mg | BM65: sugars | BN65: 0.031 | BO65: mg | BR65: sugar alcohols | BS65: 7.1 | BT65: mg | BV65: 68280 | BW65: When for use in topical medicines, the concentration of Vitamin A in the medicine must be no more than 1%. When for internal use, the maximum daily dose must be no more than 3000 micrograms of Retinol Equivalents. | BX65: When preparations for internal use in adults contain more than 33 micrograms of retinol equivalents per dosage unit in divided preparations or per gram of an undivided preparation, the medicine requires the following warning statements on the medicine label:- (VITA2) ‘WARNING: If you are pregnant - or considering becoming pregnant - do not take Vitamin A supplements without consulting your doctor or pharmacist [or words to that effect].’ NOTE: Position this warning at the beginning of the directions for use.- (VITA4) ‘WARNING - When taken in excess of 3000 micrograms retinol equivalents - Vitamin A can cause birth defects.’ NOTE: Position this warning at the beginning of the directions for use.- (VITA3) ‘The recommended daily amount of Vitamin A from all sources is 700 micrograms retinol equivalents for women and 900 micrograms retinol equivalents for men.’ | BY65: If dose contains more than 33mcg of Vitamin A: "If you are pregnant - or considering becoming pregnant - do not take Vitamin A supplements without consulting your doctor or pharmacist." "When taken in excess of 3000 micrograms retinol equivalents - Vitamin A may cause birth defects." | CA65: butylated hydroxytoluene | CC65: carmellose sodium | CE65: colloidal anhydrous silica | CL65: vanilla flavour | CM65: gelatin | CP65: glucose monohydrate | CQ65: glycerol | CT65: hypromellose | CU65: isomalt | CW65: lecithin | CX65: magnesium stearate | CY65: maize starch | DB65: microcrystalline cellulose | DN65: sucrose | DQ65: Yes | DR65: Yes | DS65: Look at linus Pauling recommendationTherapeutic range for vitamin A in mcg TR 750mcg - 3000 mcg note 10,000iu = 3000 mcg. Regs requirement UL for vitamin A = 3000mcgRE/day. 3000mcgRE = 3440 mcg Retinyl acetate (Col R&S) 900mcgRE = 1032 mcg Retinyl acetate Vitamin B12 (as methylcobalamin): Evidence-Based Clinical Dosing, 500–2,000 mcg/day. (Kuzminski et al., Blood, 1998). Although, 500–2,000 mcg lowers homocysteine. (Clarke et al., BMJ) | DT65: Retinyl acetate equivalent Retinol Equivalents (mcgRAE) equivalent vitamin A (IU) | DU65: "If you are pregnant - or considering becoming pregnant - do not take Vitamin A supplements without consulting a healthcare professional." "When taken in excess of 3000 micrograms retinol equivalents - Vitamin A can cause birth defects." "The recommended daily amount of Vitamin A from all sources is 700 micrograms retinol equivalents for women and 900 micrograms retinol equivalents for men."
A66: W030007000 | B66: A | C66: 0.0118 | D66: Vitamin K2 (menaquinone 7) | E66: Vitamin K2 | F66: A2287 | G66: Menaquinone 7 | H66: - | I66: Menaquinone 7 | J66: - | K66: - | L66: - | M66: - | N66: - | P66: Menaquinone 7 (2000ppm) Equiv. Menaquinone 7 (2000ppm) Excipient: Maltodextrin | Q66: Menaquinone 7 (vitamin K2) | R66: 10 | S66: mcg | Z66: - | AB66: 18.81 | AC66: 300 | AD66: 60 | AE66: Vitamin | AF66: Export Only, Listed, OTC, Prescription | AG66: 2106.90.99 | AH66: Highly refined organic chemicals and substances | AI66: Not required | AJ66: Not included in any CITES Appendix | AK66: No | AP66: dairy | BA66: soy | BB66: sulfites | BH66: sodium | BI66: 0.11 | BJ66: mg | BM66: sugars | BN66: 0.035 | BO66: mg | BR66: sugar alcohols | BS66: 6.9 | BT66: mg | BV66: 105890 | BW66: For oral use only. The medicine must not provide more than 180 micrograms per maximum daily dose in adults, 90 micrograms per maximum daily dose in children between 10-18 years, and 45 micrograms per maximum daily dose in children less than 10 years of age. | BX66: No warnings. | BY66: No warnings. | CC66: carmellose sodium | CE66: colloidal anhydrous silica | CL66: vanilla flavour | CP66: glucose monohydrate | CQ66: glycerol | CT66: hypromellose | CU66: isomalt | CW66: lecithin | CX66: magnesium stearate | CZ66: maltodextrin | DB66: microcrystalline cellulose | DG66: pregelatinised starch | DQ66: Yes | DR66: Yes | DS66: No adverse effects have been associated with vitamin K consumption as food or supplements in humans or animals, so it is not possible to set a UL. No adverse effects have been associated with vitamin K consumption as food or supplements in humans or animals, so it is not possible to set a UL. TR 90-180 mcg dailyhttps://pubmed.ncbi.nlm.nih.gov/25694037/ UL assigned 300mcg | DT66: Menaquinone 7 (vitamin K2) | DU66: No warnings.
A67: W030008000 | B67: A | C67: 0.0083 | D67: Vitamin B12 (as methylcobalamin) | E67: Vitamin B12 | F67: A832 | G67: Mecobalamin | H67: - | I67: Mecobalamin | J67: - | K67: - | L67: - | M67: - | N67: - | P67: Mecobalamin Equiv. Mecobalamin (88.0%, due to water) | Q67: Mecobalamin (vitamin B12) | R67: 250 | S67: mcg | Z67: - | AB67: 18.7537 | AC67: 2000 | AD67: 250 | AE67: Vitamin | AF67: Export Only, Listed, OTC, Prescription | AG67: 2936.26.00 | AH67: Highly refined organic chemicals and substances | AI67: Not required | AJ67: Not included in any CITES Appendix | AK67: No | AP67: dairy | BA67: soy | BB67: sulfites | BH67: sodium | BI67: 0.1 | BJ67: mg | BM67: sugars | BN67: 0.031 | BO67: mg | BR67: sugar alcohols | BS67: 12 | BT67: mg | BV67: 93010 | BW67: Only for use in oral medicines. | BX67: No warnings. | BY67: No warnings. | CC67: carmellose sodium | CE67: colloidal anhydrous silica | CJ67: ethanol | CL67: vanilla flavour | CP67: glucose monohydrate | CQ67: glycerol | CT67: hypromellose | CU67: isomalt | CW67: lecithin | CX67: magnesium stearate | DB67: microcrystalline cellulose | DQ67: Yes | DR67: Yes | DS67: The apparent lack of toxicity could relate to the body’s ability to decrease absorption in response to high intakes. As there are no dose-response data, no UL can be set. https://www.eatforhealth.gov.au/sites/default/files/2022-04/n35-vitaminb12_0.pdf TR 250-1000 mcg daily BC UL not necessary, but included. UL assigned 2000mcg Vitamin B12 (as methylcobalamin): Evidence-Based Clinical Dosing, 500–2,000 mcg/day. (Kuzminski et al., Blood, 1998). Although, 500–2,000 mcg lowers homocysteine. (Clarke et al., BMJ) | DT67: Mecobalamin (vitamin B12) | DU67: No warnings.
A68: W030009000 | B68: A | C68: 0.0086 | D68: Folate (as calcium levomefolate) | E68: Folate (B9) | F68: A2122 | G68: Calcium levomefolate | H68: - | I68: Levomefolate calcium | J68: - | K68: - | L68: - | M68: - | N68: - | P68: Levomefolate calcium Equiv. Levomefolic acid (92.35%) Equiv. folate (76.9%) | Q68: Levomefolate calcium equivalent levomefolic acid equivalent folate (vitamin B9) | R68: 260 | S68: mcg | T68: 240.11 | U68: mcg | V68: 199.94 | W68: mcg | Z68: - | AB68: 17.4362 | AC68: 6500 | AD68: 650 | AE68: Vitamin | AF68: Export Only, Listed, OTC, Prescription | AG68: 2936.29.00 | AH68: Highly refined organic chemicals and substances | AI68: Not required | AJ68: Not included in any CITES Appendix | AK68: No | AP68: dairy | BA68: soy | BB68: sulfites | BH68: sodium | BI68: 0.09 | BJ68: mg | BM68: sugars | BN68: 0.03 | BO68: mg | BR68: sugar alcohols | BS68: 8 | BT68: mg | BV68: 107416 | BW68: Available for medicines intended for internal use only. Levomefolic acid is a mandatory component of levomefolate calcium. The maximum recommended daily dose must not provide more than 500 micrograms of levomefolic acid from levomefolate calcium. When the medicine contains a combination of folic acid, folinic acid or levomefolic acid, the medicine must not provide more than a combined total of 500 micrograms of folic acid, folinic acid and levomefolic acid per maximum recommended daily dose. | BX68: No warnings. | BY68: No warnings. | CC68: carmellose sodium | CE68: colloidal anhydrous silica | CL68: vanilla flavour | CP68: glucose monohydrate | CQ68: glycerol | CT68: hypromellose | CU68: isomalt | CW68: lecithin | CX68: magnesium stearate | DB68: microcrystalline cellulose | DQ68: Yes | DR68: Yes | DS68: UL of 1000 mcg of folic acid set. https://www.eatforhealth.gov.au/sites/default/files/2022-04/n35-folate_0.pdf REGS TR 400 mcg - 1000 mcg UL 5mg (elevated homocysteine) Regs UL requirements YSCP have confirmed that the AUST L Limit is 0.5mg Levomefolic acid can be exceeded for extemporanus compounding, providing the quantity is within the limits below. Folate (as calcium levomefolate): Evidence-Based Clinical Dosing, Hyperhomocysteinemia 800 mcg–5 mg/day, MTHFR polymorphism 1–5 mg/day, Autism protocols 5–15 mg/day. (Papakostas GI et al., Am J Psychiatry, 2012) | DT68: Levomefolate calcium equivalent levomefolic acid equivalent folate (vitamin B9) | DU68: No warnings.
A69: W030010000 | B69: A | C69: 0.0054 | D69: Biotin (as D-Biotin) | E69: Biotin | F69: A302 | G69: Biotin | H69: - | I69: Biotin | J69: - | K69: - | L69: - | M69: - | N69: - | P69: Biotin | Q69: Biotin (vitamin H) | R69: 250 | S69: mcg | Z69: Please confirm the name and quantity of any excipients present? | AA69: No excipients | AB69: 17.4302 | AC69: 6000 | AD69: 200 | AE69: Vitamin | AF69: Export Only, Listed, OTC, Prescription | AG69: 2936.29.00 | AH69: Highly refined organic chemicals and substances | AI69: Not required | AJ69: Not included in any CITES Appendix | AK69: No | AP69: dairy | BA69: soy | BB69: sulfites | BH69: sodium | BI69: 0.09 | BJ69: mg | BM69: sugars | BN69: 0.03 | BO69: mg | BR69: sugar alcohols | BS69: 8 | BT69: mg | BV69: 52378 | BW69: No restrictions. | BX69: No warnings. | BY69: No warnings. | CC69: carmellose sodium | CE69: colloidal anhydrous silica | CL69: vanilla flavour | CP69: glucose monohydrate | CQ69: glycerol | CT69: hypromellose | CU69: isomalt | CW69: lecithin | CX69: magnesium stearate | DB69: microcrystalline cellulose | DQ69: Yes | DR69: Yes | DS69: TR 1-5 mg daily. Doses of 100-600 mg of biotin were found to be well tolerated by people with progressive MS https://lpi.oregonstate.edu/mic/vitamins/biotin#toc-safety UL 600 mg (6000mcg) of biotin Clinical Ranges, Metabolic 5,000–15,000 mcg (Tourbah A et al., Lancet Neurology, 2016) | DT69: Biotin (vitamin H) | DU69: No warnings.
A70: W030011000 | B70: A | C70: 0.0099 | D70: Riboflavin | E70: Vitamin B2 | F70: A306 | G70: Riboflavin | H70: - | I70: Riboflavin | J70: - | K70: - | L70: - | M70: - | N70: - | P70: Riboflavin | Q70: Riboflavin (vitamin B2) | R70: 10 | S70: mg | Z70: - | AB70: 18.4242 | AC70: 400 | AD70: 10 | AE70: Vitamin | AF70: Export Only, Listed, OTC, Prescription | AG70: 2936.23.00 | AH70: Highly refined organic chemicals and substances | AI70: Not required | AJ70: Not included in any CITES Appendix | AK70: No | AP70: dairy | BA70: soy | BB70: sulfites | BH70: sodium | BI70: 0.1 | BJ70: mg | BM70: sugars | BN70: 0.031 | BO70: mg | BR70: sugar alcohols | BS70: 4.33 | BT70: mg | BV70: 100378 | BW70: No restrictions. | BX70: No warnings. | BY70: No warnings. | CC70: carmellose sodium | CE70: colloidal anhydrous silica | CL70: vanilla flavour | CP70: glucose monohydrate | CU70: isomalt | CW70: lecithin | CX70: magnesium stearate | DB70: microcrystalline cellulose | DF70: poliglusam | DG70: pregelatinised starch | DQ70: Yes | DR70: Yes | DS70: No adverse events have been associated with riboflavin consumption as food or supplements so no upper level of intake can be set https://www.eatforhealth.gov.au/sites/default/files/2022-04/n35-riboflavin_0.pdf TR 10- 250 mg daily BC No UL set | DT70: Riboflavin (vitamin B2) | DU70: No warnings.
A71: W030012000 | B71: A | C71: 0.0093 | D71: Vitamin B6 (as pyridoxal 5-phosphate) | E71: Vitamin B6 (P5P) | F71: A521 | G71: Pyridoxal 5-phosphate | H71: - | I71: Pyridoxal 5-phosphate | J71: - | K71: - | L71: - | M71: - | N71: - | P71: Pyridoxal 5-phosphate monohydrate Equiv. Pyridoxine (63.8%) | Q71: Pyridoxal 5-phosphate equivalent pyridoxine (vitamin B6) | R71: 7.84 | S71: mg | T71: 5.001 | U71: mg | Z71: - | AB71: 18.4742 | AC71: 50 | AD71: 5 | AE71: Vitamin | AF71: Export Only, Listed, OTC, Prescription | AG71: 2936.25.00 | AH71: Highly refined organic chemicals and substances | AI71: Not required | AJ71: Not included in any CITES Appendix | AK71: No | AP71: dairy | BA71: soy | BB71: sulfites | BH71: sodium | BI71: 0.11 | BJ71: mg | BM71: sugars | BN71: 0.035 | BO71: mg | BV71: 108353 | BW71: Pyridoxine is a mandatory component of pyridoxal 5-phosphate. The percentage of pyridoxine from pyridoxal 5-phosphate should be calculated based on the molecular weight of pyridoxal 5-phosphate. The maximum recommended daily dose of the medicine must not provide more than: (i) 15 mg of pyridoxine for children aged between 1 and 3 years (inclusive); (ii) 20 mg of pyridoxine for children aged between 4 and 8 years (inclusive); (iii) 30 mg of pyridoxine for children aged between 9 and 13 years (inclusive); (iv) 40 mg of pyridoxine for individuals aged 14 and 18 years (inclusive); and (v) 100 mg of pyridoxine for individuals aged 19 years and older. | BX71: If the maximum recommended daily dose of the medicine provides more than 10 mg of pyridoxine, the following warning statement is required on the medicine label: - (VITB6SX) 'WARNING - Stop taking this medication if you experience tingling, burning or numbness and see your healthcare practitioner as soon as possible. [Contains vitamin B6]. | BY71: If dose contains more than 50mg Vitamin B6: "Stop taking this medication if you experience tingling, burning or numbness and consult a healthcare practitioner as soon as possible. Contains vitamin B6." | CC71: carmellose sodium | CE71: colloidal anhydrous silica | CL71: vanilla flavour | CN71: glacial acetic acid | CP71: glucose monohydrate | CT71: hypromellose | CW71: lecithin | CX71: magnesium stearate | DB71: microcrystalline cellulose | DF71: poliglusam | DG71: pregelatinised starch | DQ71: Yes | DR71: Yes | DS71: The UL for adults was thus set at 50 mg/day. The same figure was set for pregnancy and lactation as there is no evidence of teratogenicity https://www.eatforhealth.gov.au/sites/default/files/2022-10/n35-vitaminb6_0.pdf BC cites 1200mg/day (schizophrenia). TR 5-50 restrained given current TGA direction re B6 Upper limit relects dosing for schizophrenia at 1200 mg | DT71: Pyridoxal 5-phosphate equivalent pyridoxine (vitamin B6) | DU71: "Stop taking this medication if you experience tingling, burning or numbness and consult a healthcare professional as soon as possible (contains vitamin B6)."
A72: W030013000 | B72: A | C72: 0.0022 | D72: Calcium (as calcium citrate) | E72: Calcium citrate | F72: A025 | G72: Calcium citrate | H72: - | I72: Calcium citrate tetrahydrate | J72: - | K72: - | L72: - | M72: - | N72: - | P72: Calcium citrate tetrahydrate Equiv. Calcium (21.1%) | Q72: Calcium citrate tetrahydrate equivalent calcium (Ca) | R72: 9.482 | S72: mg | T72: 2.01 | U72: mg | Z72: There are two forms, calcium citrate, and calcium citrate tetrahydrate. Please confirm which form is being used, and the relevant equivalence? | AA72: calcium citrate tetrahydrate equivalent calcium (21.1%) 2mg | AB72: 19.8004 | AC72: 1200 | AD72: 500 | AE72: Mineral | AF72: Export Only, Listed, OTC, Prescription | AG72: 2918.15.00 | AH72: Mineral and metal ores, rock and sand | AI72: Not required | AJ72: Not included in any CITES Appendix | AK72: No | AP72: dairy | BA72: soy | BB72: sulfites | BH72: sodium | BI72: 0.1 | BJ72: mg | BM72: sugars | BN72: 0.033 | BO72: mg | BR72: sugar alcohols | BS72: 6 | BT72: mg | BV72: 97719 | BW72: No restrictions. | BX72: No warnings. | BY72: No warnings. | CC72: carmellose sodium | CE72: colloidal anhydrous silica | CJ72: ethanol | CL72: vanilla flavour | CP72: glucose monohydrate | CQ72: glycerol | CT72: hypromellose | CU72: isomalt | CW72: lecithin | CX72: magnesium stearate | DB72: microcrystalline cellulose | DG72: pregelatinised starch | DQ72: Yes | DR72: Yes | DS72: Calcium UL is set cautiously at 2,000 mg daily. Concern about kidney stones, competition with absorption from other mineralshttps://www.eatforhealth.gov.au/sites/default/files/2022-04/n35-calcium_0.pdf TR 100-1200 CALCIUM mg/day BC. UL of 2000 mg US office of dietary supplements Limited by 2mg Ca / granule. | DT72: Calcium citrate tetrahydrate equivalent calcium | DU72: No warnings.
A73: W030014000 | B73: A | C73: 0.007 | D73: Iodine (as potassium iodide) | E73: Potassium iodide | F73: A058 | G73: Potassium iodide | H73: - | I73: Potassium iodide | J73: - | K73: - | L73: - | M73: - | N73: - | P73: Potassium iodide Equiv. Iodine (76.45%) | Q73: Potassium iodide equivalent iodine (I) | R73: 131 | S73: mcg | T73: 100.149 | U73: mcg | Z73: - | AB73: 17.4353 | AC73: 395 | AD73: 131 | AE73: Mineral | AF73: Export Only, Listed, OTC, Prescription | AG73: 2827.60.00 | AH73: Mineral and metal ores, rock and sand | AI73: Not required | AJ73: Not included in any CITES Appendix | AK73: No | AP73: dairy | BA73: soy | BB73: sulfites | BH73: sodium | BI73: 0.09 | BJ73: mg | BM73: sugars | BN73: 0.03 | BO73: mg | BR73: sugar alcohols | BS73: 14 | BT73: mg | BV73: 55445 | BW73: Iodine is a mandatory component of potassium iodide. The percentage of iodine from potassium iodide should be calculated based on the molecular weight of potassium iodide. When for internal use, the maximum recommended daily dose of the medicine must contain less than 300 micrograms of iodine. When for external use, the concentration of iodine in the medicine (excluding salt derivatives or iodophors) must not exceed 2.5%. | BX73: No warnings. | BY73: If total iodine is more than 300mcg: "Total iodine intake may exceed recommended level when taking this preparation." "Contains iodine - do not take when pregnant except on physician’s advice" | CC73: carmellose sodium | CE73: colloidal anhydrous silica | CL73: vanilla flavour | CP73: glucose monohydrate | CQ73: glycerol | CT73: hypromellose | CU73: isomalt | CW73: lecithin | CX73: magnesium stearate | DB73: microcrystalline cellulose | DQ73: Yes | DR73: Yes | DS73: Upper limit set at 1,450 mcg of potassium iodide daily. https://www.eatforhealth.gov.au/sites/default/files/2022-04/n35-iodine_0.pdf TR 250 mcg - 1450 of potassium iodide mg equivalent to 1,100 mcg of iodine Chronic iodine toxicity can occur at doses above 2 mg day BC, however up to 6 mg daily is used in fibrocystic breast disease BC (0.395mg = 395mcg KI = 3 granules = 300mcg of iodine) | DT73: Potassium iodide equivalent iodine | DU73: No warnings.
A74: W030015000 | B74: A | C74: 0.0042 | D74: Magnesium (as magnesium threonate) | E74: Magnesium threonate | F74: A2647 | G74: Magnesium threonate | H74: - | I74: Magnesium threonate | J74: - | K74: - | L74: - | M74: - | N74: - | P74: Magnesium threonate Equiv. Magnesium (7.2%) | Q74: Magnesium threonate equivalent magnesium (Mg) | R74: 13.89 | S74: mg | T74: 1 | U74: mg | Z74: There are two forms, magnesium threonate, and magnesium threonate monohydrate. Please confirm which form is being used, and the relevant equivalence? | AA74: magnesium threonate equivalent magnesium (7.2%) 1mg | AB74: 20.5092 | AC74: 4800 | AD74: 2000.2 | AE74: Mineral | AF74: Export Only | AG74: 2915.60.00 or 2918.19.00 | AH74: Highly refined organic chemicals and substances | AI74: Not required | AJ74: Not included in any CITES Appendix | AK74: No | AP74: dairy | BA74: soy | BB74: sulfites | BH74: sodium | BI74: 0.11 | BJ74: mg | BM74: sugars | BN74: 0.035 | BO74: mg | BV74: 108491 | BW74: No restrictions. | BX74: No warnings. | BY74: No warnings. | CC74: carmellose sodium | CE74: colloidal anhydrous silica | CL74: vanilla flavour | CP74: glucose monohydrate | CQ74: glycerol | CT74: hypromellose | CW74: lecithin | CX74: magnesium stearate | DB74: microcrystalline cellulose | DQ74: Yes | DR74: Yes | DS74: TR 1000-2000 mg day of mag threonate, equiv to elemental Mg of 72 - 144 mg https://anzctr.org.au/Trial/Registration/TrialReview.aspx?id=390016&utm UL 4800 magnesium threonate, equiv to 346 mg magnesium | DT74: Magnesium threonate equivalent magnesium | DU74: No warnings.
A75: W030018000 | B75: A | C75: 0.0022 | D75: Chromium (as chromium picolinate) | E75: Chromium picolinate | F75: A299 | G75: Chromium picolinate | H75: - | I75: Chromium picolinate | J75: - | K75: - | L75: - | M75: - | N75: - | P75: Chromium picolinate Equiv. chromium (12.43%) | Q75: Chromium picolinate equivalent chromium (Cr) | R75: 805 | S75: mcg | T75: 100.061 | U75: mcg | Z75: Please confirm the relevant equivalence? | AA75: equivalent chromium (12.43%) 100mcg | AB75: 17.4407 | AC75: 810 | AD75: 805 | AE75: Mineral | AF75: Export Only, Listed, OTC, Prescription | AG75: 2933.39.00 | AH75: Mineral and metal ores, rock and sand | AI75: Not required | AJ75: Not included in any CITES Appendix | AK75: No | AP75: dairy | BA75: soy | BB75: sulfites | BH75: sodium | BI75: 0.09 | BJ75: mg | BM75: sugars | BN75: 0.03 | BO75: mg | BR75: sugar alcohols | BS75: 10 | BT75: mg | BV75: 85326 | BW75: Chromium is a mandatory component of Chromium picolinate. The maximum recommended daily dose must not provide more than 50 micrograms of chromium from organic sources. Chromium picolinate is considered to be an organic form of chromium. | BX75: No warnings. | BY75: No warnings. | CC75: carmellose sodium | CE75: colloidal anhydrous silica | CL75: vanilla flavour | CP75: glucose monohydrate | CQ75: glycerol | CT75: hypromellose | CU75: isomalt | CW75: lecithin | CX75: magnesium stearate | DB75: microcrystalline cellulose | DQ75: Yes | DR75: Yes | DS75: The ULs for chromium are unknown as there are insuffi cient data. AI is 45 mcg daily.No adverse side effects were reported in a number of supplementation trials in which subjects received up to 1 mg chromium/day, mostly as picolinate, for several months (Flodin 1990, Hathcock 1997). These trials, however, were mainly studies of effi cacy and not designed to fi nd potential toxic effects. The limited data from all studies on subchronic, chronic and reproductive toxicity on soluble trivalent chromium salts do not give clear information on the dose-response relationship. Therefore, ULs can https://www.eatforhealth.gov.au/sites/default/files/2022-04/n35-chromium_0.pdf TR range 200-800 mcg day of chromium, equiv to chromium picolonate AUST L max = 50mcg Chromium = 402.3mcg Chromium picollinate. 1 Granule = 100mcg Chromium. Therefore UL = 805mcg Cr Picollinate. | DT75: Chromium picolinate equivalent chromium | DU75: No warnings.
A76: W030019000 | B76: A | C76: 0.0054 | D76: Choline (as choline bitartrate) | E76: Choline bitartrate | F76: A2649 | G76: Choline bitartrate | H76: - | I76: Choline bitartrate | J76: - | K76: - | L76: - | M76: - | N76: - | P76: Choline bitartrate Equiv. Choline bitartrate (90%) Equiv. Choline (41.13% of CBT) Excipient: Hydrogenated Vegetable Oil | Q76: Choline bitartrate equivalent choline | R76: 7.299 | S76: mg | T76: 3 | U76: mg | Z76: - | AB76: 20.8112 | AC76: 2000 | AD76: 100 | AE76: Vitamin | AF76: Export Only, Listed, OTC, Prescription | AG76: 2923.10.00 | AH76: Highly refined organic chemicals and substances | AI76: Not required | AJ76: Not included in any CITES Appendix | AK76: No | AP76: dairy | BA76: soy | BB76: sulfites | BH76: sodium | BI76: 0.12 | BJ76: mg | BM76: sugars | BN76: 0.035 | BO76: mg | BR76: sugar alcohols | BS76: 8 | BT76: mg | BV76: 52802 | BW76: No restrictions. | BX76: No warnings. | BY76: No warnings. | CE76: colloidal anhydrous silica | CF76: croscarmellose sodium | CJ76: ethanol | CL76: vanilla flavour | CQ76: glycerol | CR76: hydrogenated vegetable oil | CT76: hypromellose | CU76: isomalt | CX76: magnesium stearate | DB76: microcrystalline cellulose | DK76: sodium starch glycollate | DQ76: Yes | DR76: Yes | DS76: UL of 3500 mg set. The data used to set the UL included a single case report of hypotension and several studies involving cholinergic effects and body odour effects after large choline doses.https://www.eatforhealth.gov.au/sites/default/files/2022-04/n35-choline_0.pdf TR is 250-2000 mg of choline bitartrate. UL set to 2000. Therapeutic Clinical Dosing 500–2,000 mg/day (U.S. National Academy of Sciences (IOM)) | DT76: Choline bitartrate equivalent choline | DU76: No warnings.
A77: W030020000 | B77: A | C77: 0.0019 | D77: Alpha lipoic acid (thioctic acid) | E77: R,S-alpha lipoic acid | F77: A157 | G77: Alpha lipoic acid | H77: - | I77: Alpha lipoic acid | J77: - | K77: - | L77: - | M77: - | N77: - | P77: Alpha lipoic acid (R,S-alpha Lipoic acid) | Q77: Alpha lipoic acid | R77: 5 | S77: mg | AB77: 18.8102 | AC77: 1800 | AD77: 300 | AE77: Amino acid | AF77: Export Only, Listed, OTC, Prescription | AG77: 2930.90.00 or 2934.99.00 | AH77: Highly refined organic chemicals and substances | AI77: Not required | AJ77: Not included in any CITES Appendix | AK77: No | AP77: dairy | BA77: soy | BB77: sulfites | BH77: sodium | BI77: 0.11 | BJ77: mg | BM77: sugars | BN77: 0.035 | BO77: mg | BV77: 102239 | BW77: No restrictions. | BX77: No warnings. | BY77: No warnings. | CC77: carmellose sodium | CE77: colloidal anhydrous silica | CJ77: ethanol | CL77: vanilla flavour | CP77: glucose monohydrate | CQ77: glycerol | CT77: hypromellose | CU77: isomalt | CW77: lecithin | CX77: magnesium stearate | DB77: microcrystalline cellulose | DQ77: Yes | DR77: Yes | DS77: Dosage range 150 mg - 1200 mg Braun and Cohen Clinical trials testing oral ALA AT 1800 mg daily for 2 years have not identified serious side effects BC study shows ALA AT 1200 MG https://pubmed.ncbi.nlm.nih.gov/25104975/ UL 1800 mg BC | DT77: R,S-alpha lipoic acid | DU77: No warnings.
A78: W030021000 | B78: A | C78: 0.0026 | D78: Coenzyme Q10 | E78: Coenzyme Q10 | F78: A2790 | G78: Ubidecarenone | H78: - | I78: Ubidecarenone | J78: - | K78: - | L78: - | M78: - | N78: - | P78: Ubidecarenone | Q78: Ubidecarenone (CoQ10) | R78: 1 | S78: mg | Z78: - | AB78: 19.4852 | AC78: 2400 | AD78: 100 | AE78: Vitamin | AF78: Export Only, Listed, OTC, Prescription | AG78: 2914.69.00 | AH78: Highly refined organic chemicals and substances | AI78: Not required | AJ78: Not included in any CITES Appendix | AK78: No | AP78: dairy | BA78: soy | BB78: sulfites | BH78: sodium | BI78: 0.1 | BJ78: mg | BM78: sugars | BN78: 0.033 | BO78: mg | BR78: sugar alcohols | BS78: 0.09 | BT78: mg | BV78: 56335 | BW78: When used as an excipient, the route of administration must be topical and the concentration in the medicine must not be more than 0.05%. Not to be included in medicines intended for use in the eye. When for internal use, the maximum recommended daily dose must not provide more than 300 milligrams of ubidecarenone. When for internal use in combination with Ubiquinol-10, the maximum recommended daily dose must not provide more than 300 milligrams of ubiquinol-10 and ubidecarenone combined. | BX78: When for internal use, the following warning statement is required on the medicine label:- (WARF) 'Do not take while on warfarin therapy without medical advice'. | BY78: No warnings. | CC78: carmellose sodium | CJ78: ethanol | CL78: vanilla flavour | CP78: glucose monohydrate | CQ78: glycerol | CT78: hypromellose | CU78: isomalt | CW78: lecithin | CX78: magnesium stearate | CZ78: maltodextrin | DB78: microcrystalline cellulose | DH78: silicon dioxide | DQ78: Yes | DR78: Yes | DS78: TR 60-1200 mg daily BC safe, non toxic and extremely well tolerated. Shults et al., 2002 — Archives of Neurology UL 2400mg | DT78: Ubidecarenone (CoQ10) | DU78: "Do not take while on warfarin without consulting a healthcare professional."
A79: W030022000 | B79: A | C79: 0.007 | D79: Vitamin E (as d-alpha tocopheryl acid succinate) | E79: Vitamin E | F79: A522 | G79: D-alpha tocopheryl acid succinate | H79: - | I79: D-alpha-tocopheryl acid succinate | J79: - | K79: - | L79: - | M79: - | N79: - | P79: Covitol 1185 (PI2796) Equiv. d-alpha Tocopheryl acid Succinate 96% Excip. ethylcellulose | Q79: D-alpha-tocopheryl acid succinate equivalent vitamin E | R79: 4.992 | S79: mg | T79: =R79*1.21 -> 6.04032 | U79: IU | Z79: - | AB79: 17.4252 | AC79: 1000 | AD79: 300 | AE79: Vitamin | AF79: Export Only, Listed, OTC, Prescription | AG79: 2936.28.00 | AH79: Highly refined organic chemicals and substances | AI79: Not required | AJ79: Not included in any CITES Appendix | AK79: No | AP79: dairy | BA79: soy | BB79: sulfites | BH79: sodium | BI79: 0.09 | BJ79: mg | BM79: sugars | BN79: 0.03 | BO79: mg | BR79: sugar alcohols | BS79: 6 | BT79: mg | BV79: 95011 | BW79: No restrictions. | BX79: No warnings. | BY79: No warnings. | CC79: carmellose sodium | CE79: colloidal anhydrous silica | CK79: ethylcellulose | CL79: vanilla flavour | CP79: glucose monohydrate | CQ79: glycerol | CT79: hypromellose | CU79: isomalt | CW79: lecithin | CX79: magnesium stearate | DB79: microcrystalline cellulose | DQ79: Yes | DR79: Yes | DS79: UL of 300 mg daily. https://www.eatforhealth.gov.au/sites/default/files/2022-04/n35-vitamine_0.pdf tr 50-800 mg daily BC is this dosage iu or mg Doses as high as 3200 mg daily have been used without adverse effects | DT79: D-alpha-tocopheryl acid succinate equivalent vitamin E (IU) | DU79: No warnings.
A80: W030026000 | B80: A | C80: 0.0358 | D80: PQQ (pyrroloquinoline quinone) | E80: PQQ | F80: A2741 | G80: Pyrroloquinoline quinone | H80: - | I80: Pyrroloquinoline quinone | J80: - | K80: - | L80: - | M80: - | N80: - | P80: Pyrroloquinoline Quinine Disodium Equiv. Pyrroloquinoline Quinine (90.9%) | Q80: Pyrroloquinoline quinone disodium equivalent pyrroloquinoline quinone | R80: 5.5 | S80: mg | T80: 5 | U80: mg | Z80: Please confirm the pyrroloquinoline quinone equivalence? | AA80: 0.909 | AB80: 19.5002 | AC80: 60 | AD80: 10 | AE80: Vitamin | AF80: Export Only | AG80: 2914.69.00 | AH80: Highly refined organic chemicals and substances | AI80: Not required | AJ80: Not included in any CITES Appendix | AK80: No | AP80: dairy | BA80: soy | BB80: sulfites | BH80: sodium | BI80: 0.1 | BJ80: mg | BM80: sugars | BN80: 0.033 | BO80: mg | BR80: sugar alcohols | BS80: 7.46 | BT80: mg | BV80: 147944 | BW80: No restrictions. | BX80: No warnings. | BY80: No warnings. | CC80: carmellose sodium | CL80: vanilla flavour | CP80: glucose monohydrate | CQ80: glycerol | CT80: hypromellose | CU80: isomalt | CW80: lecithin | CX80: magnesium stearate | CZ80: maltodextrin | DH80: silicon dioxide | DQ80: Yes | DR80: Yes | DS80: TR 10-40 mg https://journals.lww.com/nrronline/fulltext/2025/01000/pyrroloquinoline_quinone__a_potential.5.aspx?utm | DT80: Pyrroloquinoline quinone disodium equivalent pyrroloquinoline quinone (90.9%) | DU80: No warnings.
A81: W030027000 | B81: A | C81: 0.007 | D81: Folate (as calcium folinate) | E81: Calcium folinate | F81: A535 | G81: Calcium folinate | H81: - | I81: Calcium folinate | J81: - | K81: - | L81: - | M81: - | N81: - | P81: Calcium Folinate Equiv. Calcium Folinate (odb, 17% H20) Equiv. Folinic acid (92.55%) | Q81: Calcium folinate equivalent Folinic acid | R81: 218.788 | S81: mcg | T81: 202.488 | U81: mcg | Z81: - | AB81: 17.44016 | AC81: 547 | AD81: 547 | AE81: Vitamin | AF81: Export Only, Listed, OTC, Prescription | AG81: 2936.29.00 | AH81: Highly refined organic chemicals and substances | AI81: Not required | AJ81: Not included in any CITES Appendix | AK81: No | AP81: dairy | BA81: soy | BB81: sulfites | BH81: sodium | BI81: 0.09 | BJ81: mg | BM81: sugars | BN81: 0.03 | BO81: mg | BR81: sugar alcohols | BS81: 8 | BT81: mg | BV81: 52536 | BW81: Folinic acid is a mandatory component of calcium folinate. The maximum recommended daily dose must not provide more than 500 micrograms of folinic acid. When the medicine contains a combination of folic acid, folinic acid or levomefolic acid, the medicine must not provide more than a combined total of 500 micrograms of folic acid, folinic acid and levomefolic acid per maximum recommended daily dose. | BX81: No warnings. | BY81: No warnings. | CC81: carmellose sodium | CE81: colloidal anhydrous silica | CL81: vanilla flavour | CP81: glucose monohydrate | CQ81: glycerol | CT81: hypromellose | CU81: isomalt | CW81: lecithin | CX81: magnesium stearate | DB81: microcrystalline cellulose | DQ81: Yes | DR81: Yes | DS81: TR is 0.5 - 30 mg (depression) https://pubmed.ncbi.nlm.nih.gov/12046638/ why the 5mg cut off? Regs? TR 0.5 - 5 mg 547mcg Ca folinate = 500mcg Folinic acid, which is AUST L Limit YSCP have confirmed that the AUST L Limit is 0.5mg Folinic acid can be exceeded for extemporanus compounding, providing the quantity is within the limits below. Clinical Ceiling: Therapeutic metabolic 200–600 mcg/day, Aggressive insulin resistance 600–1,000 mcg/day (600–1,000 mcg/day, Balk EM et al., Diabetes Care, 2007 | DT81: Calcium folinate equivalent folinic acid | DU81: No warnings.
A82: W030029000 | B82: A | C82: 0.009 | D82: Nicotinamide riboside chloride | E82: Nicotinamide riboside chloride (NR) | F82: A3202 | G82: Nicotinamide riboside chloride | H82: - | I82: Nicotinamide riboside chloride | J82: - | K82: - | L82: - | M82: - | N82: - | P82: Nicotinamide riboside chloride | Q82: Nicotinamide riboside chloride | R82: 10 | S82: mg | Z82: - | AB82: 17.4402 | AC82: 2000 | AD82: 150 | AE82: Vitamin | AF82: Export Only, Listed | AG82: 2936.29.00 | AH82: Highly refined organic chemicals and substances | AI82: Not required | AJ82: Not included in any CITES Appendix | AK82: No | AP82: dairy | BA82: soy | BB82: sulfites | BH82: sodium | BI82: 0.09 | BJ82: mg | BM82: sugars | BN82: 0.03 | BO82: mg | BV82: 114469 | BW82: Ribose is a mandatory component of nicotinamide riboside chloride. Only permitted for use in medicines limited to oral routes of administration. The maximum recommended daily dose of the medicine must not provide more than 300 mg of nicotinamide riboside chloride. | BX82: The following warning statement (or words to the same effect) is required on the medicine label: - (NTAKEN12) 'Not to be taken by children under 12 years old.' When the maximum recommended daily dose of the medicine provides greater than 230 mg of nicotinamide riboside chloride, the following warning statement is required on the medicine label:- (PREG) ‘Not recommended for use during pregnancy or lactation’ | BY82: No warnings. | CC82: carmellose sodium | CE82: colloidal anhydrous silica | CL82: vanilla flavour | CP82: glucose monohydrate | CQ82: glycerol | CT82: hypromellose | CW82: lecithin | CX82: magnesium stearate | DB82: microcrystalline cellulose | DQ82: Yes | DR82: Yes | DS82: TR 100-1000 mg https://pubmed.ncbi.nlm.nih.gov/27721479/ agreed tr ul 2000 mg Airhart SE, et al. Nat Commun. 2017;8:12948. Safety demonstrated at 1000 mg theoretically >2000 mg could cause liver toxicity | DT82: Nicotinamide riboside chloride (NR) | DU82: "Not recommended for use by pregnant and lactating women."
A83: W030030000 | B83: A | C83: 0.0102 | D83: Nicotinamide adenine dinucleotide (NAD) | E83: Nicotinamide adenine dinucleotide (NAD) | F83: A633 | G83: Nicotinamide adenine dinucleotide | H83: - | I83: Nadide | J83: - | K83: - | L83: - | M83: - | N83: - | P83: Nadide | Q83: Nadide (NAD) | R83: 10 | S83: mg | AB83: 19.4902 | AC83: 1000 | AD83: 150 | AE83: Vitamin | AF83: Export Only | AG83: 2934.99.00 | AH83: Highly refined organic chemicals and substances | AI83: Not required | AJ83: Not included in any CITES Appendix | AK83: No | AP83: dairy | BA83: soy | BB83: sulfites | BH83: sodium | BI83: 0.1 | BJ83: mg | BM83: sugars | BN83: 0.033 | BO83: mg | BV83: 132341 | BW83: No restrictions. | BX83: No warnings. | BY83: No warnings. | CC83: carmellose sodium | CE83: colloidal anhydrous silica | CL83: vanilla flavour | CP83: glucose monohydrate | CQ83: glycerol | CT83: hypromellose | CW83: lecithin | CX83: magnesium stearate | CZ83: maltodextrin | DB83: microcrystalline cellulose | DQ83: Yes | DR83: Yes | DS83: Oral NAD has poor bioavailability in the gut. Therefore it can create gut upset or convert in gut to nicotinamide and adenosine derivatives that do have upper limits - Confirmed Matt L. 1000mg reasonable upper limit no safety concern. | DT83: Nadide (NAD) | DU83: No warnings.
A84: W040001000 | B84: A | C84: 0.0038 | D84: Iron (as iron bisglycinate) | E84: Iron bisglycinate | F84: A904 | G84: Iron bisglycinate | H84: - | I84: Iron (II) glycinate | J84: - | K84: - | L84: - | M84: - | N84: - | P84: iron (II) glycinate Equiv. Iron (19.0%) | Q84: Iron (II) glycinate equivalent iron (Fe) | R84: 5.26 | S84: mg | T84: 1 | U84: mg | Z84: Please confirm the relevant equivalence? | AA84: equivalent iron (19%) 1mg | AB84: 18.4222 | AC84: 126.3 | AD84: 94.73 | AE84: Mineral | AF84: Export Only, Listed, OTC | AG84: 2922.49.00 | AH84: Highly refined organic chemicals and substances | AI84: Not required | AJ84: Not included in any CITES Appendix | AK84: No | AP84: dairy | BA84: soy | BB84: sulfites | BH84: sodium | BI84: 0.1 | BJ84: mg | BM84: sugars | BN84: 0.31 | BO84: mg | BV84: 107972 | BW84: Only for use in oral medicines. Iron is a mandatory component. When for internal use, the medicine must contain a daily dose of no more than 24 mg of iron. If the divided dosage form contains more than 5 mg of iron per dosage unit (excluding up to 10 mg of iron oxide when used as an excipient), the primary pack must contain no more than 750 mg of iron. In undivided preparations, the primary pack must contain no more than 750 mg of iron (excluding iron oxides when present as an excipient at a quantity of no more than 1%). Divided preparations with a dose of more than 5 mg of elemental iron per dosage unit and more than 250 mg of elemental iron in the total contents of the container are required to have a child resistant closure. | BX84: When for internal use except for iron-containing multivitamin/mineral products indicated for general nutritional support that do not make specific iron-deficiency related claims, the following warning statement is required on the label:- (IRONDEF) 'Not for the treatment of iron deficiency conditions' (or words to that effect). | BY84: No warnings. | CC84: carmellose sodium | CE84: colloidal anhydrous silica | CL84: vanilla flavour | CN84: glacial acetic acid | CP84: glucose monohydrate | CW84: lecithin | CX84: magnesium stearate | CZ84: maltodextrin | DB84: microcrystalline cellulose | DF84: poliglusam | DQ84: Yes | DR84: Yes | DS84: Upper limit of iron is 45 mg. Severity of toxicity is related to the amount of elemental iron and can range from GIT irritation to systemic toxicity. Self limiting nature of advers outcomes low UF https://www.eatforhealth.gov.au/sites/default/files/2022-04/n35-iron_0.pdf What are regs here?TR 15-50 mg of elemental iron AUST L Limit = 24mg iron = 126.3mg of Fe Glycinate, 18mg Fe = 94.73mg Fe Glycinate | DT84: Iron (II) glycinate equivalent iron | DU84: "Not for the treatment of iron deficiency conditions."
A85: W040002000 | B85: A | C85: 0.0026 | D85: Magnesium (as magnesium glycinate) | E85: Magnesium glycinate | F85: A2641 | G85: Magnesium glycinate | H85: - | I85: Magnesium glycinate dihydrate | J85: - | K85: - | L85: - | M85: - | N85: - | P85: Magnesium glycinate dihydrate Equiv. Magnesium (11.7%) | Q85: Magnesium glycinate dihydrate equivalent magnesium (Mg) | R85: 8.55 | S85: mg | T85: 1 | U85: mg | AB85: 18.4552 | AC85: 3000 | AD85: 855 | AE85: Mineral | AF85: Export Only, Listed, OTC, Prescription | AG85: 2922.49.00 | AH85: Highly refined organic chemicals and substances | AI85: Not required | AJ85: Not included in any CITES Appendix | AK85: No | AP85: dairy | BA85: soy | BB85: sulfites | BH85: sodium | BI85: 0.1 | BJ85: mg | BM85: sugars | BN85: 0.31 | BO85: mg | BR85: sugar alcohols | BS85: 1 | BT85: mg | BV85: 108650 | BW85: No restrictions. | BX85: No warnings. | BY85: No warnings. | CC85: carmellose sodium | CE85: colloidal anhydrous silica | CL85: vanilla flavour | CP85: glucose monohydrate | CQ85: glycerol | CT85: hypromellose | CU85: isomalt | CW85: lecithin | CX85: magnesium stearate | DB85: microcrystalline cellulose | DQ85: Yes | DR85: Yes | DS85: UL is 350 mg Mg elemental daily. There are few reports to assist in setting ULs for magnesium, as it has not been shown to produce toxic effects when ingested as naturally occurring magnesium in food. Diarrhoea was selected as the critical endpoint as it is the first sign of excess intake (FNB:IOM 1997). TR is 700-1400 mg of magnesium glycinate (82-164mg Mg elemental) | DT85: Magnesium glycinate dihydrate equivalent magnesium | DU85: No warnings.
A86: W040003000 | B86: A | C86: 0.0022 | D86: Magnesium (as magnesium citrate) | E86: Magnesium citrate | F86: A376 | G86: Magnesium citrate | H86: - | I86: Magnesium citrate | J86: - | K86: - | L86: - | M86: - | N86: - | P86: Magnesium citrate (anhydrous) | Q86: Magnesium citrate equivalent magnesium (Mg) | R86: 6.9 | S86: mg | T86: 1 | U86: mg | Z86: Please confirm the relevant equivalence? | AA86: equivalent magnesium (14.5%) 1mg | AB86: 19.4902 | AC86: 2400 | AD86: 1000 | AE86: Mineral | AF86: Export Only, Listed, OTC, Prescription | AG86: 2918.15.00 | AH86: Mineral and metal ores, rock and sand | AI86: Not required | AJ86: Not included in any CITES Appendix | AK86: No | AP86: dairy | BA86: soy | BB86: sulfites | BH86: sodium | BI86: 0.1 | BJ86: mg | BM86: sugars | BN86: 0.033 | BO86: mg | BV86: 62823 | BW86: No restrictions. | BX86: No warnings. | BY86: No warnings. | CC86: carmellose sodium | CE86: colloidal anhydrous silica | CL86: vanilla flavour | CP86: glucose monohydrate | CQ86: glycerol | CT86: hypromellose | CW86: lecithin | CX86: magnesium stearate | CZ86: maltodextrin | DB86: microcrystalline cellulose | DQ86: Yes | DR86: Yes | DS86: UL is 350 mg Mg elemental daily.T here are few reports to assist in setting ULs for magnesium, as it has not been shown to produce toxic effects when ingested as naturally occurring magnesium in food. Diarrhoea was selected as the critical endpoint as it is the first sign of excess intake (FNB:IOM 1997).TR 900-1800 mg Mag citrate (130-260mg Mg elemental) | DT86: Magnesium citrate equivalent magnesium | DU86: No warnings.
A87: W040004000 | B87: A | C87: 0.0058 | D87: Selenium (as selenomethionine) | E87: Selenium (Selenomethionine) | F87: A247 | G87: Selenomethionine | H87: - | I87: Selenomethionine | J87: - | K87: - | L87: - | M87: - | N87: - | P87: Selenomethionine 5000ppm Equiv. Selenomethionine Equiv. Selenium (40.26% of Selenomethionine) Excipient: Calcium hydrogen phosphate | Q87: Selenomethionine equivalent selenium (Se) | R87: 124.19 | S87: mcg | T87: 50 | U87: mcg | Z87: Please confirm the selenomethionine equivalence, and the name and quantity of any excipients present? | AA87: equivalent selenium (0.5%) 50mcg Excipient Calcium hydrogen phosphate | AB87: 22.8102 | AC87: 375 | AD87: 124.19 | AE87: Mineral | AF87: Export Only, Listed, OTC, Prescription | AG87: 2930.90.00 | AH87: Highly refined organic chemicals and substances | AI87: Not required | AJ87: Not included in any CITES Appendix | AK87: No | AP87: dairy | BA87: soy | BB87: sulfites | BH87: sodium | BI87: 0.11 | BJ87: mg | BM87: sugars | BN87: 0.035 | BO87: mg | BR87: sugar alcohols | BS87: 5.7 | BT87: mg | BV87: 94797 | BW87: Selenium is a mandatory component of Selenomethionine for oral and sublingual use. Oral medicines must not contain more than 150 micrograms of selenium per maximum recommended daily dose. | BX87: When for oral use, the medicine requires the following warning statement on the medicine label: - (SELE) 'This medicine contains selenium which is toxic in high doses. A daily dose of 150 micrograms for adults of selenium from dietary supplements should not be exceeded. | BY87: "This medicine contains selenium which is toxic in high doses. A daily dose of 150 micrograms of selenium for adults from dietary supplements should not be exceeded." | CB87: calcium hydrogen phosphate | CC87: carmellose sodium | CE87: colloidal anhydrous silica | CL87: vanilla flavour | CP87: glucose monohydrate | CQ87: glycerol | CT87: hypromellose | CU87: isomalt | CW87: lecithin | CX87: magnesium stearate | DB87: microcrystalline cellulose | DQ87: Yes | DR87: Yes | DS87: TR 50 -200 mcg day chronic intakes 400 mcg daily selenium (ELEMENTAL SELENIUM) The UL is 400 mcg relates to intakes from food and supplements. There are limited data about toxicity in humans but the most common outcomes are brittleness and loss of hair and nails (Yang et al 1983) as well as gastrointestinal disturbance, skin rash, fatigue, irritability and nervous system abnormalities https://www.eatforhealth.gov.au/sites/default/files/2022-04/n35-selenium_0.pdf AUST L max dose = 150mcg Se elemental/day = 375mcg Selenomethionine. | DT87: Selenomethionine equivalent selenium | DU87: "This medicine contains selenium which is toxic in high doses. A daily dose of 150 micrograms of selenium for adults from dietary supplements should not be exceeded."
A88: W040008000 | B88: A | C88: 0.0048 | D88: Zinc (as zinc citrate) | E88: Zinc citrate | F88: A503 | G88: Zinc citrate | H88: - | I88: Zinc citrate dihydrate | J88: - | K88: - | L88: - | M88: - | N88: - | P88: Zinc citrate dihydrate Equiv. Zinc (32.1%) | Q88: Zinc citrate dihydrate equivalent zinc (Zn) | R88: 6.23 | S88: mg | T88: 2 | U88: mg | Z88: - | AB88: 21.8132 | AC88: 155.8 | AD88: 77.88 | AE88: Mineral | AF88: Export Only, Listed, OTC, Prescription | AG88: 2918.15.00 | AH88: Mineral and metal ores, rock and sand | AI88: Not required | AJ88: Not included in any CITES Appendix | AK88: No | AP88: dairy | BA88: soy | BB88: sulfites | BH88: sodium | BI88: 0.11 | BJ88: mg | BM88: sugars | BN88: 0.036 | BO88: mg | BV88: 101150 | BW88: When used internally, zinc is a mandatory component of zinc citrate. When for internal use, the maximum recommended daily dose must be no more than 50mg of zinc. | BX88: When for internal use and the maximum recommended daily dose is more than 25mg but no more than 50mg of zinc, the medicine requires the following warning statement on the medicine label: - (ZINC) 'WARNING: May be dangerous if taken in large amounts or for a long period.' OR 'WARNING: Contains zinc which may be dangerous if taken in large amounts or for a long period (or words to that effect). | BY88: When contains more than 25mg Zinc: "Contains zinc which may be dangerous if taken in large amounts or for a long period." | CC88: carmellose sodium | CE88: colloidal anhydrous silica | CJ88: ethanol | CL88: vanilla flavour | CP88: glucose monohydrate | CQ88: glycerol | CT88: hypromellose | CW88: lecithin | CX88: magnesium stearate | CZ88: maltodextrin | DB88: microcrystalline cellulose | DQ88: Yes | DR88: Yes | DS88: TR is 15-75 mg of elemental Zinc ( 48mg- 242mg of zinc citrate) General therapeutic supplementation = 15-30 mg, moderate 30-50 mg, upper 50-75 mg 50 mg used immune stress, recurrent infections, IBS, male infertility, inflammatory conditions, 10- 80 mg elemental daily BC AUST L daily limit = 50mg Zn elemental = 155.8mg Zn Citrate dihydrate 77.89mg Zn citrate dihydrate = 25mg Zn elemental. | DT88: Zinc citrate dihydrate equivalent zinc | DU88: "Contains zinc which may be dangerous if taken in large amounts or for a long period."
A89: W040010000 | B89: A | C89: 0.007 | D89: Manganese (as manganese gluconate) | E89: Manganese gluconate | F89: A140 | G89: Manganese gluconate | H89: - | I89: Manganese gluconate | J89: - | K89: - | L89: - | M89: - | N89: - | P89: Manganese gluconate Equiv. Manganese (11.5%) | Q89: Manganese gluconate equivalent manganese (Mn) | R89: 8.7 | S89: mg | T89: 1 | U89: mg | Z89: - | AB89: 19.4502 | AC89: 43.5 | AD89: 8.7 | AE89: Mineral | AF89: Export Only, Listed, OTC, Prescription | AG89: 2918.16.00 | AH89: Mineral and metal ores, rock and sand | AI89: Not required | AJ89: Not included in any CITES Appendix | AK89: No | AP89: dairy | BA89: soy | BB89: sulfites | BH89: sodium | BI89: 0.1 | BJ89: mg | BM89: sugars | BN89: 0.033 | BO89: mg | BR89: sugar alcohols | BS89: 5 | BT89: mg | BV89: 61598 | BW89: No restrictions. | BX89: No warnings. | BY89: No warnings. | CC89: carmellose sodium | CE89: colloidal anhydrous silica | CL89: vanilla flavour | CN89: glacial acetic acid | CP89: glucose monohydrate | CU89: isomalt | CW89: lecithin | CX89: magnesium stearate | DB89: microcrystalline cellulose | DF89: poliglusam | DQ89: Yes | DR89: Yes | DS89: Manganese intake beyond that normally present in food and beverages could represent a health risk, but there are insufficient data to set a UL. UL set at 5 mg elemental. Mn is a neurotoxin so a UL may be prudent https://www.eatforhealth.gov.au/sites/default/files/2022-04/n35-manganese_0.pdf TR is 1-5 mg of manganese (8.3 mg - 42 mg of maganese gluconate) | DT89: Manganese gluconate equivalent manganese | DU89: No warnings.
A90: W040012000 | B90: A | C90: 0.0042 | D90: Calcium d-glucarate | E90: Calcium d-glucarate | F90: A2729 | G90: Calcium d-glucarate | H90: - | I90: Calcium saccharate | J90: - | K90: - | L90: - | M90: - | N90: - | P90: Calcium saccharate Equiv. Calcium (16.1%) | Q90: Calcium saccharate equivalent calcium (Ca) | R90: 5 | S90: mg | T90: 0.805 | U90: mg | Z90: Please confirm the relevant equivalence? | AA90: calcium saccharate 5mg, equivalent calcium (16.1%) 0.81mg | AB90: 18.6602 | AC90: 3000 | AD90: 500 | AE90: Mineral | AF90: - | AG90: 2918.19.00 | AH90: Highly refined organic chemicals and substances | AI90: Not required | AJ90: Not included in any CITES Appendix | AK90: No | AP90: dairy | BA90: soy | BB90: sulfites | BH90: sodium | BI90: 0.1 | BJ90: mg | BM90: sugars | BN90: 0.31 | BO90: mg | BV90: - | BW90: - | BX90: No warnings. | BY90: No warnings. | CC90: carmellose sodium | CE90: colloidal anhydrous silica | CL90: vanilla flavour | CP90: glucose monohydrate | CQ90: glycerol | CT90: hypromellose | CW90: lecithin | CX90: magnesium stearate | CZ90: maltodextrin | DB90: microcrystalline cellulose | DQ90: Yes | DR90: Yes | DS90: TR 200-1000 mg/day https://altmedrev.com/wp-content/uploads/2019/02/v7-4-336.pdf?utm Practical Clinical Ceiling: Therapeutic 1,000–2,000 mg/day, Aggressive detox protocols 2,000–3,000 mg/day | DT90: Calcium saccharate equivalent calcium | DU90: No warnings.
A91: W040013000 | B91: A | C91: 0.008 | D91: Potassium (as potassium citrate) | E91: Potassium citrate | F91: A530 | G91: Potassium citrate | H91: - | I91: Potassium citrate | J91: - | K91: - | L91: - | M91: - | N91: - | P91: Potassium citrate Equiv. Potassium (36.16%) | Q91: Potassium citrate equivalent potassium (K) | R91: 5.53 | S91: mg | T91: 2.001 | U91: mg | Z91: Please confirm the relevant equivalence? | AA91: equivalent potassium (36.2%) 2mg | AB91: 20.5132 | AC91: 100 | AD91: 50 | AE91: Mineral | AF91: Export Only, Listed, OTC, Prescription | AG91: 2918.15.00 | AH91: Mineral and metal ores, rock and sand | AI91: Not required | AJ91: Not included in any CITES Appendix | AK91: No | AP91: dairy | BA91: soy | BB91: sulfites | BD91: potassium | BE91: 2.21 | BF91: mg | BH91: sodium | BI91: 0.11 | BJ91: mg | BM91: sugars | BN91: 0.035 | BO91: mg | BV91: 55432 | BW91: When used as an active ingredient and the medicine is intended as a mineral supplementation, potassium is a mandatory component of potassium citrate. | BX91: No warnings. | BY91: No warnings. | CC91: carmellose sodium | CE91: colloidal anhydrous silica | CL91: vanilla flavour | CP91: glucose monohydrate | CQ91: glycerol | CT91: hypromellose | CW91: lecithin | CX91: magnesium stearate | CZ91: maltodextrin | DB91: microcrystalline cellulose | DQ91: Yes | DR91: Yes | DS91: No ULs have been set for potassium from dietary sources. AI is 3,800 mg https://www.eatforhealth.gov.au/sites/default/files/2022-04/n35-potassium_0.pdf | DT91: Potassium citrate equivalent potassium | DU91: No warnings.
A92: W040016000 | B92: A | C92: 0.0022 | D92: Copper (as copper gluconate) | E92: Copper gluconate | F92: A353 | G92: Copper gluconate | H92: - | I92: Copper gluconate | J92: - | K92: - | L92: - | M92: - | N92: - | P92: Copper gluconate Equiv. Copper (14%) | Q92: Copper gluconate equivalent copper (Cu) | R92: 7.14 | S92: mg | T92: 0.9996 | U92: mg | Z92: - | AB92: 20.8142 | AC92: 35.7 | AD92: 7.14 | AE92: Mineral | AF92: Export Only, Listed, OTC, Prescription | AG92: 2918.16.00 | AH92: Mineral and metal ores, rock and sand | AI92: Not required | AJ92: Not included in any CITES Appendix | AK92: No | AP92: dairy | BA92: soy | BB92: sulfites | BH92: sodium | BI92: 0.11 | BJ92: mg | BM92: sugars | BN92: 0.035 | BO92: mg | BR92: sugar alcohols | BS92: 5.85 | BT92: mg | BV92: 52985 | BW92: Copper is a mandatory component of copper gluconate. The percentage of copper from copper gluconate should be calculated based on the molecular weight of copper gluconate. When for internal use the maximum daily dose must not contain more than 5 mg of copper. When for other than internal use, the concentration of copper compounds must be no more than 5%. | BX92: No warnings. | BY92: No warnings. | CC92: carmellose sodium | CE92: colloidal anhydrous silica | CJ92: ethanol | CL92: vanilla flavour | CP92: glucose monohydrate | CQ92: glycerol | CT92: hypromellose | CU92: isomalt | CW92: lecithin | CX92: magnesium stearate | DB92: microcrystalline cellulose | DQ92: Yes | DR92: Yes | DS92: Upper level of 10 mg Cu Elemental daily assigned. https://www.eatforhealth.gov.au/sites/default/files/2022-04/n35-copper_0.pdf TR 1-6mg copper daily UL for adults 10 mg daily elemental copper Happy with TR 1-5 mg of elemental copper | DT92: Copper gluconate equivalent copper | DU92: No warnings.
A93: W040017000 | B93: A | C93: 0.007 | D93: Calcium hydroxyapatite | E93: Calcium hydroxyapatite | F93: A331 | G93: Calcium hydroxyapatite | H93: - | I93: Hydroxyapatite | J93: - | K93: - | L93: - | M93: - | N93: - | P93: Hydroxyapatite Equiv. Calcium (22%) | Q93: Hydroxyapatite equivalent calcium (Ca) | R93: 10 | S93: mg | T93: 2.2 | U93: mg | Z93: Please confirm the relevant equivalence? | AA93: equivalent calcium (22%) 2.2mg | AB93: 22.5602 | AC93: 2500 | AD93: 500 | AE93: Mineral | AF93: Export Only, Listed, OTC, Prescription | AG93: 2835.26.00 | AH93: Mineral and metal ores, rock and sand | AI93: Not required | AJ93: Not included in any CITES Appendix | AK93: No | AP93: dairy | BA93: soy | BB93: sulfites | BH93: sodium | BI93: 0.12 | BJ93: mg | BM93: sugars | BN93: 0.038 | BO93: mg | BV93: 71139 | BW93: No restrictions. | BX93: No warnings. | BY93: No warnings. | CC93: carmellose sodium | CE93: colloidal anhydrous silica | CL93: vanilla flavour | CP93: glucose monohydrate | CQ93: glycerol | CT93: hypromellose | CW93: lecithin | CX93: magnesium stearate | CZ93: maltodextrin | DB93: microcrystalline cellulose | DQ93: Yes | DR93: Yes | DS93: Calcium UL is set cautiously at 2,500 mg daily. Concern about kidney stones, competition with absorption from other mineralshttps://www.eatforhealth.gov.au/sites/default/files/2022-04/n35-calcium_0.pdf TR 100-2000 mg/day of calcium, equiv BC | DT93: Hydroxyapatite equivalent calcium | DU93: No warnings.
A94: W130001000 | B94: A | C94: 0.0029 | D94: GABA (gamma-aminobutyric acid) | E94: GABA | F94: A594 | G94: Gamma amino butyric acid | H94: - | I94: Aminobutyric acid | J94: - | K94: - | L94: - | M94: - | N94: - | P94: Aminobutyric acid | Q94: Aminobutyric acid | R94: 5.05 | S94: mg | Z94: - | AB94: 18.2552 | AC94: 800 | AD94: 150 | AE94: Synthetic | AF94: Export Only | AG94: 2922.49.00 | AH94: Highly refined organic chemicals and substances | AI94: Not required | AJ94: Not included in any CITES Appendix | AK94: No | AP94: dairy | BA94: soy | BB94: sulfites | BH94: sodium | BI94: 0.1 | BJ94: mg | BM94: sugars | BN94: 0.31 | BO94: mg | BR94: sugar alcohols | BS94: 1.5 | BT94: mg | BV94: 105269 | BW94: No restrictions. | BX94: No warnings. | BY94: No warnings. | CC94: carmellose sodium | CE94: colloidal anhydrous silica | CL94: vanilla flavour | CP94: glucose monohydrate | CQ94: glycerol | CT94: hypromellose | CU94: isomalt | CW94: lecithin | CX94: magnesium stearate | DB94: microcrystalline cellulose | DQ94: Yes | DR94: Yes | DS94: TR 250 mg - 1500 mg daily TBR Higher supplement range 300–800 mg (YSCP). | DT94: Aminobutyric acid | DU94: No warnings.
A95: W130002000 | B95: A | C95: 0.0102 | D95: 5-HTP (5-hydroxytryptophan) | E95: 5-HTP | F95: A608 | G95: Griffonia simplicifolia | H95: Griffonia simplicifolia | I95: - | J95: seed | K95: extract dry concentrate standardised | L95: 20:1 | M95: 70% ethanol:water | N95: 98% 5-hydroxytryptophan | O95: - | P95: Griffonia simplicifolia seed extract dry conc std 20:1, 70% E:W Equiv. Griffonia simplicifolia dry seed Equiv. 5-hydroxytryptophan (98%) | Q95: Griffonia simplicifolia seed extract equivalent Griffonia simplicifolia dry seed equivalent 5-hydroxytryptophan | R95: 10 | S95: mg | T95: 200 | U95: mg | V95: 9.8 | W95: mg | Z95: Please confirm the Latin binomial, plant part, preparation type, extract ratio, extraction solvents, standardisation, and the name and quantity of any excipients present? | AA95: Griffonia simplicifolia seed extract dry concentrate standardised 20:1 70% ethanol:water 98% 5-hydroxytryptophan No excipients | AB95: 19.4852 | AC95: 600 | AD95: 100 | AE95: Herb | AF95: - | AG95: 1302.19.90 | AH95: Highly refined organic chemicals and substances | AI95: Not required | AJ95: Not included in any CITES Appendix | AK95: No | AP95: dairy | BA95: soy | BB95: sulfites | BH95: sodium | BI95: 0.1 | BJ95: mg | BM95: sugars | BN95: 0.033 | BO95: mg | BV95: - | BW95: - | BX95: No warnings. | BY95: No warnings. | CC95: carmellose sodium | CE95: colloidal anhydrous silica | CL95: vanilla flavour | CP95: glucose monohydrate | CQ95: glycerol | CT95: hypromellose | CW95: lecithin | CX95: magnesium stearate | DB95: microcrystalline cellulose | DQ95: Yes | DR95: Yes | DS95: TR 100- 300 mg daily, trials at higher levels of 3250 mg anxiety +800 mg, migraine = 600 mg https://altmedrev.com/wp-content/uploads/2019/02/v7-4-336.pdf?utm | DT95: Griffonia simplicifolia seed extract (20:1) equivalent Griffonia simplicifolia dry seed equivalent 5-hydroxytryptophan (98%) | DU95: No warnings.
A96: W130003000 | B96: A | C96: 0.0054 | D96: L-theanine | E96: L-theanine | F96: A631 | G96: L-theanine | H96: - | I96: Theanine | J96: - | K96: - | L96: - | M96: - | N96: - | P96: Theanine | Q96: Theanine | R96: 5 | S96: mg | Z96: - | AB96: 19.8102 | AC96: 600 | AD96: 200 | AE96: Amino acid | AF96: Export Only, Listed | AG96: 2922.49.00 | AH96: Highly refined organic chemicals and substances | AI96: Not required | AJ96: Not included in any CITES Appendix | AK96: No | AP96: dairy | BA96: soy | BB96: sulfites | BH96: sodium | BI96: 0.1 | BJ96: mg | BM96: sugars | BN96: 0.033 | BO96: mg | BV96: 104158 | BW96: Only to be used in a medicine where Trans Chem Pty Ltd (Client ID 21878), who applied to have the ingredient included in this Determination, is the sponsor of the medicine or has given written authorisation to the sponsor of a medicine to include the ingredient in the medicine. This paragraph ceases to be a requirement for this ingredient after 1 March 2026. The route of administration for medicines that contain theanine must be limited to oral. The maximum recommended daily dose of the medicine must not provide more than 450 mg of theanine. | BX96: The following warning statements (or words to the same effect) are required on the medicine label:- (PREGNT) 'Not recommended for use by pregnant and lactating women'; and- (ADULT) 'Adults only'. | BY96: No warnings. | CC96: carmellose sodium | CE96: colloidal anhydrous silica | CL96: vanilla flavour | CP96: glucose monohydrate | CQ96: glycerol | CT96: hypromellose | CW96: lecithin | CX96: magnesium stearate | CZ96: maltodextrin | DB96: microcrystalline cellulose | DQ96: Yes | DR96: Yes | DS96: TR 100-400 mg, doses of 600 - 1200 mg have been used. it is recommended that the maximum dosage not exceed 600 mg in a six-hour period or 1,200 mg in a 24-hour period. https://pmc.ncbi.nlm.nih.gov/articles/PMC11811612/?utm TR 100-400 mg daily | DT96: Theanine | DU96: "Not recommended for use by pregnant and lactating women."
A97: W130004000 | B97: A | C97: 0.0074 | D97: L-arginine | E97: L-arginine | F97: A405 | G97: L-arginine | H97: - | I97: Arginine | J97: - | K97: - | L97: - | M97: - | N97: - | P97: Arginine | Q97: Arginine | R97: 5 | S97: mg | Z97: - | AB97: 18.4602 | AC97: 2000 | AD97: 750 | AE97: Amino acid | AF97: Export Only, Listed, OTC, Prescription | AG97: 2925.29.00 or 2922.49.00 | AH97: Highly refined organic chemicals and substances | AI97: Not required | AJ97: Not included in any CITES Appendix | AK97: No | AP97: dairy | BA97: soy | BB97: sulfites | BH97: sodium | BI97: 0.1 | BJ97: mg | BM97: sugars | BN97: 0.31 | BO97: mg | BV97: 52216 | BW97: Only for use in topical medicines for dermal application. | BX97: The medicine requires the following warning statement on the medicine label:- (ARGIN1) 'This medicine contains arginine and is intended to be applied to the skin only and not to the mucosa - vagina or rectum.' | BY97: No warnings. | CC97: carmellose sodium | CE97: colloidal anhydrous silica | CL97: vanilla flavour | CP97: glucose monohydrate | CQ97: glycerol | CT97: hypromellose | CW97: lecithin | CX97: magnesium stearate | CZ97: maltodextrin | DB97: microcrystalline cellulose | DQ97: Yes | DR97: Yes | DS97: Doses <30 gm are well tolerated clinical trials use 5-30 g/day BC Lowest observed adverse effect at 42 gm daily Rec Dose - Reduced from 1500 for machine efficiency and pod size | DT97: Arginine | DU97: No warnings.
A98: W130005000 | B98: A | C98: 0.0064 | D98: L-citrulline | E98: L-citrulline | F98: A2736 | G98: L-citrulline | H98: - | I98: Citrulline | J98: - | K98: - | L98: - | M98: - | N98: - | P98: Citrulline | Q98: Citrulline | R98: 5 | S98: mg | Z98: - | AB98: 19.81 | AC98: 2000 | AD98: 750 | AE98: Amino acid | AF98: Export Only, Listed, OTC | AG98: 2924.19.00 or 2922.49.00 | AH98: Highly refined organic chemicals and substances | AI98: Not required | AJ98: Not included in any CITES Appendix | AK98: No | AP98: dairy | BA98: soy | BB98: sulfites | BH98: sodium | BI98: 0.11 | BJ98: mg | BM98: sugars | BN98: 0.035 | BO98: mg | BV98: 121976 | BW98: Only permitted for use in medicines: (a) limited to oral routes of administration; and (b) when the maximum recommended daily dose does not provide more than 6 g of citrulline. | BX98: No warnings. | BY98: No warnings. | CE98: colloidal anhydrous silica | CJ98: ethanol | CL98: vanilla flavour | CQ98: glycerol | CT98: hypromellose | CX98: magnesium stearate | CZ98: maltodextrin | DB98: microcrystalline cellulose | DQ98: Yes | DR98: Yes | DS98: TR is 1.5-6 gm daily https://pmc.ncbi.nlm.nih.gov/articles/PMC6369322/?utm | DT98: Citrulline | DU98: No warnings.
A99: W130006000 | B99: A | C99: 0.0035 | D99: L-tyrosine | E99: L-tyrosine | F99: A404 | G99: L-tyrosine | H99: - | I99: Tyrosine | J99: - | K99: - | L99: - | M99: - | N99: - | P99: Tyrosine | Q99: Tyrosine | R99: 5 | S99: mg | Z99: - | AB99: 20.5102 | AC99: 2000 | AD99: 500 | AE99: Amino acid | AF99: Export Only, Listed, OTC, Prescription | AG99: 2922.50.00 or 2922.49.00 | AH99: Highly refined organic chemicals and substances | AI99: Not required | AJ99: Not included in any CITES Appendix | AK99: No | AP99: dairy | BA99: soy | BB99: sulfites | BH99: sodium | BI99: 0.11 | BJ99: mg | BM99: sugars | BN99: 0.035 | BO99: mg | BV99: 94212 | BW99: No restrictions. | BX99: No warnings. | BY99: No warnings. | CC99: carmellose sodium | CE99: colloidal anhydrous silica | CL99: vanilla flavour | CP99: glucose monohydrate | CQ99: glycerol | CT99: hypromellose | CW99: lecithin | CX99: magnesium stearate | CZ99: maltodextrin | DB99: microcrystalline cellulose | DQ99: Yes | DR99: Yes | DS99: 100- 2000 mg (divided doses). 1000 mg first thing in am, 9gm daily for narcolepsy BC Agreed TR 500-1000mg | DT99: Tyrosine | DU99: No warnings.
A100: W140002000 | B100: A | C100: 0.0035 | D100: Bromelain | E100: Bromelain | F100: A2719 | G100: Bromelains | H100: - | I100: Bromelains | J100: - | K100: - | L100: - | M100: - | N100: - | O100: 400 GDU/g 6000 PU/g | P100: Bromelains (from Pineapple) 400GDU/g 6000 PU/g Excipient: Glucose (from corn) 75% | Q100: Bromelains (from Pineapple) equivalent bromelains | R100: 5 | S100: mg | T100: 30 | U100: PU | Z100: - | AB100: 18.81 | AC100: 2000 | AD100: 400 | AE100: Enzyme | AF100: Export Only, Listed, OTC, Prescription | AG100: 3507.90.00 | AH100: Highly refined organic chemicals and substances | AI100: Not required | AJ100: Not included in any CITES Appendix | AK100: No | AP100: dairy | BA100: soy | BB100: sulfites | BH100: sodium | BI100: 0.11 | BJ100: mg | BM100: sugars | BN100: 0.035 | BO100: mg | BV100: 52421 | BW100: May be derived from either the stem or fruit of the pineapple (Ananas comosus). | BX100: No warnings. | BY100: No warnings. | CC100: carmellose sodium | CE100: colloidal anhydrous silica | CL100: vanilla flavour | CO100: glucose | CP100: glucose monohydrate | CQ100: glycerol | CT100: hypromellose | CW100: lecithin | CX100: magnesium stearate | CZ100: maltodextrin | DB100: microcrystalline cellulose | DQ100: Yes | DR100: Yes | DS100: TR 200 - 2000 mg day https://pmc.ncbi.nlm.nih.gov/articles/PMC538506/ | DT100: Bromelains (from Pineapple, mg) equivalent bromelains (PU) | DU100: No warnings.
...

Sheet Nof1 Cost Calculator
A1: Nof 1 Cost Calculator | E1: Number of Pods | F1: 28 | H1: CURRENT AT DATE: | I1: 46083 | J1: REVISION No: | K1: 15
A2: Required for formulation | D2: Printed on label
A3: TSI Ingredients Library Summary Code | B3: Granule Price $AUD/granule | C3: Common Name (TSI Global granule name) | D3: Label Expression (To be printed on box back label) | E3: description | F3: enter amount of extract or active here | G3: Unit of Measure | H3: unit of measure (S) per granule | I3: Number of Granules | J3: Total Cost | K3: Comments | L3: equivalent (mg) | M3: standardised marker (mg) | N3: second standardised marker (mg)
A4: 31P0017 | B4: =VLOOKUP(A4,' Ingredients Library'!$A$4:$AK$112,3,FALSE) -> 0.12 | C4: Aluminium Cup | J4: =B4*$F$1 -> 3.36
A5: 31M0133 | B5: =VLOOKUP(A5,' Ingredients Library'!$A$4:$AK$112,3,FALSE) -> 0.02 | C5: Black Foil Lid Custom | J5: =B5*$F$1 -> 0.56
A6: W010001000 | B6: =VLOOKUP(A6,' Ingredients Library'!$A$4:$AK$112,3,FALSE) -> 0.0096 | C6: =VLOOKUP(A6,' Ingredients Library'!$A$4:$AK$112,5,FALSE) -> American ginseng | D6: =VLOOKUP(A6,' Ingredients Library'!$A$4:$AK$112,17,FALSE) -> Panax quinquefolius (American ginseng) root extract equivalent Panax quinquefolius dry root equivalent ginsenosides | E6: Panax quinquefolius (American ginseng) root extract 4:1 equivalent ginsenosides 9% | G6: mg | H6: 10 | I6: =F6/H6 -> 0 | J6: =(I6*B6)*$F$1 -> 0 | L6: =F6*4 -> 0 | M6: =F6*0.09 -> 0
A7: W010003000 | B7: =VLOOKUP(A7,' Ingredients Library'!$A$4:$AK$112,3,FALSE) -> 0.0122 | C7: =VLOOKUP(A7,' Ingredients Library'!$A$4:$AK$112,5,FALSE) -> Ashwagandha | D7: =VLOOKUP(A7,' Ingredients Library'!$A$4:$AK$112,17,FALSE) -> Withania somnifera (Ashwagandha) root extract equivalent Withania somnifera dry root equivalent withanolides | E7: Withania somnifera (Ashwagandha) root extract 10:1 equivalent withanolides 2.5% | G7: mg | H7: 10 | I7: =F7/H7 -> 0 | J7: =(I7*B7)*$F$1 -> 0 | L7: =F7*10 -> 0 | M7: =F7*0.025 -> 0
A8: W010004000 | B8: =VLOOKUP(A8,' Ingredients Library'!$A$4:$AK$112,3,FALSE) -> 0.0022 | C8: =VLOOKUP(A8,' Ingredients Library'!$A$4:$AK$112,5,FALSE) -> Astragalus | D8: =VLOOKUP(A8,' Ingredients Library'!$A$4:$AK$112,17,FALSE) -> Astragalus membranaceus (Astragalus) root extract equivalent Astragalus membranaceus dry root | E8: Astragalus membranaceus (Astragalus) root extract 20:1 | G8: mg | H8: 10 | I8: =F8/H8 -> 0 | J8: =(I8*B8)*$F$1 -> 0 | L8: =F8*20 -> 0
A9: W010006000 | B9: =VLOOKUP(A9,' Ingredients Library'!$A$4:$AK$112,3,FALSE) -> 0.0051 | C9: =VLOOKUP(A9,' Ingredients Library'!$A$4:$AK$112,5,FALSE) -> Siberian ginseng | D9: =VLOOKUP(A9,' Ingredients Library'!$A$4:$AK$112,17,FALSE) -> Eleutherococcus senticosus (Siberian ginseng) root extract equivalent Eleutherococcus senticosus dry root equivalent eleutherosides | E9: Eleutherococcus senticosus (Siberian ginseng) root extract 15:1 equivalent eleutherosides 8% | G9: mg | H9: 10 | I9: =F9/H9 -> 0 | J9: =(I9*B9)*$F$1 -> 0 | L9: =F9*15 -> 0 | M9: =F9*0.08 -> 0
A10: W010007000 | B10: =VLOOKUP(A10,' Ingredients Library'!$A$4:$AK$112,3,FALSE) -> 0.0038 | C10: =VLOOKUP(A10,' Ingredients Library'!$A$4:$AK$112,5,FALSE) -> Green Tea (EGCG) | D10: =VLOOKUP(A10,' Ingredients Library'!$A$4:$AK$112,17,FALSE) -> Camellia sinensis (Green tea) leaf extract equivalent Camellia sinensis dry leaf equivalent EGCG equivalent caffeine | E10: Camellia sinensis (Green tea) leaf extract 15:1 equivalent EGCG 50% equiuvalent caffeine 1% | G10: mg | H10: 10 | I10: =F10/H10 -> 0 | J10: =(I10*B10)*$F$1 -> 0 | L10: =F10*15 -> 0 | M10: =F10*0.5 -> 0 | N10: =F10*0.01 -> 0
A11: W010008000 | B11: =VLOOKUP(A11,' Ingredients Library'!$A$4:$AK$112,3,FALSE) -> 0.0051 | C11: =VLOOKUP(A11,' Ingredients Library'!$A$4:$AK$112,5,FALSE) -> Garlic | D11: =VLOOKUP(A11,' Ingredients Library'!$A$4:$AK$112,17,FALSE) -> Allium sativum (Garlic) bulb extract equivalent Allium sativum dry bulb | E11: Allium sativum (Garlic) bulb extract 20:1 | G11: mg | H11: 10 | I11: =F11/H11 -> 0 | J11: =(I11*B11)*$F$1 -> 0 | L11: =F11*20 -> 0
A12: W010009000 | B12: =VLOOKUP(A12,' Ingredients Library'!$A$4:$AK$112,3,FALSE) -> 0.0035 | C12: =VLOOKUP(A12,' Ingredients Library'!$A$4:$AK$112,5,FALSE) -> Grape Seed | D12: =VLOOKUP(A12,' Ingredients Library'!$A$4:$AK$112,17,FALSE) -> Vitis vinifera (Grape) seed extract equivalent Vitis vinifera dry seed equivalent proanthocyanidins | E12: Vitis vinifera (Grape) seed extract 120:1 equivalent proanthocyanidins 92% | G12: mg | H12: 10 | I12: =F12/H12 -> 0 | J12: =(I12*B12)*$F$1 -> 0 | L12: =F12*120 -> 0 | M12: =F12*0.92 -> 0
A13: W010011000 | B13: =VLOOKUP(A13,' Ingredients Library'!$A$4:$AK$112,3,FALSE) -> 0.0083 | C13: =VLOOKUP(A13,' Ingredients Library'!$A$4:$AK$112,5,FALSE) -> Lutein | D13: =VLOOKUP(A13,' Ingredients Library'!$A$4:$AK$112,17,FALSE) -> Tagetes erecta (Aztec marigold) flower extract equivalent Tagetes erecta dry flower equivalent lutein | E13: Lutein (from Tagetes erecta (Aztec marigold) flower extract 4:1 | G13: mg | H13: 0.5 | I13: =F13/H13 -> 0 | J13: =(I13*B13)*$F$1 -> 0
A14: W010012000 | B14: =VLOOKUP(A14,' Ingredients Library'!$A$4:$AK$112,3,FALSE) -> 0.0093 | C14: =VLOOKUP(A14,' Ingredients Library'!$A$4:$AK$112,5,FALSE) -> Zeaxanthin | D14: =VLOOKUP(A14,' Ingredients Library'!$A$4:$AK$112,17,FALSE) -> Zeaxanthin | E14: Zeaxanthin | G14: mg | H14: 1 | I14: =F14/H14 -> 0 | J14: =(I14*B14)*$F$1 -> 0
A15: W010013000 | B15: =VLOOKUP(A15,' Ingredients Library'!$A$4:$AK$112,3,FALSE) -> 0.0048 | C15: =VLOOKUP(A15,' Ingredients Library'!$A$4:$AK$112,5,FALSE) -> Milk thistle | D15: =VLOOKUP(A15,' Ingredients Library'!$A$4:$AK$112,17,FALSE) -> Silybum marianum (Milk thistle) fruit extract equivalent Silybum marianum dry fruit equivalent silymarin | E15: Silybum marianum (Milk thistle) fruit extract 70:1 equivalent silymarin 80% | G15: mg | H15: 10 | I15: =F15/H15 -> 0 | J15: =(I15*B15)*$F$1 -> 0 | L15: =F15*70 -> 0 | M15: =F15*0.8 -> 0
A16: W010017000 | B16: =VLOOKUP(A16,' Ingredients Library'!$A$4:$AK$112,3,FALSE) -> 0.0029 | C16: =VLOOKUP(A16,' Ingredients Library'!$A$4:$AK$112,5,FALSE) -> Pine Bark (Pycnogenol) | D16: =VLOOKUP(A16,' Ingredients Library'!$A$4:$AK$112,17,FALSE) -> Pinus massoniana (Pine) bark extract equivalent Pinus massoniana dry bark equivalent procyanidins | E16: Pycnogenol Pinus massoniana (Pine) bark extract 50:1 equivalent procyanidins 60% | G16: mg | H16: 5 | I16: =F16/H16 -> 0 | J16: =(I16*B16)*$F$1 -> 0 | L16: =F16*50 -> 0 | M16: =F16*0.6 -> 0
A17: W010018000 | B17: =VLOOKUP(A17,' Ingredients Library'!$A$4:$AK$112,3,FALSE) -> 0.0045 | C17: =VLOOKUP(A17,' Ingredients Library'!$A$4:$AK$112,5,FALSE) -> Pomegranate | D17: =VLOOKUP(A17,' Ingredients Library'!$A$4:$AK$112,17,FALSE) -> Punica granatum (Pomegranate) hull extract equivalent Punica granatum dry hull equivalent ellagic acid | E17: Punica granatum (Pomegranate) hull extract 18:1 equivalent ellagic acid 40% | G17: mg | H17: 10 | I17: =F17/H17 -> 0 | J17: =(I17*B17)*$F$1 -> 0 | L17: =F17*18 -> 0 | M17: =F17*0.4 -> 0
A18: W010019000 | B18: =VLOOKUP(A18,' Ingredients Library'!$A$4:$AK$112,3,FALSE) -> 0.0144 | C18: =VLOOKUP(A18,' Ingredients Library'!$A$4:$AK$112,5,FALSE) -> Resveratrol | D18: =VLOOKUP(A18,' Ingredients Library'!$A$4:$AK$112,17,FALSE) -> Resveratrol | E18: Resveratrol | G18: mg | H18: 10 | I18: =F18/H18 -> 0 | J18: =(I18*B18)*$F$1 -> 0
A19: W010020000 | B19: =VLOOKUP(A19,' Ingredients Library'!$A$4:$AK$112,3,FALSE) -> 0.0122 | C19: =VLOOKUP(A19,' Ingredients Library'!$A$4:$AK$112,5,FALSE) -> Rhodiola rosea (Rose Root) | D19: =VLOOKUP(A19,' Ingredients Library'!$A$4:$AK$112,17,FALSE) -> Rhodiola rosea (Rose root) root extract equivalent Rhodiola rosea dry root equivalent rosavins equivalent salidroside | E19: Rhodiola rosea (Rose root) root extract 10:1 equivalent rosavins 3% equivalent salidroside 1% | G19: mg | H19: 10 | I19: =F19/H19 -> 0 | J19: =(I19*B19)*$F$1 -> 0 | L19: =F19*10 -> 0 | M19: =F19*0.03 -> 0 | N19: =F19*0.01 -> 0
A20: W010022000 | B20: =VLOOKUP(A20,' Ingredients Library'!$A$4:$AK$112,3,FALSE) -> 0.0016 | C20: =VLOOKUP(A20,' Ingredients Library'!$A$4:$AK$112,5,FALSE) -> Boswellia (Frankincense) | D20: =VLOOKUP(A20,' Ingredients Library'!$A$4:$AK$112,17,FALSE) -> Boswellia serrata (Frankincense) sap resin extract equivalent Boswellia serrata dry sap resin equivalent boswellic acids | E20: Boswellia serrata (Frankincense) sap resin extract 6:1 equivalent boswellic acids 60% | G20: mg | H20: 5 | I20: =F20/H20 -> 0 | J20: =(I20*B20)*$F$1 -> 0 | L20: =F20*6 -> 0 | M20: =F20*0.6 -> 0
A21: W010023000 | B21: =VLOOKUP(A21,' Ingredients Library'!$A$4:$AK$112,3,FALSE) -> 0.0026 | C21: =VLOOKUP(A21,' Ingredients Library'!$A$4:$AK$112,5,FALSE) -> Betaine (Trimethylglycine) | D21: =VLOOKUP(A21,' Ingredients Library'!$A$4:$AK$112,17,FALSE) -> Betaine | E21: Betaine | G21: mg | H21: 5 | I21: =F21/H21 -> 0 | J21: =(I21*B21)*$F$1 -> 0
A22: W010024000 | B22: =VLOOKUP(A22,' Ingredients Library'!$A$4:$AK$112,3,FALSE) -> 0.0054 | C22: =VLOOKUP(A22,' Ingredients Library'!$A$4:$AK$112,5,FALSE) -> Licorice DGL | D22: =VLOOKUP(A22,' Ingredients Library'!$A$4:$AK$112,17,FALSE) -> Glycyrrhiza glabra (Liquorice) root extract equivalent Glycyrrhiza glabra dry root equivalent glycyrrhizin | E22: DGL Glycyrrhiza glabra (Liquorice) root extract 8:1 equivalent glycyrrhizin 1.5% | G22: mg | H22: 10 | I22: =F22/H22 -> 0 | J22: =(I22*B22)*$F$1 -> 0 | L22: =F22*8 -> 0 | M22: =F22*0.015 -> 0
A23: W010025000 | B23: =VLOOKUP(A23,' Ingredients Library'!$A$4:$AK$112,3,FALSE) -> 0.008 | C23: =VLOOKUP(A23,' Ingredients Library'!$A$4:$AK$112,5,FALSE) -> Dong quai | D23: =VLOOKUP(A23,' Ingredients Library'!$A$4:$AK$112,17,FALSE) -> Angelica polymorpha (Dong quai) root extract equivalent Angelica polymorpha dry root equivalent ligustilide | E23: Angelica polymorpha (Dong quai) root extract 2:1 equivalent ligustilide 0.25% | G23: mg | H23: 10 | I23: =F23/H23 -> 0 | J23: =(I23*B23)*$F$1 -> 0 | L23: =F23*2 -> 0 | M23: =F23*0.0025 -> 0
A24: W010026000 | B24: =VLOOKUP(A24,' Ingredients Library'!$A$4:$AK$112,3,FALSE) -> 0.0074 | C24: =VLOOKUP(A24,' Ingredients Library'!$A$4:$AK$112,5,FALSE) -> Berberine HCL (Indian Barberry) | D24: =VLOOKUP(A24,' Ingredients Library'!$A$4:$AK$112,17,FALSE) -> Berberis aristata (Indian barberry) root extract equivalent Berberis aristata dry root equivalent berberine hydrochloride | E24: Beberine HCL | G24: mg | H24: 10 | I24: =F24/H24 -> 0 | J24: =(I24*B24)*$F$1 -> 0
A25: W010028000 | B25: =VLOOKUP(A25,' Ingredients Library'!$A$4:$AK$112,3,FALSE) -> 0.0048 | C25: =VLOOKUP(A25,' Ingredients Library'!$A$4:$AK$112,5,FALSE) -> Maca (fruit) | D25: =VLOOKUP(A25,' Ingredients Library'!$A$4:$AK$112,17,FALSE) -> Lepidium meyenii (Maca) fruit extract equivalent Lepidium meyenii dry fruit equivalent glucosinates | E25: Lepidium meyenii (Maca) fruit extract 18:1 equivalent glucosinates 0.6% | G25: mg | H25: 10 | I25: =F25/H25 -> 0 | J25: =(I25*B25)*$F$1 -> 0 | L25: =F25*18 -> 0 | M25: =F25*0.006 -> 0
A26: W010029000 | B26: =VLOOKUP(A26,' Ingredients Library'!$A$4:$AK$112,3,FALSE) -> 0.0038 | C26: =VLOOKUP(A26,' Ingredients Library'!$A$4:$AK$112,5,FALSE) -> Turmeric (Curcumin) | D26: =VLOOKUP(A26,' Ingredients Library'!$A$4:$AK$112,17,FALSE) -> Curcuma longa (Turmeric) root extract equivalent Curcuma longa dry root equivalent curcuminoids | E26: Curcuma longa (Turmeric) root extract 25:1 equivalent curcuminoids 40% | G26: mg | H26: 10 | I26: =F26/H26 -> 0 | J26: =(I26*B26)*$F$1 -> 0 | L26: =F26*25 -> 0 | M26: =F26*0.4 -> 0
A27: W010030000 | B27: =VLOOKUP(A27,' Ingredients Library'!$A$4:$AK$112,3,FALSE) -> 0.0086 | C27: =VLOOKUP(A27,' Ingredients Library'!$A$4:$AK$112,5,FALSE) -> Fenugreek | D27: =VLOOKUP(A27,' Ingredients Library'!$A$4:$AK$112,17,FALSE) -> Trigonella foenum-graecum (Fenugreek) seed extract equivalent Trigonella foenum-graecum dry seed equivalent saponins | E27: Trigonella foenum-graecum (Fenugreek) seed extract 50:1 equivalent saponins 50% | G27: mg | H27: 5 | I27: =F27/H27 -> 0 | J27: =(I27*B27)*$F$1 -> 0 | L27: =F27*50 -> 0 | M27: =F27*0.5 -> 0
A28: W010031000 | B28: =VLOOKUP(A28,' Ingredients Library'!$A$4:$AK$112,3,FALSE) -> 0.0045 | C28: =VLOOKUP(A28,' Ingredients Library'!$A$4:$AK$112,5,FALSE) -> Quercetin | D28: =VLOOKUP(A28,' Ingredients Library'!$A$4:$AK$112,17,FALSE) -> Quercetin dihydrate equivalent quercetin | E28: Quercetin | G28: mg | H28: 10 | I28: =F28/H28 -> 0 | J28: =(I28*B28)*$F$1 -> 0
